Workbook
Name ————: #REF!,#REF!,#REF!,#REF!,#REF!,#REF!,#REF!,#REF!,#REF!,#REF!,#REF!,#REF!
Name \0: #REF!
Name \00: #REF!
Name \1: #N/A
Name \a: #N/A
Name \b: #N/A
Name \C: #REF!
Name \d: #REF!
Name \e: #REF!
Name \f: #N/A
Name \i: #REF!
Name \J: #REF!
Name \m: #REF!
Name \p: #REF!
Name \q: #REF!
Name \s: #REF!
Name \t: #REF!
Name \u: #REF!
Name \x: #REF!
Name \z: #REF!
Name _: #N/A
Name __: #N/A
Name _______: #REF!
Name ____________________________________________________d100000: #REF!
Name ___________________________________________________d100000: #REF!
Name __________________________________________________d100000: #REF!
Name _________________________________________________d100000: #REF!
Name ________________________________________________d100000: #REF!
Name _______________________________________________a1: #REF!,#REF!,#REF!,#REF!,#REF!,#REF!,#REF!,#REF!,#REF!,#REF!,#REF!,#REF!
Name _______________________________________________d100000: #REF!
Name ______________________________________________d100000: #REF!
Name _____________________________________________a1: #REF!,#REF!,#REF!,#REF!,#REF!,#REF!,#REF!,#REF!,#REF!,#REF!,#REF!,#REF!
Name _____________________________________________A166999: #REF!
Name _____________________________________________A16999: #REF!
Name _____________________________________________bc2: #REF!,#REF!,#REF!,#REF!,#REF!,#REF!,#REF!,#REF!,#REF!,#REF!,#REF!,#REF!
Name _____________________________________________d100000: #REF!
Name ____________________________________________a1: #REF!,#REF!,#REF!,#REF!,#REF!,#REF!,#REF!,#REF!,#REF!,#REF!,#REF!,#REF!
Name ____________________________________________A166999: #REF!
Name ____________________________________________a99999: #REF!
Name ____________________________________________bc2: #REF!,#REF!,#REF!,#REF!,#REF!,#REF!,#REF!,#REF!,#REF!,#REF!,#REF!,#REF!
Name ____________________________________________d100000: #REF!
Name ____________________________________________si1: #REF!
Name ____________________________________________sl2: #REF!
Name ___________________________________________a1: #REF!,#REF!,#REF!,#REF!,#REF!,#REF!,#REF!,#REF!,#REF!,#REF!,#REF!,#REF!
Name ___________________________________________A166999: #REF!
Name ___________________________________________a99999: #REF!
Name ___________________________________________bc2: #REF!,#REF!,#REF!,#REF!,#REF!,#REF!,#REF!,#REF!,#REF!,#REF!,#REF!,#REF!
Name ___________________________________________d100000: #REF!
Name ___________________________________________si1: #REF!
Name ___________________________________________sl2: #REF!
Name __________________________________________a1: #REF!,#REF!,#REF!,#REF!,#REF!,#REF!,#REF!,#REF!,#REF!,#REF!,#REF!,#REF!
Name __________________________________________A166999: #REF!
Name __________________________________________A16999: #REF!
Name __________________________________________a19999: #REF!
Name __________________________________________a2: #REF!
Name __________________________________________a20000: #REF!
Name __________________________________________a99999: #REF!
Name __________________________________________ab1: #REF!
Name __________________________________________bc1: #REF!
Name __________________________________________bc2: #REF!,#REF!,#REF!,#REF!,#REF!,#REF!,#REF!,#REF!,#REF!,#REF!,#REF!,#REF!

Sheet 一级看板
B2: 决策依据 | D2: A-根据猪价行情&期货进行收储期判断 | L2: B-分割部位及分割量 | T2: C-销售及损益测算
D3: 收储研判 | E3: 基于当前4月23日猪价情况分析，收储窗口期：今天至2026年7月，共3个月； | L3: 分割收储 | M3: 日屠宰生猪目标4854头/天，分割储备23个产品，共储备3.1万吨 | T3: 销售期 | U3: 转深加工出库及销售期：26年11月-2027年2月，资金回报率11%
D4: ①现货猪价 | E4: 2026年4月23日 9.57元/kg | L4: ①产品参数 | M4: 23个目标储备产品头均产出76kg/头 | T4: ①销售期 | U4: 0 | V4: 合计 | W4: 26年11月 | X4: 26年12月 | Y4: 27年1月
D5: ②期货猪价 | E5: 2605期 | F5: 2607期 | G5: 2609期 | H5: 2611期 | I5: 2701期 | J5: 2703期 | L5: ②储备量及资金 | M5: 月份 | N5: 合计 | O5: 202605 | P5: 202606 | Q5: 202607 | T5: ②储备量 及资金 | U5: 销量 | V5: 3.1万吨 | W5: 1.03 | X5: 1.03 | Y5: 1.03
E6: 9.74元/kg | F6: 11.45 | G6: 12.53 | H6: 12.71 | I6: 13.16 | J6: 12.68 | M6: 储备量 | N6: 3.1万吨 | O6: 1.03 | P6: 1.03 | Q6: 1.03 | U6: 销售价格 | V6: 15.2元/kg | W6: 14.987571 | X6: 15.17573 | Y6: 15.363889
D7: ③数据参数 | E7: 行业头部企业平均成本12元/kg； 储备期仓储及资金占用费0.22元/kg/月； | M7: 收储成本 | N7: 12.2元/kg | O7: 11.346847 | P7: 12.182567 | Q7: 13.018287 | U7: 收入 | V7: 4.7亿元 | W7: 1.5504086 | X7: 1.5698729 | Y7: 1.5893373
D8: ④收储算法 | E8: 生猪价格低于“行业头部企业成本-储备期费用”时，即具备储备窗口； | M8: 资金需求 | N8: 3.8亿元 | O8: 1.2 | P8: 1.3 | Q8: 1.3 | U8: 净利润 | V8: 0.41亿元 | W8: 0.20503324 | X8: 0.13804547 | Y8: 0.071057713
D9: ⑤风险预判 | E9: 储备熔断机制：以下月份出现大于此猪价时，应立即停止收储工作； | U9: 利润率 | V9: 0.088 | W9: 0.13224465 | X9: 0.087934171 | Y9: 0.04470902
E10: 时间 | F10: 202604 | G10: 202605 | H10: 202606 | I10: 202607
E11: 价格 | F11: 10.80元/kg | G11: 11.02 | H11: 11.26 | I11: 11.47925
B13: 决策建议 | E13: 襄阳工厂 | F13: 洛阳工厂 | G13: 徐州工厂 | H13: 内蒙古工厂 | I13: 山西工厂 | J13: 庆阳工厂 | K13: 成都OEM | L13: 长沙OEM
D14: 屠宰分割头数 | E14: 947头/天 | F14: 789.31189 | G14: 947.17427 | H14: 1315.5198 | I14: 263.10396 | J14: 394.65594 | K14: 98.663986 | L14: 98.663986
D15: 日储备量 | E15: 72吨/天 | F15: 60000 | G15: 72000 | H15: 100000 | I15: 20000 | J15: 30000 | K15: 7500 | L15: 7500
D16: 总储备量 | E16: 5629吨 | F16: 5156446.7 | G16: 6339993.8 | H16: 8342359.7 | I16: 1793520 | J16: 2422943.8 | K16: 675000 | L16: 675000
D17: 仓储缺口 | E17: 629吨 | F17: 4156446.7 | G17: 1339993.8 | H17: 3342359.7 | I17: 1493520 | J17: 1922943.8 | K17: - | L17: -
D18: 资金缺口 | E18: 3.8亿元 | F18: 0.77127707 | G18: 0.94830648 | H18: 1.247811 | I18: 0.26826629 | J18: 0.36241255 | K18: 0.10096333 | L18: 0.10096333
B20: 派单角色 | D20: 流程任务1 | E20: 屠宰分割储备 | F20: 屠宰分割储备 | G20: 屠宰分割储备 | H20: 屠宰分割储备 | I20: 屠宰分割储备 | J20: 屠宰分割储备 | K20: 屠宰分割储备 | L20: 屠宰分割储备
D21: 角色 | E21: 徐杰 | F21: 沈道华 | G21: 王荣师 | H21: 高世玺 | I21: 李世彬 | J21: 王寒 | K21: 张佰才 | L21: 张鹏
D23: 流程任务2 | E23: 寻找社会外租库 | F23: 寻找社会外租库 | G23: 寻找社会外租库 | H23: 寻找社会外租库 | I23: 寻找社会外租库 | J23: 寻找社会外租库 | K23: 寻找社会外租库 | L23: 寻找社会外租库
D24: 角色 | E24: 王学斌 | F24: 王学斌 | G24: 王学斌 | H24: 王学斌 | I24: 王学斌 | J24: 王学斌 | K24: 王学斌 | L24: 王学斌
D26: 流程任务3 | E26: 资金缺口 | F26: 资金缺口 | G26: 资金缺口 | H26: 资金缺口 | I26: 资金缺口 | J26: 资金缺口 | K26: 资金缺口 | L26: 资金缺口
D27: 角色 | E27: 冯鑫 | F27: 冯鑫 | G27: 冯鑫 | H27: 冯鑫 | I27: 冯鑫 | J27: 冯鑫 | K27: 冯鑫 | L27: 冯鑫
D29: 流程任务4 | E29: 转熟增值 | F29: 转熟增值 | G29: 转熟增值 | H29: 转熟增值 | I29: 转熟增值 | J29: 转熟增值 | K29: 转熟增值 | L29: 转熟增值
D30: 角色 | E30: 侯孝海 | F30: 侯孝海 | G30: 侯孝海 | H30: 侯孝海 | I30: 侯孝海 | J30: 侯孝海 | K30: 侯孝海 | L30: 侯孝海
D32: 流程任务5 | E32: 销售 | F32: 销售 | G32: 销售 | H32: 销售 | I32: 销售 | J32: 销售 | K32: 销售 | L32: 销售
D33: 角色 | E33: 王学斌 | F33: 王学斌 | G33: 王学斌 | H33: 王学斌 | I33: 王学斌 | J33: 王学斌 | K33: 王学斌 | L33: 王学斌

Sheet 二级看板-决策依据
A1: 日期
A2: =TODAY() -> 46136 | C2: A-生猪行情及期货价格 | L2: B-储备期日储备量及总储备量 | Q2: C-数据测算（基于财务的三张表）
C3: 今日毛猪价及利润 | L3: 标准储存部位 | N3: 日储备量 | O3: 总储备量 | Q3: 收储期 | W3: 0 | X3: 销售期-找到最佳销售期
C4: =A2 -> 46136 | D4: =[1]期货行情预测价!C13 -> 9.5579427 | E4: 元/kg | G4: 毛猪利润 | H4: =[1]毛猪损益测算!C9 -> -509.04688 | L4: 序号 | M4: 储备部位 | N4: 吨/日 | O4: （万吨） | Q4: ='[1]4854头总结'!B4 -> 0 | R4: ='[1]4854头总结'!C4 -> 0 | S4: ='[1]4854头总结'!D4 -> 26年5月 | T4: ='[1]4854头总结'!E4 -> 26年6月 | U4: ='[1]4854头总结'!F4 -> 26年7月 | W4: ='[1]4854头总结'!L4 -> 0 | X4: ='[1]4854头总结'!M4 -> 0 | Y4: ='[1]4854头总结'!N4 -> 0 | Z4: ='[1]4854头总结'!O4 -> 26年11月 | AA4: ='[1]4854头总结'!P4 -> 26年12月 | AB4: ='[1]4854头总结'!Q4 -> 27年1月 | AC4: ='[1]4854头总结'!R4 -> 27年2月
L5: ='[1]23个储备部位-储备量'!B5 -> 1 | M5: ='[1]23个储备部位-储备量'!C5 -> 冻前腿肌肉(Ⅱ) | N5: ='[1]23个储备部位-储备量'!AD5 -> 29781.677 | O5: ='[1]23个储备部位-储备量'!AH5/10000/1000 -> 0.2443066 | Q5: ='[1]4854头总结'!B5 -> 毛猪价格 | R5: ='[1]4854头总结'!C5 -> 元/kg | S5: ='[1]4854头总结'!D5 -> 9.78 | T5: ='[1]4854头总结'!E5 -> 10.635 | U5: ='[1]4854头总结'!F5 -> 11.49 | W5: ='[1]4854头总结'!L5 -> 0 | X5: ='[1]4854头总结'!M5 -> 毛猪价格 | Y5: ='[1]4854头总结'!N5 -> 元/kg | Z5: ='[1]4854头总结'!O5 -> 12.79 | AA5: ='[1]4854头总结'!P5 -> 12.9825 | AB5: ='[1]4854头总结'!Q5 -> 13.175 | AC5: ='[1]4854头总结'!R5 -> 12.935
C6: 行业平均毛猪成本 | G6: 月储存费 | L6: ='[1]23个储备部位-储备量'!B6 -> 2 | M6: ='[1]23个储备部位-储备量'!C6 -> 冻带皮前上肉 冻去皮前上肉 冻带皮后上肉 冻去皮后上肉 | N6: ='[1]23个储备部位-储备量'!AD6 -> 34092.561 | O6: ='[1]23个储备部位-储备量'!AH6/10000/1000 -> 0.30620905 | Q6: ='[1]4854头总结'!B6 -> 储存量 | R6: ='[1]4854头总结'!C6 -> 万吨 | S6: ='[1]4854头总结'!D6 -> 1034.4629 | T6: ='[1]4854头总结'!E6 -> 1034.4629 | U6: ='[1]4854头总结'!F6 -> 1034.4629 | W6: ='[1]4854头总结'!L6 -> 0 | X6: ='[1]4854头总结'!M6 -> 销售量 | Y6: ='[1]4854头总结'!N6 -> 万吨 | Z6: ='[1]4854头总结'!O6 -> 3103.3887 | AA6: ='[1]4854头总结'!P6 -> 3103.3887 | AB6: ='[1]4854头总结'!Q6 -> 3103.3887 | AC6: ='[1]4854头总结'!R6 -> 3103.3887
C7: 12 | D7: 元/kg | G7: =[1]生产及仓储费用标准!H16 -> 0.22075 | H7: 元/kg | L7: ='[1]23个储备部位-储备量'!B7 -> 3 | M7: ='[1]23个储备部位-储备量'!C7 -> 冻后腿肌肉(Ⅳ) | N7: ='[1]23个储备部位-储备量'!AD7 -> 49767.631 | O7: ='[1]23个储备部位-储备量'!AH7/10000/1000 -> 0.41016016 | Q7: ='[1]4854头总结'!B8 -> 收储成本 | R7: ='[1]4854头总结'!C8 -> 元/kg | S7: ='[1]4854头总结'!D8 -> 11.346847 | T7: ='[1]4854头总结'!E8 -> 12.182567 | U7: ='[1]4854头总结'!F8 -> 13.018287 | W7: ='[1]4854头总结'!L7 -> 0 | X7: ='[1]4854头总结'!M8 -> 收入 | Y7: ='[1]4854头总结'!N8 -> 亿元 | Z7: ='[1]4854头总结'!O8 -> 4.6512257 | AA7: ='[1]4854头总结'!P8 -> 4.7096188 | AB7: ='[1]4854头总结'!Q8 -> 4.7680119 | AC7: ='[1]4854头总结'!R8 -> 4.6952101
L8: ='[1]23个储备部位-储备量'!B8 -> 4 | M8: ='[1]23个储备部位-储备量'!C8 -> 冻里脊肉(Ⅲ) | N8: ='[1]23个储备部位-储备量'!AD8 -> 27094.108 | O8: ='[1]23个储备部位-储备量'!AH8/10000/1000 -> 0.22893213 | Q8: ='[1]4854头总结'!B10 -> 资金占用 | R8: ='[1]4854头总结'!C10 -> 亿元 | S8: ='[1]4854头总结'!D10 -> 1.1737892 | T8: ='[1]4854头总结'!E10 -> 1.2602413 | U8: ='[1]4854头总结'!F10 -> 1.3466935 | W8: ='[1]4854头总结'!L8 -> 0 | X8: ='[1]4854头总结'!M7 -> 销售价格 | Y8: ='[1]4854头总结'!N7 -> 元/kg | Z8: ='[1]4854头总结'!O7 -> 14.987571 | AA8: ='[1]4854头总结'!P7 -> 15.17573 | AB8: ='[1]4854头总结'!Q7 -> 15.363889 | AC8: ='[1]4854头总结'!R7 -> 15.129301
A9: 202604 | C9: 期货价格-收储判断 | G9: 仓储费 | H9: 毛猪平均成本 -毛猪价-仓储费 | I9: 风险预警 毛猪成本-仓储费-0.3 | L9: ='[1]23个储备部位-储备量'!B9 -> 5 | M9: ='[1]23个储备部位-储备量'!C9 -> 冻精碎肉 | N9: ='[1]23个储备部位-储备量'!AD9 -> 6014.3087 | O9: ='[1]23个储备部位-储备量'!AH9/10000/1000 -> 0.039728358 | Q9: ='[1]4854头总结'!B9 -> 0 | R9: ='[1]4854头总结'!C9 -> 0 | S9: ='[1]4854头总结'!D9 -> 0 | T9: ='[1]4854头总结'!E9 -> 0 | U9: ='[1]4854头总结'!F9 -> 0 | W9: ='[1]4854头总结'!L9 -> 0 | X9: 销售成本 | Y9: ='[1]4854头总结'!N9 -> 元/kg | Z9: ='[1]生猪储备时效利润分析模型-4854头'!AD15 -> 13.286317 | AA9: ='[1]生猪储备时效利润分析模型-4万头'!AD25 -> 13.507067 | AB9: ='[1]生猪储备时效利润分析模型-4万头'!AD35 -> 13.727817 | AC9: ='[1]生猪储备时效利润分析模型-4万头'!AD45 -> 13.948567
A10: =IF($C$7-D10<0,0,1) -> 1 | B10: =IF(H10<0,0,1) -> 1 | C10: =[1]期货行情预测价!B4 -> 202605 | D10: =[1]期货行情预测价!D13 -> 9.78 | E10: 元/kg | G10: =(SUM($B$10:$B$20)*$G$7) -> 0.66225 | H10: =$C$7-(D10+SUM($A$10:$A$20)*$G$7) -> 1.55775 | I10: =$C$7-G10-0.3 -> 11.03775 | J10: =IF(I10>D10,"收储","停止收储") -> 收储 | L10: ='[1]23个储备部位-储备量'!B10 -> 6 | M10: ='[1]23个储备部位-储备量'!C10 -> 冻肥膘 | N10: ='[1]23个储备部位-储备量'!AD10 -> 17870.688 | O10: ='[1]23个储备部位-储备量'!AH10/10000/1000 -> 0.11101027 | W10: ='[1]4854头总结'!L10 -> 0 | X10: 销售费用 | Y10: 元/kg | Z10: ='[1]生猪储备时效利润分析模型-4万头'!AD16 -> 0.33419766 | AA10: ='[1]生猪储备时效利润分析模型-4万头'!AD26 -> 0.33419766 | AB10: ='[1]生猪储备时效利润分析模型-4万头'!AD36 -> 0.33419766 | AC10: ='[1]生猪储备时效利润分析模型-4万头'!AD46 -> 0.33419766
A11: =IF($C$7-D11<0,0,1) -> 1 | B11: =IF(H11<0,0,1) -> 1 | C11: 202606 | D11: =[1]期货行情预测价!E13 -> 10.635 | E11: 元/kg | G11: =((SUM($B$10:$B$20)-B10)*$G$7) -> 0.4415 | H11: =$C$7-(D11+(SUM($A$10:$A$20)-A10)*$G$7) -> 0.9235 | I11: =$C$7-G11-0.3 -> 11.2585 | J11: =IF(I11>D11,"收储","停止收储") -> 收储 | L11: ='[1]23个储备部位-储备量'!B11 -> 7 | M11: ='[1]23个储备部位-储备量'!C11 -> 冻原料肥膘 | N11: ='[1]23个储备部位-储备量'!AD11 -> 8935.344 | O11: ='[1]23个储备部位-储备量'!AH11/10000/1000 -> 0.080418096 | Q11: ='[1]4854头总结'!B11 -> 0 | R11: ='[1]4854头总结'!C11 -> 0 | S11: ='[1]4854头总结'!D11 -> 0 | T11: ='[1]4854头总结'!E11 -> 0 | U11: ='[1]4854头总结'!F11 -> 0 | V11: ='[1]4854头总结'!G11 -> 0 | W11: ='[1]4854头总结'!L11 -> 0 | X11: 单位利润 | Y11: 元/kg | Z11: =Z8-Z9-Z10 -> 1.367056 | AA11: =AA8-AA9-AA10 -> 1.3344652 | AB11: =AB8-AB9-AB10 -> 1.3018744 | AC11: =AC8-AC9-AC10 -> 0.84653633
A12: =IF($C$7-D12<0,0,1) -> 1 | B12: =IF(H12<0,0,1) -> 1 | C12: =[1]期货行情预测价!B5 -> 202607 | D12: =[1]期货行情预测价!F13 -> 11.49 | E12: 元/kg | G12: =((SUM($B$10:$B$20)-B10-B11)*$G$7) -> 0.22075 | H12: =$C$7-(D12+(SUM($A$10:$A$20)-A10-A11)*$G$7) -> 0.28925 | I12: =$C$7-G12-0.3 -> 11.47925 | J12: =IF(I12>D12,"收储","停止收储") -> 停止收储 | L12: ='[1]23个储备部位-储备量'!B12 -> 8 | M12: ='[1]23个储备部位-储备量'!C12 -> 冻带皮肉花膘 冻去皮肉花膘 | N12: ='[1]23个储备部位-储备量'!AD12 -> 5361.2064 | O12: ='[1]23个储备部位-储备量'!AH12/10000/1000 -> 0.048250857 | W12: ='[1]4854头总结'!L12 -> 0 | X12: ='[1]4854头总结'!M10 -> 净利润 | Y12: ='[1]4854头总结'!N10 -> 亿元 | Z12: ='[1]4854头总结'!O10 -> 0.42425062 | AA12: ='[1]4854头总结'!P10 -> 0.41413642 | AB12: ='[1]4854头总结'!Q10 -> 0.40402222 | AC12: ='[1]4854头总结'!R10 -> 0.26271313
A13: =IF($C$7-D13<0,0,1) -> 0 | B13: =IF(H13<0,0,1) -> 0 | C13: 202608 | D13: =[1]期货行情预测价!G13 -> 12.0325 | E13: 元/kg | G13: =((SUM($B$10:$B$20)-B10-B11-B12)*$G$7) -> 0 | H13: =$C$7-(D13+(SUM($A$10:$A$20)-A10-A11-A12)*$G$7) -> -0.0325 | I13: =$C$7-G13-0.3 -> 11.7 | J13: 停止收储 | L13: ='[1]23个储备部位-储备量'!B13 -> 9 | M13: ='[1]23个储备部位-储备量'!C13 -> 冻碎肥 | N13: ='[1]23个储备部位-储备量'!AD13 -> 3574.1376 | O13: ='[1]23个储备部位-储备量'!AH13/10000/1000 -> 0.024344738 | W13: ='[1]4854头总结'!L13 -> 0 | X13: ='[1]4854头总结'!M11 -> 利润率 | Y13: ='[1]4854头总结'!N11 -> % | Z13: ='[1]4854头总结'!O11 -> 0.09121265 | AA13: ='[1]4854头总结'!P11 -> 0.087934171 | AB13: ='[1]4854头总结'!Q11 -> 0.084735993 | AC13: ='[1]4854头总结'!R11 -> 0.055953433
A14: =IF($C$7-D14<0,0,1) -> 0 | B14: =IF($C$7-D14<0,0,1) -> 0 | C14: =[1]期货行情预测价!B6 -> 202609 | D14: =[1]期货行情预测价!H13 -> 12.575 | E14: 元/kg | G14: =((SUM($B$10:$B$20)-B11-B12-B13-B10)*$G$7) -> 0 | H14: =$C$7-(D14+(SUM($A$10:$A$20)-A11-A12-A13-A10)*$G$7) -> -0.575 | I14: =$C$7-G14-0.3 -> 11.7 | J14: =IF(I14>D14,"收储","停止收储") -> 停止收储 | L14: ='[1]23个储备部位-储备量'!B14 -> 10 | M14: ='[1]23个储备部位-储备量'!C14 -> 冻带皮腮肉（25kg） 冻槽头肉（25kg） | N14: ='[1]23个储备部位-储备量'!AD14 -> 10776.925 | O14: ='[1]23个储备部位-储备量'!AH14/10000/1000 -> 0.096992323 | W14: ='[1]4854头总结'!L14 -> 0
A15: =IF($C$7-D15<0,0,1) -> 0 | B15: =IF($C$7-D15<0,0,1) -> 0 | C15: 202610 | D15: =[1]期货行情预测价!I13 -> 12.6825 | E15: 元/kg | G15: =((SUM($B$10:$B$20)-B12-B13-B14-B11-B10)*$G$7) -> 0 | H15: =$C$7-(D15+(SUM($A$10:$A$20)-A12-A13-A14-A11-A10)*$G$7) -> -0.6825 | I15: =$C$7-G15-0.3 -> 11.7 | J15: =IF(I15>D15,"收储","停止收储") -> 停止收储 | L15: ='[1]23个储备部位-储备量'!B15 -> 11 | M15: ='[1]23个储备部位-储备量'!C15 -> 冻猪汤骨 | N15: ='[1]23个储备部位-储备量'!AD15 -> 7674.7885 | O15: ='[1]23个储备部位-储备量'!AH15/10000/1000 -> 0.056696311 | Q15: 收储期总结 | W15: ='[1]4854头总结'!L15 -> 0 | X15: 销售期总结
A16: =IF($C$7-D16<0,0,1) -> 0 | B16: =IF($C$7-D16<0,0,1) -> 0 | C16: =[1]期货行情预测价!B7 -> 202611 | D16: =[1]期货行情预测价!J13 -> 12.79 | E16: 元/kg | G16: =((SUM($B$10:$B$20)-B13-B14-B15-B12-B11-B10)*$G$7) -> 0 | H16: =$C$7-(D16+(SUM($A$10:$A$20)-A13-A14-A15-A12-A11-A10)*$G$7) -> -0.79 | I16: =$C$7-G16-0.3 -> 11.7 | J16: =IF(I16>D16,"收储","停止收储") -> 停止收储 | L16: ='[1]23个储备部位-储备量'!B16 -> 12 | M16: ='[1]23个储备部位-储备量'!C16 -> 冻肋排 | N16: ='[1]23个储备部位-储备量'!AD16 -> 16736.587 | O16: ='[1]23个储备部位-储备量'!AH16/10000/1000 -> 0.14756929 | Q16: ='[1]4854头总结'!B13 -> 收储期毛猪价格 | R16: 元/kg | S16: ='[1]4854头总结'!D13 -> 10.635 | T16: ='[1]4854头总结'!E13 -> 0 | U16: ='[1]4854头总结'!F13 -> 0 | W16: ='[1]4854头总结'!L16 -> 0 | X16: 毛猪价格 | Y16: 元/kg | Z16: =Z5 -> 12.79
A17: =IF($C$7-D17<0,0,1) -> 0 | B17: =IF($C$7-D17<0,0,1) -> 0 | C17: 202612 | D17: =[1]期货行情预测价!K13 -> 12.9825 | E17: 元/kg | G17: =((SUM($B$10:$B$20)-B14-B15-B16-B13-B12-B11-B10)*$G$7) -> 0 | H17: =$C$7-(D17+(SUM($A$10:$A$20)-A14-A15-A16-A13-A12-A11-A10)*$G$7) -> -0.9825 | I17: =$C$7-G17-0.3 -> 11.7 | J17: =IF(I17>D17,"收储","停止收储") -> 停止收储 | L17: ='[1]23个储备部位-储备量'!B17 -> 13 | M17: ='[1]23个储备部位-储备量'!C17 -> 冻带皮五花肉 | N17: ='[1]23个储备部位-储备量'!AD17 -> 28266.622 | O17: ='[1]23个储备部位-储备量'!AH17/10000/1000 -> 0.24248975 | Q17: ='[1]4854头总结'!B14 -> 储存量 | R17: ='[1]4854头总结'!C14 -> 万吨 | S17: ='[1]4854头总结'!D14 -> 3103.3887 | T17: ='[1]4854头总结'!E14 -> 0 | U17: ='[1]4854头总结'!F14 -> 0 | W17: ='[1]4854头总结'!L17 -> 0 | X17: 销售量 | Y17: 万吨 | Z17: =Z6 -> 3103.3887
A18: =IF($C$7-D18<0,0,1) -> 0 | B18: =IF($C$7-D18<0,0,1) -> 0 | C18: =[1]期货行情预测价!B8 -> 202701 | D18: =[1]期货行情预测价!L13 -> 13.175 | E18: 元/kg | G18: =(SUM($B$10:$B$20)-B15-B16-B17-B14-B13-B12-B11-B10)*$G$7 -> 0 | H18: =$C$7-(D18+(SUM($A$10:$A$20)-A15-A16-A17-A14-A13-A12-A11-A10)*$G$7) -> -1.175 | I18: =$C$7-G18-0.3 -> 11.7 | J18: =IF(I18>D18,"收储","停止收储") -> 停止收储 | L18: ='[1]23个储备部位-储备量'!B18 -> 14 | M18: ='[1]23个储备部位-储备量'!C18 -> 冻去皮五花肉 | N18: ='[1]23个储备部位-储备量'!AD18 -> 11306.649 | O18: ='[1]23个储备部位-储备量'!AH18/10000/1000 -> 0.099233666 | Q18: ='[1]4854头总结'!B15 -> 收储成本 | R18: ='[1]4854头总结'!C15 -> 元/kg | S18: ='[1]4854头总结'!D15 -> 12.182567 | T18: ='[1]4854头总结'!E15 -> 0 | U18: ='[1]4854头总结'!F15 -> 0 | X18: 收入 | Y18: 亿元 | Z18: =Z7 -> 4.6512257
A19: =IF($C$7-D19<0,0,1) -> 0 | B19: =IF($C$7-D19<0,0,1) -> 0 | C19: 202602 | D19: =[1]期货行情预测价!M13 -> 12.935 | E19: 元/kg | G19: =((SUM($B$10:$B$20)-B16-B17-B18-B15-B14-B13-B12-B11-B10)*$G$7) -> 0 | H19: =$C$7-(D19+(SUM($A$10:$A$20)-A16-A17-A18-A15-A14-A13-A12-A11-A10)*$G$7) -> -0.935 | I19: =$C$7-G19-0.3 -> 11.7 | J19: =IF(I19>D19,"收储","停止收储") -> 停止收储 | L19: ='[1]23个储备部位-储备量'!B19 -> 15 | M19: ='[1]23个储备部位-储备量'!C19 -> 冻肥五花 | N19: ='[1]23个储备部位-储备量'!AD19 -> 8479.9867 | O19: ='[1]23个储备部位-储备量'!AH19/10000/1000 -> 0.07451688 | Q19: 资金需求 | R19: 亿元 | S19: =Z25 -> 3.780724 | X19: 销售价格 | Y19: 元/kg | Z19: =Z8 -> 14.987571
A20: =IF($C$7-D20<0,0,1) -> 0 | B20: =IF($C$7-D20<0,0,1) -> 0 | C20: =[1]期货行情预测价!B9 -> 202703 | D20: =[1]期货行情预测价!N13 -> 12.695 | E20: 元/kg | G20: =((SUM($B$10:$B$20)-B17-B18-B19-B16-B15-B14-B13-B12-B11-B10)*$G$7) -> 0 | H20: =$C$7-(D20+(SUM($A$10:$A$20)-A17-A18-A19-A16-A15-A14-A13-A12-A11-A10)*$G$7) -> -0.695 | I20: =$C$7-G20-0.3 -> 11.7 | J20: =IF(I20>D20,"收储","停止收储") -> 停止收储 | L20: ='[1]23个储备部位-储备量'!B20 -> 16 | M20: ='[1]23个储备部位-储备量'!C20 -> 冻带皮腹肋肉 冻带皮带骨中方 | N20: ='[1]23个储备部位-储备量'!AD20 -> 8479.9867 | O20: ='[1]23个储备部位-储备量'!AH20/10000/1000 -> 0.07631988 | T20: ='[1]4854头总结'!E16 -> 0 | U20: ='[1]4854头总结'!F16 -> 0 | X20: 销售成本 | Y20: 元/kg | Z20: =Z9 -> 13.286317
L21: ='[1]23个储备部位-储备量'!B21 -> 17 | M21: ='[1]23个储备部位-储备量'!C21 -> 冻带皮带骨前肘 冻带皮带骨后肘 | N21: ='[1]23个储备部位-储备量'!AD21 -> 27421.013 | O21: ='[1]23个储备部位-储备量'!AH21/10000/1000 -> 0.24225728 | T21: ='[1]4854头总结'!E17 -> 0 | U21: ='[1]4854头总结'!F17 -> 0 | X21: 销售费用 | Y21: 元/kg | Z21: =Z10 -> 0.33419766
L22: ='[1]23个储备部位-储备量'!B22 -> 18 | M22: ='[1]23个储备部位-储备量'!C22 -> 冻猪带皮小蹄膀（25kg） | N22: ='[1]23个储备部位-储备量'!AD22 -> 10676.105 | O22: ='[1]23个储备部位-储备量'!AH22/10000/1000 -> 0.095659351 | X22: 单位利润 | Y22: 元/kg | Z22: =Z11 -> 1.367056
L23: ='[1]23个储备部位-储备量'!B23 -> 19 | M23: ='[1]23个储备部位-储备量'!C23 -> 冻猪原料皮 | N23: ='[1]23个储备部位-储备量'!AD23 -> 5043.5258 | O23: ='[1]23个储备部位-储备量'!AH23/10000/1000 -> 0.026755204 | Q23: ='[1]4854头总结'!B17 -> 毛猪利润 | R23: ='[1]4854头总结'!C17 -> 亿 | S23: ='[1]4854头总结'!D17 -> -1.6592859 | X23: 净利润 | Y23: 亿元 | Z23: =Z12 -> 0.42425062
L24: ='[1]23个储备部位-储备量'!B24 -> 20 | M24: ='[1]23个储备部位-储备量'!C24 -> 冻猪肘花皮 | N24: ='[1]23个储备部位-储备量'!AD24 -> 4413.0851 | O24: ='[1]23个储备部位-储备量'!AH24/10000/1000 -> 0.039717766 | Q24: 毛猪利润 | R24: 元/头 | S24: =[1]毛猪损益测算!C17 -> -379.8 | X24: 利润率 | Y24: % | Z24: =Z13 -> 0.09121265
L25: ='[1]23个储备部位-储备量'!B25 -> 21 | M25: ='[1]23个储备部位-储备量'!C25 -> 鲜猪精制皮 冻猪精制皮 | N25: ='[1]23个储备部位-储备量'!AD25 -> 3152.2036 | O25: ='[1]23个储备部位-储备量'!AH25/10000/1000 -> 0.028369833 | X25: ='[1]4854头总结'!M15 -> 资金占用 | Y25: ='[1]4854头总结'!N15 -> 亿元 | Z25: ='[1]4854头总结'!O15 -> 3.780724
L26: ='[1]23个储备部位-储备量'!B26 -> 22 | M26: ='[1]23个储备部位-储备量'!C26 -> 冻猪带皮脊背 | N26: ='[1]23个储备部位-储备量'!AD26 -> 27421.013 | O26: ='[1]23个储备部位-储备量'!AH26/10000/1000 -> 0.2410769
L27: ='[1]23个储备部位-储备量'!B27 -> 23 | M27: ='[1]23个储备部位-储备量'!C27 -> 鲜碎肉 冻碎肉 | N27: ='[1]23个储备部位-储备量'!AD27 -> 16659.848 | O27: ='[1]23个储备部位-储备量'!AH27/10000/1000 -> 0.14237398 | X27: ='[1]4854头总结'!M17 -> 资金回报率 | Y27: ='[1]4854头总结'!N17 -> % | Z27: ='[1]4854头总结'!O17 -> 0.11221412
L28: ='[1]23个储备部位-储备量'!B28 -> 合计 | M28: ='[1]23个储备部位-储备量'!C28 -> 0 | N28: ='[1]23个储备部位-储备量'!AD28 -> 369000 | O28: ='[1]23个储备部位-储备量'!AH28/10000/1000 -> 3.1033887

Sheet 二级看板-决策建议
F2: 当日 | J2: 累计
B3: 工厂 | C3: 指标 | D3: 单位 | F3: 目标 | G3: 实际 | H3: 达成率 | J3: 目标 | K3: 实际 | L3: 达成率
B4: 襄阳 | C4: 屠宰量 | D4: 头
C5: 分割量 | D5: 头
C6: 速冻量 | D6: 吨
C7: 储备量 | D7: 吨
C8: 部位1 | D8: 吨
C9: 部位2 | D9: 吨
C10: 部位3 | D10: 吨
C11: 部位4 | D11: 吨
C12: 部位5 | D12: 吨
C13: 部位6 | D13: 吨
C14: 部位7 | D14: 吨
C15: 部位8 | D15: 吨
C16: 部位9 | D16: 吨
... C34: 库容率 | D34: %

Sheet 派单角色-派单文案
B2: 工单序号 | C2: 流程任务 | D2: 角色 | E2: 派单文案
B3: 工单1 | C3: 屠宰分割储备 | D3: 王荣师 | E3: 【冻品储备肉工单】王荣师您好！根据AI收储决策，襄阳工厂具备收储窗口，请按日屠宰947头/天、日储备72吨/天推进屠宰分割储备，总储备目标5629吨。请每日同步数据，异常及时反馈。
B4: 工单2 | C4: 寻找社会外租库 | D4: 王学斌 | E4: 【冻品储备肉工单】王学斌您好！襄阳工厂当前仓储缺口629吨，请优先对接社会外租库解决库容问题，保障储备计划落地。请同步对接进度。
B5: 工单3 | C5: 资金缺口协调 | D5: 冯鑫 | E5: 【冻品储备肉工单】冯鑫您好！襄阳工厂本次收储资金缺口3.8亿元，请按缺口完成资金统筹对接，保障项目资金到位。请同步协调进度。
B6: 工单4 | C6: 转熟增值 | D6: 侯孝海 | E6: 【冻品储备肉工单】侯孝海您好！襄阳工厂收储产品将于2026年11月起转深加工销售，请提前搭建转熟增值链路，保障顺利出库。请同步链路进度。
B7: 工单5 | C7: 销售统筹 | D7: 王学斌 | E7: 【冻品储备肉工单】王学斌您好！襄阳工厂收储产品需纳入2026年11月-2027年2月销售计划，目标资金回报率11%，请按销售期推进落地。请同步销售进度。
