Workbook
Name ————: #REF!,#REF!,#REF!,#REF!,#REF!,#REF!,#REF!,#REF!,#REF!,#REF!,#REF!,#REF!
Name \1: #N/A
Name \a: #N/A
Name \b: #N/A
Name \f: #N/A
Name ______Module1.Macro1: #N/A
Name ______Module1.Macro111: #N/A
Name _____Module1.Macro1: #N/A
Name _____Module1.Macro111: #N/A
Name _Module1.Macro1: #N/A
Name _Module1.Macro111: #N/A
Name _ModuleU201__ARP_A: #N/A
Name _ModuleU201__ARP_B: #N/A
Name _ModuleU201__ARP_C: #N/A
Name _ModuleU201__ARP_D: #N/A
Name _ModuleU201__ARP_E: #N/A
Name _ModuleU201__ARP_F: #N/A
Name _ModuleU201__ARP_G: #N/A
Name _ModuleU201__ARP_H: #N/A
Name _ModuleU201__Back: #N/A
Name A: #N/A
Name area1_15: #N/A
Name ARP_A: #N/A
Name as: #N/A
Name B: #N/A
Name balance_type: 1
Name BGKZ: NA()
Name BGKZ1: NA()
Name BGKZ2: NA()
Name BGKZ3: NA()
Name BGKZ4: NA()
Name BGKZ5: NA()
Name BGKZ6: NA()
Name BM_1: NA()
Name BMONAT: NA()
Name bsdw: "菲特科技"
Name C_: #N/A
Name calc: 1
Name CC101_ARP_A: #N/A
Name CC101_ARP_B: #N/A
Name CC101_ARP_C: #N/A
Name co: 100
Name drf: #N/A
Name E: #N/A
Name F: #N/A
Name FAFEKZ: NA()
Name FAFEKZ1: NA()
Name FAFEKZ10: NA()
Name FAFEKZ11: NA()
Name FAFEKZ12: NA()
Name FAFEKZ13: NA()
Name FAFEKZ14: NA()
Name FAFEKZ15: NA()
Name FAFEKZ16: NA()
Name FAFEKZ2: NA()
Name FAFEKZ3: NA()
Name FAFEKZ4: NA()
Name FAFEKZ5: NA()
Name FAFEKZ6: NA()
Name FAFEKZ7: NA()

Sheet 1.出栏表
B2: 所属省份 | C2: 日期 | D2: 出栏量-头 | E2: 均重 | F2: 毛猪价格-元/kg-用于计算成本 | G2: 网站价格-用于计算决策 | H2: 未来期货价格-元/kg
A3: =B3&C3 -> 甘肃46135 | B3: 甘肃 | C3: 46135 | D3: 1179.8684 | E3: 125 | F3: 8.8166562 | G3: 8.8166562 | H3: 9.3737657
A4: =B4&C4 -> 甘肃46136 | B4: 甘肃 | C4: 46136 | D4: 1179.8684 | E4: 125 | F4: 8.8166562 | G4: 8.8166562 | H4: 9.3737657
A5: =B5&C5 -> 甘肃46137 | B5: 甘肃 | C5: 46137 | D5: 1179.8684 | E5: 125 | F5: 8.8166562 | G5: 8.8166562 | H5: 9.3737657
A6: =B6&C6 -> 甘肃46138 | B6: 甘肃 | C6: 46138 | D6: 1179.8684 | E6: 125 | F6: 8.8166562 | G6: 8.8166562 | H6: 9.3737657
A7: =B7&C7 -> 甘肃46139 | B7: 甘肃 | C7: 46139 | D7: 1179.8684 | E7: 125 | F7: 8.8166562 | G7: 8.8166562 | H7: 9.3737657
A8: =B8&C8 -> 甘肃46140 | B8: 甘肃 | C8: 46140 | D8: 1179.8684 | E8: 125 | F8: 8.8166562 | G8: 8.8166562 | H8: 9.3737657
A9: =B9&C9 -> 甘肃46141 | B9: 甘肃 | C9: 46141 | D9: 1179.8684 | E9: 125 | F9: 8.8166562 | G9: 8.8166562 | H9: 9.3737657
A10: =B10&C10 -> 甘肃46142 | B10: 甘肃 | C10: 46142 | D10: 1179.8684 | E10: 125 | F10: 8.8166562 | G10: 8.8166562 | H10: 9.3737657
A11: =B11&C11 -> 甘肃46143 | B11: 甘肃 | C11: 46143 | D11: 983.69077 | E11: 125 | F11: 10.261247 | G11: 10.261247 | H11: 9.5866404
A12: =B12&C12 -> 甘肃46144 | B12: 甘肃 | C12: 46144 | D12: 983.69077 | E12: 125 | F12: 10.261247 | G12: 10.261247 | H12: 9.5866404
A13: =B13&C13 -> 甘肃46145 | B13: 甘肃 | C13: 46145 | D13: 983.69077 | E13: 125 | F13: 10.261247 | G13: 10.261247 | H13: 9.5866404
A14: =B14&C14 -> 甘肃46146 | B14: 甘肃 | C14: 46146 | D14: 983.69077 | E14: 125 | F14: 10.261247 | G14: 10.261247 | H14: 9.5866404
... A6074: =B6074&C6074 -> 江西46387 | B6074: 江西 | C6074: 46387 | D6074: 1003.3847 | E6074: 125 | F6074: 13.595936 | G6074: 13.595936 | H6074: 12.999565

Sheet 2.出品率表
B2: 分割父物料 | C2: 分割子物料 | D2: 产出率 | E2: 工艺 | F2: 是否储备
B3: 毛猪 | C3: 白条 | D3: 0.715 | E3: 屠宰 | F3: N
B4: 毛猪 | C4: 猪头 | D4: 0.043342238 | E4: 屠宰 | F4: N
B5: 毛猪 | C5: 猪蹄 | D5: 0.018327695 | E5: 屠宰 | F5: N
B6: 毛猪 | C6: 猪尾 | D6: 0.00032562132 | E6: 屠宰 | F6: N
B7: 毛猪 | C7: 猪心 | D7: 0.0030632399 | E7: 屠宰 | F7: N
B8: 毛猪 | C8: 猪肝 | D8: 0.015822797 | E8: 屠宰 | F8: N
B9: 毛猪 | C9: 猪腰 | D9: 0.0030934025 | E9: 屠宰 | F9: N
B10: 毛猪 | C10: 大肠 | D10: 0.010824799 | E10: 屠宰 | F10: N
B11: 毛猪 | C11: 猪肚 | D11: 0.0049657251 | E11: 屠宰 | F11: N
B12: 毛猪 | C12: 罗膈肉 | D12: 0.0041516718 | E12: 屠宰 | F12: N
B13: 毛猪 | C13: 猪舌 | D13: 0.0036632399 | E13: 屠宰 | F13: N
B14: 毛猪 | C14: 大肠头 | D14: 0.0026863759 | E14: 屠宰 | F14: N
... B99: 猪血 | C99: 猪血-冷冻 | D99: 0.99 | E99: 冷冻 | F99: N

Sheet 3.屠宰能力表
B2: 屠宰厂id | C2: 公司名称 | D2: 所属省份 | E2: 屠宰产能-头/日
B3: 0567 | C3: 正大食品（襄阳）有限公司 | D3: 湖北 | E3: 3200
B4: 0555 | C4: 洛阳正大食品有限公司 | D4: 河南 | E4: 3200
B5: 0476 | C5: 正大食品（徐州）有限公司 | D5: 江苏 | E5: 3200
B6: 0370 | C6: 内蒙古正大鸿业食品有限公司 | D6: 内蒙古 | E6: 4800
B7: 0377 | C7: 山西正大食品有限公司 | D7: 山西 | E7: 800
B8: 0388 | C8: 甘肃庆阳正大食品有限公司 | D8: 甘肃 | E8: 900
B9: 0638 | C9: 成都正大农牧食品有限公司 | D9: 四川 | E9: 1500
B10: 1533 | C10: 正大食品（长沙）有限公司 | D10: 湖南 | E10: 838
B11: A388 | C11: 庆阳正大食品有限公司OEM | D11: 甘肃 | E11: 300
B12: 0294 | C12: 正大畜牧(阜新)有限公司 | D12: 辽宁 | E12: 2739.726
B13: 0261 | C13: 吉林中新正大食品有限公司 | D13: 吉林 | E13: 1500
B14: 0360 | C14: 新疆正大畜禽有限公司 | D14: 新疆 | E14: 150
... B17: 0648 | C17: 昆明正大猪业有限公司 | D17: 云南 | E17: 900
B18: 1522 | C18: 正大食品（咸宁）有限公司 | D18: 湖北 | E18: 1820
B19: 1521 | C19: 正大食品（宜昌）有限公司 | D19: 湖北 | E19: 550
B20: 1850 | C20: 江西正大畜禽有限公司高安分公司 | D20: 江西 | E20: 1370
B21: 0692 | C21: 正大食品（来宾）有限公司 | D21: 广西 | E21: 2000
B22: 0662 | C22: 贵州正大农牧食品有限公司 | D22: 贵州 | E22: 1000
B23: 1658 | C23: 正大卜蜂食品(重庆)有限公司 | D23: 重庆 | E23: 1000
B24: 1441 | C24: 正大食品（徐州）有限公司山东第二分公司 | D24: 山东 | E24: 1500
B25: 1810 | C25: 正大食品（广东）有限公司 | D25: 广东 | E25: 1590

Sheet 4.分割能力表
B2: 屠宰厂id | C2: 公司名称 | D2: 分割能力上限-头 | E2: 冷冻能力上限-kg
B3: 0567 | C3: 正大食品（襄阳）有限公司 | D3: 1600 | E3: 72000
B4: 0555 | C4: 洛阳正大食品有限公司 | D4: 960 | E4: 60000
B5: 0476 | C5: 正大食品（徐州）有限公司 | D5: 1600 | E5: 72000
B6: 0370 | C6: 内蒙古正大鸿业食品有限公司 | D6: 1600 | E6: 100000
B7: 0377 | C7: 山西正大食品有限公司 | D7: 480 | E7: 20000
B8: 0388 | C8: 甘肃庆阳正大食品有限公司 | D8: 640 | E8: 30000
B9: 0638 | C9: 成都正大农牧食品有限公司 | D9: 400 | E9: 7500
B10: 1533 | C10: 正大食品（长沙）有限公司 | D10: 320 | E10: 7500
B11: A388 | C11: 庆阳正大食品有限公司OEM | D11: 0 | E11: 0
B12: 0294 | C12: 正大畜牧(阜新)有限公司 | D12: 0 | E12: 0
B13: 0261 | C13: 吉林中新正大食品有限公司 | D13: 0 | E13: 0
B14: 0360 | C14: 新疆正大畜禽有限公司 | D14: 0 | E14: 0
... B17: 0648 | C17: 昆明正大猪业有限公司 | D17: 260 | E17: 0
B18: 1522 | C18: 正大食品（咸宁）有限公司 | D18: 0 | E18: 0
B19: 1521 | C19: 正大食品（宜昌）有限公司 | D19: 0 | E19: 0
B20: 1850 | C20: 江西正大畜禽有限公司高安分公司 | D20: 1000 | E20: 0
B21: 0692 | C21: 正大食品（来宾）有限公司 | D21: 700 | E21: 0
B22: 0662 | C22: 贵州正大农牧食品有限公司 | D22: 200 | E22: 0
B23: 1658 | C23: 正大卜蜂食品(重庆)有限公司 | D23: 500 | E23: 0
B24: 1441 | C24: 正大食品（徐州）有限公司山东第二分公司 | D24: 1000 | E24: 0
B25: 1810 | C25: 正大食品（广东）有限公司 | D25: 0 | E25: 0

Sheet 5.成本表
B2: 工厂id | C2: 公司名称 | D2: 分割部位 | E2: 屠宰成本-元/kg | F2: 分割费用-元/kg | G2: 包装费用-元/kg | H2: 速冻费用-元/kg | I2: 成本系数-后期统计用
B3: 0567 | C3: 正大食品（襄阳）有限公司 | D3: 白条 | E3: =IFERROR(VLOOKUP($B3,'标准费用表-2024年&2025年优化'!$D:$K,8,0)*VLOOKUP('5.成本表'!$D3,系数辅助表!$C:$G,5,0)/VLOOKUP($D3,系数辅助表!$C:$E,3,0),0) -> 0.3962704 | I3: =VLOOKUP($D3,系数辅助表!$C:$F,4,0) -> 1.33 | J3: 白条
B4: 0567 | C4: 正大食品（襄阳）有限公司 | D4: 猪头 | E4: =IFERROR(VLOOKUP($B4,'标准费用表-2024年&2025年优化'!$D:$K,8,0)*系数辅助表!$J$6*VLOOKUP('5.成本表'!$D4,系数辅助表!$C:$G,5,0)/VLOOKUP($D4,系数辅助表!$C:$E,3,0),0) -> 0.22664346 | I4: =VLOOKUP($D4,系数辅助表!$C:$F,4,0) -> 0.78902786 | J4: 副产
B5: 0567 | C5: 正大食品（襄阳）有限公司 | D5: 猪蹄 | E5: =IFERROR(VLOOKUP($B5,'标准费用表-2024年&2025年优化'!$D:$K,8,0)*系数辅助表!$J$6*VLOOKUP('5.成本表'!$D5,系数辅助表!$C:$G,5,0)/VLOOKUP($D5,系数辅助表!$C:$E,3,0),0) -> 0.60573265 | I5: =VLOOKUP($D5,系数辅助表!$C:$F,4,0) -> 2.1087745 | J5: 副产
B6: 0567 | C6: 正大食品（襄阳）有限公司 | D6: 猪尾 | E6: =IFERROR(VLOOKUP($B6,'标准费用表-2024年&2025年优化'!$D:$K,8,0)*系数辅助表!$J$6*VLOOKUP('5.成本表'!$D6,系数辅助表!$C:$G,5,0)/VLOOKUP($D6,系数辅助表!$C:$E,3,0),0) -> 1.1211469 | I6: =VLOOKUP($D6,系数辅助表!$C:$F,4,0) -> 3.903118 | J6: 副产
B7: 0567 | C7: 正大食品（襄阳）有限公司 | D7: 猪心 | E7: =IFERROR(VLOOKUP($B7,'标准费用表-2024年&2025年优化'!$D:$K,8,0)*系数辅助表!$J$6*VLOOKUP('5.成本表'!$D7,系数辅助表!$C:$G,5,0)/VLOOKUP($D7,系数辅助表!$C:$E,3,0),0) -> 0.23561474 | I7: =VLOOKUP($D7,系数辅助表!$C:$F,4,0) -> 0.82026014 | J7: 副产
B8: 0567 | C8: 正大食品（襄阳）有限公司 | D8: 猪肝 | E8: =IFERROR(VLOOKUP($B8,'标准费用表-2024年&2025年优化'!$D:$K,8,0)*系数辅助表!$J$6*VLOOKUP('5.成本表'!$D8,系数辅助表!$C:$G,5,0)/VLOOKUP($D8,系数辅助表!$C:$E,3,0),0) -> 0.10401791 | I8: =VLOOKUP($D8,系数辅助表!$C:$F,4,0) -> 0.36212396 | J8: 副产
B9: 0567 | C9: 正大食品（襄阳）有限公司 | D9: 猪腰 | E9: =IFERROR(VLOOKUP($B9,'标准费用表-2024年&2025年优化'!$D:$K,8,0)*系数辅助表!$J$6*VLOOKUP('5.成本表'!$D9,系数辅助表!$C:$G,5,0)/VLOOKUP($D9,系数辅助表!$C:$E,3,0),0) -> 0.32192162 | I9: =VLOOKUP($D9,系数辅助表!$C:$F,4,0) -> 1.1207256 | J9: 副产
B10: 0567 | C10: 正大食品（襄阳）有限公司 | D10: 大肠 | E10: =IFERROR(VLOOKUP($B10,'标准费用表-2024年&2025年优化'!$D:$K,8,0)*系数辅助表!$J$6*VLOOKUP('5.成本表'!$D10,系数辅助表!$C:$G,5,0)/VLOOKUP($D10,系数辅助表!$C:$E,3,0),0) -> 0.53178934 | I10: =VLOOKUP($D10,系数辅助表!$C:$F,4,0) -> 1.851351 | J10: 副产
B11: 0567 | C11: 正大食品（襄阳）有限公司 | D11: 猪肚 | E11: =IFERROR(VLOOKUP($B11,'标准费用表-2024年&2025年优化'!$D:$K,8,0)*系数辅助表!$J$6*VLOOKUP('5.成本表'!$D11,系数辅助表!$C:$G,5,0)/VLOOKUP($D11,系数辅助表!$C:$E,3,0),0) -> 0.77143748 | I11: =VLOOKUP($D11,系数辅助表!$C:$F,4,0) -> 2.6856529 | J11: 副产
B12: 0567 | C12: 正大食品（襄阳）有限公司 | D12: 罗膈肉 | E12: =IFERROR(VLOOKUP($B12,'标准费用表-2024年&2025年优化'!$D:$K,8,0)*系数辅助表!$J$6*VLOOKUP('5.成本表'!$D12,系数辅助表!$C:$G,5,0)/VLOOKUP($D12,系数辅助表!$C:$E,3,0),0) -> 0.45070687 | I12: =VLOOKUP($D12,系数辅助表!$C:$F,4,0) -> 1.5690736 | J12: 副产
B13: 0567 | C13: 正大食品（襄阳）有限公司 | D13: 猪舌 | E13: =IFERROR(VLOOKUP($B13,'标准费用表-2024年&2025年优化'!$D:$K,8,0)*系数辅助表!$J$6*VLOOKUP('5.成本表'!$D13,系数辅助表!$C:$G,5,0)/VLOOKUP($D13,系数辅助表!$C:$E,3,0),0) -> 0.41391117 | I13: =VLOOKUP($D13,系数辅助表!$C:$F,4,0) -> 1.4409745 | J13: 副产
B14: 0567 | C14: 正大食品（襄阳）有限公司 | D14: 大肠头 | E14: =IFERROR(VLOOKUP($B14,'标准费用表-2024年&2025年优化'!$D:$K,8,0)*系数辅助表!$J$6*VLOOKUP('5.成本表'!$D14,系数辅助表!$C:$G,5,0)/VLOOKUP($D14,系数辅助表!$C:$E,3,0),0) -> 0.52876811 | I14: =VLOOKUP($D14,系数辅助表!$C:$F,4,0) -> 1.8408331 | J14: 副产
B15: 0567 | C15: 正大食品（襄阳）有限公司 | D15: 心血管 | E15: =IFERROR(VLOOKUP($B15,'标准费用表-2024年&2025年优化'!$D:$K,8,0)*系数辅助表!$J$6*VLOOKUP('5.成本表'!$D15,系数辅助表!$C:$G,5,0)/VLOOKUP($D15,系数辅助表!$C:$E,3,0),0) -> 0.9196813 | I15: =VLOOKUP($D15,系数辅助表!$C:$F,4,0) -> 3.2017433 | J15: 副产
... B27: 0567 | C27: 正大食品（襄阳）有限公司 | D27: 猪血 | E27: =IFERROR(VLOOKUP($B27,'标准费用表-2024年&2025年优化'!$D:$K,8,0)*系数辅助表!$J$6*VLOOKUP('5.成本表'!$D27,系数辅助表!$C:$G,5,0)/VLOOKUP($D27,系数辅助表!$C:$E,3,0),0) -> 0.024372263 | I27: =VLOOKUP($D27,系数辅助表!$C:$F,4,0) -> 0.084848664 | J27: 副产
B28: 0567 | C28: 正大食品（襄阳）有限公司 | D28: 五花肉 | E28: =IFERROR(VLOOKUP($B28,'标准费用表-2024年&2025年优化'!$D:$K,8,0)*VLOOKUP("白条",系数辅助表!$C:$G,5,0)*VLOOKUP('5.成本表'!$D28,系数辅助表!$C:$G,5,0)/VLOOKUP('5.成本表'!$D28,系数辅助表!$C:$E,3,0),) -> 0.59393064 | F28: =IFERROR(VLOOKUP($B28,'标准费用表-2024年&2025年优化'!$D:$L,9,0)*VLOOKUP('5.成本表'!$D28,系数辅助表!$C:$G,5,0)/VLOOKUP($D28,系数辅助表!$C:$E,3,0),0) -> 1.3974839 | I28: =VLOOKUP($D28,系数辅助表!$C:$F,4,0) -> 2.28 | J28: 分割
B29: 0567 | C29: 正大食品（襄阳）有限公司 | D29: 大排肌肉 | E29: =IFERROR(VLOOKUP($B29,'标准费用表-2024年&2025年优化'!$D:$K,8,0)*VLOOKUP("白条",系数辅助表!$C:$G,5,0)*VLOOKUP('5.成本表'!$D29,系数辅助表!$C:$G,5,0)/VLOOKUP('5.成本表'!$D29,系数辅助表!$C:$E,3,0),) -> 0.39692367 | F29: =IFERROR(VLOOKUP($B29,'标准费用表-2024年&2025年优化'!$D:$L,9,0)*VLOOKUP('5.成本表'!$D29,系数辅助表!$C:$G,5,0)/VLOOKUP($D29,系数辅助表!$C:$E,3,0),0) -> 0.93393805 | I29: =VLOOKUP($D29,系数辅助表!$C:$F,4,0) -> 1.5237233 | J29: 分割
B30: 0567 | C30: 正大食品（襄阳）有限公司 | D30: 肋排 | E30: =IFERROR(VLOOKUP($B30,'标准费用表-2024年&2025年优化'!$D:$K,8,0)*VLOOKUP("白条",系数辅助表!$C:$G,5,0)*VLOOKUP('5.成本表'!$D30,系数辅助表!$C:$G,5,0)/VLOOKUP('5.成本表'!$D30,系数辅助表!$C:$E,3,0),) -> 1.0504904 | F30: =IFERROR(VLOOKUP($B30,'标准费用表-2024年&2025年优化'!$D:$L,9,0)*VLOOKUP('5.成本表'!$D30,系数辅助表!$C:$G,5,0)/VLOOKUP($D30,系数辅助表!$C:$E,3,0),0) -> 2.4717422 | I30: =VLOOKUP($D30,系数辅助表!$C:$F,4,0) -> 4.0326564 | J30: 分割
B31: 0567 | C31: 正大食品（襄阳）有限公司 | D31: 前排 | E31: =IFERROR(VLOOKUP($B31,'标准费用表-2024年&2025年优化'!$D:$K,8,0)*VLOOKUP("白条",系数辅助表!$C:$G,5,0)*VLOOKUP('5.成本表'!$D31,系数辅助表!$C:$G,5,0)/VLOOKUP('5.成本表'!$D31,系数辅助表!$C:$E,3,0),) -> 0.61179544 | F31: =IFERROR(VLOOKUP($B31,'标准费用表-2024年&2025年优化'!$D:$L,9,0)*VLOOKUP('5.成本表'!$D31,系数辅助表!$C:$G,5,0)/VLOOKUP($D31,系数辅助表!$C:$E,3,0),0) -> 1.4395187 | I31: =VLOOKUP($D31,系数辅助表!$C:$F,4,0) -> 2.34858 | J31: 分割
B32: 0567 | C32: 正大食品（襄阳）有限公司 | D32: 颈背肌肉 | E32: =IFERROR(VLOOKUP($B32,'标准费用表-2024年&2025年优化'!$D:$K,8,0)*VLOOKUP("白条",系数辅助表!$C:$G,5,0)*VLOOKUP('5.成本表'!$D32,系数辅助表!$C:$G,5,0)/VLOOKUP('5.成本表'!$D32,系数辅助表!$C:$E,3,0),) -> 0.36752765 | F32: =IFERROR(VLOOKUP($B32,'标准费用表-2024年&2025年优化'!$D:$L,9,0)*VLOOKUP('5.成本表'!$D32,系数辅助表!$C:$G,5,0)/VLOOKUP($D32,系数辅助表!$C:$E,3,0),0) -> 0.86477094 | I32: =VLOOKUP($D32,系数辅助表!$C:$F,4,0) -> 1.4108769 | J32: 分割
B33: 0567 | C33: 正大食品（襄阳）有限公司 | D33: 小里脊 | E33: =IFERROR(VLOOKUP($B33,'标准费用表-2024年&2025年优化'!$D:$K,8,0)*VLOOKUP("白条",系数辅助表!$C:$G,5,0)*VLOOKUP('5.成本表'!$D33,系数辅助表!$C:$G,5,0)/VLOOKUP('5.成本表'!$D33,系数辅助表!$C:$E,3,0),) -> 0.49627133 | F33: =IFERROR(VLOOKUP($B33,'标准费用表-2024年&2025年优化'!$D:$L,9,0)*VLOOKUP('5.成本表'!$D33,系数辅助表!$C:$G,5,0)/VLOOKUP($D33,系数辅助表!$C:$E,3,0),0) -> 1.1676972 | I33: =VLOOKUP($D33,系数辅助表!$C:$F,4,0) -> 1.9051023 | J33: 分割
B34: 0567 | C34: 正大食品（襄阳）有限公司 | D34: 前腿肌肉 | E34: =IFERROR(VLOOKUP($B34,'标准费用表-2024年&2025年优化'!$D:$K,8,0)*VLOOKUP("白条",系数辅助表!$C:$G,5,0)*VLOOKUP('5.成本表'!$D34,系数辅助表!$C:$G,5,0)/VLOOKUP('5.成本表'!$D34,系数辅助表!$C:$E,3,0),) -> 0.37160154 | F34: =IFERROR(VLOOKUP($B34,'标准费用表-2024年&2025年优化'!$D:$L,9,0)*VLOOKUP('5.成本表'!$D34,系数辅助表!$C:$G,5,0)/VLOOKUP($D34,系数辅助表!$C:$E,3,0),0) -> 0.87435657 | I34: =VLOOKUP($D34,系数辅助表!$C:$F,4,0) -> 1.4265159 | J34: 分割
B35: 0567 | C35: 正大食品（襄阳）有限公司 | D35: 后腿肌肉 | E35: =IFERROR(VLOOKUP($B35,'标准费用表-2024年&2025年优化'!$D:$K,8,0)*VLOOKUP("白条",系数辅助表!$C:$G,5,0)*VLOOKUP('5.成本表'!$D35,系数辅助表!$C:$G,5,0)/VLOOKUP('5.成本表'!$D35,系数辅助表!$C:$E,3,0),) -> 0.3786523 | F35: =IFERROR(VLOOKUP($B35,'标准费用表-2024年&2025年优化'!$D:$L,9,0)*VLOOKUP('5.成本表'!$D35,系数辅助表!$C:$G,5,0)/VLOOKUP($D35,系数辅助表!$C:$E,3,0),0) -> 0.89094658 | I35: =VLOOKUP($D35,系数辅助表!$C:$F,4,0) -> 1.4535826 | J35: 分割
B36: 0567 | C36: 正大食品（襄阳）有限公司 | D36: 前肘 | E36: =IFERROR(VLOOKUP($B36,'标准费用表-2024年&2025年优化'!$D:$K,8,0)*VLOOKUP("白条",系数辅助表!$C:$G,5,0)*VLOOKUP('5.成本表'!$D36,系数辅助表!$C:$G,5,0)/VLOOKUP('5.成本表'!$D36,系数辅助表!$C:$E,3,0),) -> 0.37538452 | F36: =IFERROR(VLOOKUP($B36,'标准费用表-2024年&2025年优化'!$D:$L,9,0)*VLOOKUP('5.成本表'!$D36,系数辅助表!$C:$G,5,0)/VLOOKUP($D36,系数辅助表!$C:$E,3,0),0) -> 0.88325769 | I36: =VLOOKUP($D36,系数辅助表!$C:$F,4,0) -> 1.4410381 | J36: 分割
B37: 0567 | C37: 正大食品（襄阳）有限公司 | D37: 后肘 | E37: =IFERROR(VLOOKUP($B37,'标准费用表-2024年&2025年优化'!$D:$K,8,0)*VLOOKUP("白条",系数辅助表!$C:$G,5,0)*VLOOKUP('5.成本表'!$D37,系数辅助表!$C:$G,5,0)/VLOOKUP('5.成本表'!$D37,系数辅助表!$C:$E,3,0),) -> 0.32192933 | F37: =IFERROR(VLOOKUP($B37,'标准费用表-2024年&2025年优化'!$D:$L,9,0)*VLOOKUP('5.成本表'!$D37,系数辅助表!$C:$G,5,0)/VLOOKUP($D37,系数辅助表!$C:$E,3,0),0) -> 0.75748077 | I37: =VLOOKUP($D37,系数辅助表!$C:$F,4,0) -> 1.2358326 | J37: 分割
B38: 0567 | C38: 正大食品（襄阳）有限公司 | D38: 肥膘 | E38: =IFERROR(VLOOKUP($B38,'标准费用表-2024年&2025年优化'!$D:$K,8,0)*VLOOKUP("白条",系数辅助表!$C:$G,5,0)*VLOOKUP('5.成本表'!$D38,系数辅助表!$C:$G,5,0)/VLOOKUP('5.成本表'!$D38,系数辅助表!$C:$E,3,0),) -> 0.22486449 | F38: =IFERROR(VLOOKUP($B38,'标准费用表-2024年&2025年优化'!$D:$L,9,0)*VLOOKUP('5.成本表'!$D38,系数辅助表!$C:$G,5,0)/VLOOKUP($D38,系数辅助表!$C:$E,3,0),0) -> 0.52909292 | I38: =VLOOKUP($D38,系数辅助表!$C:$F,4,0) -> 0.86321702 | J38: 分割
B39: 0567 | C39: 正大食品（襄阳）有限公司 | D39: 脊膘 | E39: =IFERROR(VLOOKUP($B39,'标准费用表-2024年&2025年优化'!$D:$K,8,0)*VLOOKUP("白条",系数辅助表!$C:$G,5,0)*VLOOKUP('5.成本表'!$D39,系数辅助表!$C:$G,5,0)/VLOOKUP('5.成本表'!$D39,系数辅助表!$C:$E,3,0),) -> 0.20758239 | F39: =IFERROR(VLOOKUP($B39,'标准费用表-2024年&2025年优化'!$D:$L,9,0)*VLOOKUP('5.成本表'!$D39,系数辅助表!$C:$G,5,0)/VLOOKUP($D39,系数辅助表!$C:$E,3,0),0) -> 0.48842915 | I39: =VLOOKUP($D39,系数辅助表!$C:$F,4,0) -> 0.79687393 | J39: 分割
... B51: 0567 | C51: 正大食品（襄阳）有限公司 | D51: 碎皮 | E51: =IFERROR(VLOOKUP($B51,'标准费用表-2024年&2025年优化'!$D:$K,8,0)*VLOOKUP("白条",系数辅助表!$C:$G,5,0)*VLOOKUP('5.成本表'!$D51,系数辅助表!$C:$G,5,0)/VLOOKUP('5.成本表'!$D51,系数辅助表!$C:$E,3,0),) -> 0.062665133 | F51: =IFERROR(VLOOKUP($B51,'标准费用表-2024年&2025年优化'!$D:$L,9,0)*VLOOKUP('5.成本表'!$D51,系数辅助表!$C:$G,5,0)/VLOOKUP($D51,系数辅助表!$C:$E,3,0),0) -> 0.14744737 | I51: =VLOOKUP($D51,系数辅助表!$C:$F,4,0) -> 0.24056092 | J51: 分割
B52: 0567 | C52: 正大食品（襄阳）有限公司 | D52: 五花肉-冷冻 | E52: =E28 -> 0.59393064 | F52: =F28 -> 1.3974839 | G52: 0.2 | H52: 0.3 | J52: 分割
B53: 0567 | C53: 正大食品（襄阳）有限公司 | D53: 大排肌肉-冷冻 | E53: =E29 -> 0.39692367 | F53: =F29 -> 0.93393805 | G53: 0.2 | H53: 0.3 | J53: 分割
B54: 0567 | C54: 正大食品（襄阳）有限公司 | D54: 肋排-冷冻 | E54: =E30 -> 1.0504904 | F54: =F30 -> 2.4717422 | G54: 0.2 | H54: 0.3 | J54: 分割
B55: 0567 | C55: 正大食品（襄阳）有限公司 | D55: 前排-冷冻 | E55: =E31 -> 0.61179544 | F55: =F31 -> 1.4395187 | G55: 0.2 | H55: 0.3 | J55: 分割
B56: 0567 | C56: 正大食品（襄阳）有限公司 | D56: 颈背肌肉-冷冻 | E56: =E32 -> 0.36752765 | F56: =F32 -> 0.86477094 | G56: 0.2 | H56: 0.3 | J56: 分割
B57: 0567 | C57: 正大食品（襄阳）有限公司 | D57: 小里脊-冷冻 | E57: =E33 -> 0.49627133 | F57: =F33 -> 1.1676972 | G57: 0.2 | H57: 0.3 | J57: 分割
B58: 0567 | C58: 正大食品（襄阳）有限公司 | D58: 前腿肌肉-冷冻 | E58: =E34 -> 0.37160154 | F58: =F34 -> 0.87435657 | G58: 0.2 | H58: 0.3 | J58: 分割
B59: 0567 | C59: 正大食品（襄阳）有限公司 | D59: 后腿肌肉-冷冻 | E59: =E35 -> 0.3786523 | F59: =F35 -> 0.89094658 | G59: 0.2 | H59: 0.3 | J59: 分割
B60: 0567 | C60: 正大食品（襄阳）有限公司 | D60: 前肘-冷冻 | E60: =E36 -> 0.37538452 | F60: =F36 -> 0.88325769 | G60: 0.2 | H60: 0.3 | J60: 分割
B61: 0567 | C61: 正大食品（襄阳）有限公司 | D61: 后肘-冷冻 | E61: =E37 -> 0.32192933 | F61: =F37 -> 0.75748077 | G61: 0.2 | H61: 0.3 | J61: 分割
B62: 0567 | C62: 正大食品（襄阳）有限公司 | D62: 肥膘-冷冻 | E62: =E38 -> 0.22486449 | F62: =F38 -> 0.52909292 | G62: 0.2 | H62: 0.3 | J62: 分割
B63: 0567 | C63: 正大食品（襄阳）有限公司 | D63: 脊膘-冷冻 | E63: =E39 -> 0.20758239 | F63: =F39 -> 0.48842915 | G63: 0.2 | H63: 0.3 | J63: 分割
... B75: 0567 | C75: 正大食品（襄阳）有限公司 | D75: 碎皮-冷冻 | E75: =E51 -> 0.062665133 | F75: =F51 -> 0.14744737 | G75: 0.2 | H75: 0.3 | J75: 分割
B76: 0567 | C76: 正大食品（襄阳）有限公司 | D76: 猪头-冷冻 | E76: =E4 -> 0.22664346 | F76: =F52 -> 1.3974839 | G76: 0.2 | H76: 0.3 | J76: 分割
B77: 0567 | C77: 正大食品（襄阳）有限公司 | D77: 猪蹄-冷冻 | E77: =E5 -> 0.60573265 | F77: =F53 -> 0.93393805 | G77: 0.2 | H77: 0.3 | J77: 分割
B78: 0567 | C78: 正大食品（襄阳）有限公司 | D78: 猪尾-冷冻 | E78: =E6 -> 1.1211469 | F78: =F54 -> 2.4717422 | G78: 0.2 | H78: 0.3 | J78: 分割
B79: 0567 | C79: 正大食品（襄阳）有限公司 | D79: 猪心-冷冻 | E79: =E7 -> 0.23561474 | F79: =F55 -> 1.4395187 | G79: 0.2 | H79: 0.3 | J79: 分割
B80: 0567 | C80: 正大食品（襄阳）有限公司 | D80: 猪肝-冷冻 | E80: =E8 -> 0.10401791 | F80: =F56 -> 0.86477094 | G80: 0.2 | H80: 0.3 | J80: 分割
B81: 0567 | C81: 正大食品（襄阳）有限公司 | D81: 猪腰-冷冻 | E81: =E9 -> 0.32192162 | F81: =F57 -> 1.1676972 | G81: 0.2 | H81: 0.3 | J81: 分割
B82: 0567 | C82: 正大食品（襄阳）有限公司 | D82: 大肠-冷冻 | E82: =E10 -> 0.53178934 | F82: =F58 -> 0.87435657 | G82: 0.2 | H82: 0.3 | J82: 分割
B83: 0567 | C83: 正大食品（襄阳）有限公司 | D83: 猪肚-冷冻 | E83: =E11 -> 0.77143748 | F83: =F59 -> 0.89094658 | G83: 0.2 | H83: 0.3 | J83: 分割
B84: 0567 | C84: 正大食品（襄阳）有限公司 | D84: 罗膈肉-冷冻 | E84: =E12 -> 0.45070687 | F84: =F60 -> 0.88325769 | G84: 0.2 | H84: 0.3 | J84: 分割
B85: 0567 | C85: 正大食品（襄阳）有限公司 | D85: 猪舌-冷冻 | E85: =E13 -> 0.41391117 | F85: =F61 -> 0.75748077 | G85: 0.2 | H85: 0.3 | J85: 分割
B86: 0567 | C86: 正大食品（襄阳）有限公司 | D86: 大肠头-冷冻 | E86: =E14 -> 0.52876811 | F86: =F62 -> 0.52909292 | G86: 0.2 | H86: 0.3 | J86: 分割
B87: 0567 | C87: 正大食品（襄阳）有限公司 | D87: 心血管-冷冻 | E87: =E15 -> 0.9196813 | F87: =F63 -> 0.48842915 | G87: 0.2 | H87: 0.3 | J87: 分割
... B99: 0567 | C99: 正大食品（襄阳）有限公司 | D99: 猪血-冷冻 | E99: =E27 -> 0.024372263 | F99: =F75 -> 0.14744737 | G99: 0.2 | H99: 0.3 | J99: 分割
B100: 0555 | C100: =VLOOKUP($B100,'标准费用表-2024年&2025年优化'!$D:$E,2,0) -> 洛阳正大食品有限公司 | D100: 白条 | E100: =IFERROR(VLOOKUP($B100,'标准费用表-2024年&2025年优化'!$D:$K,8,0)*VLOOKUP('5.成本表'!$D100,系数辅助表!$C:$G,5,0)/VLOOKUP($D100,系数辅助表!$C:$E,3,0),0) -> 0.32189369 | I100: =VLOOKUP($D100,系数辅助表!$C:$F,4,0) -> 1.33 | J100: 白条
B101: 0555 | C101: =VLOOKUP($B101,'标准费用表-2024年&2025年优化'!$D:$E,2,0) -> 洛阳正大食品有限公司 | D101: 猪头 | E101: =IFERROR(VLOOKUP($B101,'标准费用表-2024年&2025年优化'!$D:$K,8,0)*系数辅助表!$J$6*VLOOKUP('5.成本表'!$D101,系数辅助表!$C:$G,5,0)/VLOOKUP($D101,系数辅助表!$C:$E,3,0),0) -> 0.18410433 | I101: =VLOOKUP($D101,系数辅助表!$C:$F,4,0) -> 0.78902786 | J101: 副产
B102: 0555 | C102: =VLOOKUP($B102,'标准费用表-2024年&2025年优化'!$D:$E,2,0) -> 洛阳正大食品有限公司 | D102: 猪蹄 | E102: =IFERROR(VLOOKUP($B102,'标准费用表-2024年&2025年优化'!$D:$K,8,0)*系数辅助表!$J$6*VLOOKUP('5.成本表'!$D102,系数辅助表!$C:$G,5,0)/VLOOKUP($D102,系数辅助表!$C:$E,3,0),0) -> 0.49204159 | I102: =VLOOKUP($D102,系数辅助表!$C:$F,4,0) -> 2.1087745 | J102: 副产
B103: 0555 | C103: =VLOOKUP($B103,'标准费用表-2024年&2025年优化'!$D:$E,2,0) -> 洛阳正大食品有限公司 | D103: 猪尾 | E103: =IFERROR(VLOOKUP($B103,'标准费用表-2024年&2025年优化'!$D:$K,8,0)*系数辅助表!$J$6*VLOOKUP('5.成本表'!$D103,系数辅助表!$C:$G,5,0)/VLOOKUP($D103,系数辅助表!$C:$E,3,0),0) -> 0.91071682 | I103: =VLOOKUP($D103,系数辅助表!$C:$F,4,0) -> 3.903118 | J103: 副产
B104: 0555 | C104: =VLOOKUP($B104,'标准费用表-2024年&2025年优化'!$D:$E,2,0) -> 洛阳正大食品有限公司 | D104: 猪心 | E104: =IFERROR(VLOOKUP($B104,'标准费用表-2024年&2025年优化'!$D:$K,8,0)*系数辅助表!$J$6*VLOOKUP('5.成本表'!$D104,系数辅助表!$C:$G,5,0)/VLOOKUP($D104,系数辅助表!$C:$E,3,0),0) -> 0.19139178 | I104: =VLOOKUP($D104,系数辅助表!$C:$F,4,0) -> 0.82026014 | J104: 副产
B105: 0555 | C105: =VLOOKUP($B105,'标准费用表-2024年&2025年优化'!$D:$E,2,0) -> 洛阳正大食品有限公司 | D105: 猪肝 | E105: =IFERROR(VLOOKUP($B105,'标准费用表-2024年&2025年优化'!$D:$K,8,0)*系数辅助表!$J$6*VLOOKUP('5.成本表'!$D105,系数辅助表!$C:$G,5,0)/VLOOKUP($D105,系数辅助表!$C:$E,3,0),0) -> 0.084494598 | I105: =VLOOKUP($D105,系数辅助表!$C:$F,4,0) -> 0.36212396 | J105: 副产
B106: 0555 | C106: =VLOOKUP($B106,'标准费用表-2024年&2025年优化'!$D:$E,2,0) -> 洛阳正大食品有限公司 | D106: 猪腰 | E106: =IFERROR(VLOOKUP($B106,'标准费用表-2024年&2025年优化'!$D:$K,8,0)*系数辅助表!$J$6*VLOOKUP('5.成本表'!$D106,系数辅助表!$C:$G,5,0)/VLOOKUP($D106,系数辅助表!$C:$E,3,0),0) -> 0.26149957 | I106: =VLOOKUP($D106,系数辅助表!$C:$F,4,0) -> 1.1207256 | J106: 副产
B107: 0555 | C107: =VLOOKUP($B107,'标准费用表-2024年&2025年优化'!$D:$E,2,0) -> 洛阳正大食品有限公司 | D107: 大肠 | E107: =IFERROR(VLOOKUP($B107,'标准费用表-2024年&2025年优化'!$D:$K,8,0)*系数辅助表!$J$6*VLOOKUP('5.成本表'!$D107,系数辅助表!$C:$G,5,0)/VLOOKUP($D107,系数辅助表!$C:$E,3,0),0) -> 0.43197683 | I107: =VLOOKUP($D107,系数辅助表!$C:$F,4,0) -> 1.851351 | J107: 副产
B108: 0555 | C108: =VLOOKUP($B108,'标准费用表-2024年&2025年优化'!$D:$E,2,0) -> 洛阳正大食品有限公司 | D108: 猪肚 | E108: =IFERROR(VLOOKUP($B108,'标准费用表-2024年&2025年优化'!$D:$K,8,0)*系数辅助表!$J$6*VLOOKUP('5.成本表'!$D108,系数辅助表!$C:$G,5,0)/VLOOKUP($D108,系数辅助表!$C:$E,3,0),0) -> 0.62664499 | I108: =VLOOKUP($D108,系数辅助表!$C:$F,4,0) -> 2.6856529 | J108: 副产
B109: 0555 | C109: =VLOOKUP($B109,'标准费用表-2024年&2025年优化'!$D:$E,2,0) -> 洛阳正大食品有限公司 | D109: 罗膈肉 | E109: =IFERROR(VLOOKUP($B109,'标准费用表-2024年&2025年优化'!$D:$K,8,0)*系数辅助表!$J$6*VLOOKUP('5.成本表'!$D109,系数辅助表!$C:$G,5,0)/VLOOKUP($D109,系数辅助表!$C:$E,3,0),0) -> 0.36611288 | I109: =VLOOKUP($D109,系数辅助表!$C:$F,4,0) -> 1.5690736 | J109: 副产
B110: 0555 | C110: =VLOOKUP($B110,'标准费用表-2024年&2025年优化'!$D:$E,2,0) -> 洛阳正大食品有限公司 | D110: 猪舌 | E110: =IFERROR(VLOOKUP($B110,'标准费用表-2024年&2025年优化'!$D:$K,8,0)*系数辅助表!$J$6*VLOOKUP('5.成本表'!$D110,系数辅助表!$C:$G,5,0)/VLOOKUP($D110,系数辅助表!$C:$E,3,0),0) -> 0.33622343 | I110: =VLOOKUP($D110,系数辅助表!$C:$F,4,0) -> 1.4409745 | J110: 副产
B111: 0555 | C111: =VLOOKUP($B111,'标准费用表-2024年&2025年优化'!$D:$E,2,0) -> 洛阳正大食品有限公司 | D111: 大肠头 | E111: =IFERROR(VLOOKUP($B111,'标准费用表-2024年&2025年优化'!$D:$K,8,0)*系数辅助表!$J$6*VLOOKUP('5.成本表'!$D111,系数辅助表!$C:$G,5,0)/VLOOKUP($D111,系数辅助表!$C:$E,3,0),0) -> 0.42952266 | I111: =VLOOKUP($D111,系数辅助表!$C:$F,4,0) -> 1.8408331 | J111: 副产
B112: 0555 | C112: =VLOOKUP($B112,'标准费用表-2024年&2025年优化'!$D:$E,2,0) -> 洛阳正大食品有限公司 | D112: 心血管 | E112: =IFERROR(VLOOKUP($B112,'标准费用表-2024年&2025年优化'!$D:$K,8,0)*系数辅助表!$J$6*VLOOKUP('5.成本表'!$D112,系数辅助表!$C:$G,5,0)/VLOOKUP($D112,系数辅助表!$C:$E,3,0),0) -> 0.74706465 | I112: =VLOOKUP($D112,系数辅助表!$C:$F,4,0) -> 3.2017433 | J112: 副产
... B124: 0555 | C124: =VLOOKUP($B124,'标准费用表-2024年&2025年优化'!$D:$E,2,0) -> 洛阳正大食品有限公司 | D124: 猪血 | E124: =IFERROR(VLOOKUP($B124,'标准费用表-2024年&2025年优化'!$D:$K,8,0)*系数辅助表!$J$6*VLOOKUP('5.成本表'!$D124,系数辅助表!$C:$G,5,0)/VLOOKUP($D124,系数辅助表!$C:$E,3,0),0) -> 0.019797789 | I124: =VLOOKUP($D124,系数辅助表!$C:$F,4,0) -> 0.084848664 | J124: 副产
B125: 0555 | C125: =VLOOKUP($B125,'标准费用表-2024年&2025年优化'!$D:$E,2,0) -> 洛阳正大食品有限公司 | D125: 五花肉 | E125: =IFERROR(VLOOKUP($B125,'标准费用表-2024年&2025年优化'!$D:$K,8,0)*VLOOKUP("白条",系数辅助表!$C:$G,5,0)*VLOOKUP('5.成本表'!$D125,系数辅助表!$C:$G,5,0)/VLOOKUP('5.成本表'!$D125,系数辅助表!$C:$E,3,0),) -> 0.48245472 | F125: =IFERROR(VLOOKUP($B125,'标准费用表-2024年&2025年优化'!$D:$L,9,0)*VLOOKUP('5.成本表'!$D125,系数辅助表!$C:$G,5,0)/VLOOKUP($D125,系数辅助表!$C:$E,3,0),0) -> 0.91634914 | I125: =VLOOKUP($D125,系数辅助表!$C:$F,4,0) -> 2.28 | J125: 分割
B126: 0555 | C126: =VLOOKUP($B126,'标准费用表-2024年&2025年优化'!$D:$E,2,0) -> 洛阳正大食品有限公司 | D126: 大排肌肉 | E126: =IFERROR(VLOOKUP($B126,'标准费用表-2024年&2025年优化'!$D:$K,8,0)*VLOOKUP("白条",系数辅助表!$C:$G,5,0)*VLOOKUP('5.成本表'!$D126,系数辅助表!$C:$G,5,0)/VLOOKUP('5.成本表'!$D126,系数辅助表!$C:$E,3,0),) -> 0.32242435 | F126: =IFERROR(VLOOKUP($B126,'标准费用表-2024年&2025年优化'!$D:$L,9,0)*VLOOKUP('5.成本表'!$D126,系数辅助表!$C:$G,5,0)/VLOOKUP($D126,系数辅助表!$C:$E,3,0),0) -> 0.61239586 | I126: =VLOOKUP($D126,系数辅助表!$C:$F,4,0) -> 1.5237233 | J126: 分割
B127: 0555 | C127: =VLOOKUP($B127,'标准费用表-2024年&2025年优化'!$D:$E,2,0) -> 洛阳正大食品有限公司 | D127: 肋排 | E127: =IFERROR(VLOOKUP($B127,'标准费用表-2024年&2025年优化'!$D:$K,8,0)*VLOOKUP("白条",系数辅助表!$C:$G,5,0)*VLOOKUP('5.成本表'!$D127,系数辅助表!$C:$G,5,0)/VLOOKUP('5.成本表'!$D127,系数辅助表!$C:$E,3,0),) -> 0.85332199 | F127: =IFERROR(VLOOKUP($B127,'标准费用表-2024年&2025年优化'!$D:$L,9,0)*VLOOKUP('5.成本表'!$D127,系数辅助表!$C:$G,5,0)/VLOOKUP($D127,系数辅助表!$C:$E,3,0),0) -> 1.6207549 | I127: =VLOOKUP($D127,系数辅助表!$C:$F,4,0) -> 4.0326564 | J127: 分割
B128: 0555 | C128: =VLOOKUP($B128,'标准费用表-2024年&2025年优化'!$D:$E,2,0) -> 洛阳正大食品有限公司 | D128: 前排 | E128: =IFERROR(VLOOKUP($B128,'标准费用表-2024年&2025年优化'!$D:$K,8,0)*VLOOKUP("白条",系数辅助表!$C:$G,5,0)*VLOOKUP('5.成本表'!$D128,系数辅助表!$C:$G,5,0)/VLOOKUP('5.成本表'!$D128,系数辅助表!$C:$E,3,0),) -> 0.49696645 | F128: =IFERROR(VLOOKUP($B128,'标准费用表-2024年&2025年优化'!$D:$L,9,0)*VLOOKUP('5.成本表'!$D128,系数辅助表!$C:$G,5,0)/VLOOKUP($D128,系数辅助表!$C:$E,3,0),0) -> 0.94391195 | I128: =VLOOKUP($D128,系数辅助表!$C:$F,4,0) -> 2.34858 | J128: 分割
B129: 0555 | C129: =VLOOKUP($B129,'标准费用表-2024年&2025年优化'!$D:$E,2,0) -> 洛阳正大食品有限公司 | D129: 颈背肌肉 | E129: =IFERROR(VLOOKUP($B129,'标准费用表-2024年&2025年优化'!$D:$K,8,0)*VLOOKUP("白条",系数辅助表!$C:$G,5,0)*VLOOKUP('5.成本表'!$D129,系数辅助表!$C:$G,5,0)/VLOOKUP('5.成本表'!$D129,系数辅助表!$C:$E,3,0),) -> 0.29854572 | F129: =IFERROR(VLOOKUP($B129,'标准费用表-2024年&2025年优化'!$D:$L,9,0)*VLOOKUP('5.成本表'!$D129,系数辅助表!$C:$G,5,0)/VLOOKUP($D129,系数辅助表!$C:$E,3,0),0) -> 0.56704205 | I129: =VLOOKUP($D129,系数辅助表!$C:$F,4,0) -> 1.4108769 | J129: 分割
B130: 0555 | C130: =VLOOKUP($B130,'标准费用表-2024年&2025年优化'!$D:$E,2,0) -> 洛阳正大食品有限公司 | D130: 小里脊 | E130: =IFERROR(VLOOKUP($B130,'标准费用表-2024年&2025年优化'!$D:$K,8,0)*VLOOKUP("白条",系数辅助表!$C:$G,5,0)*VLOOKUP('5.成本表'!$D130,系数辅助表!$C:$G,5,0)/VLOOKUP('5.成本表'!$D130,系数辅助表!$C:$E,3,0),) -> 0.40312526 | F130: =IFERROR(VLOOKUP($B130,'标准费用表-2024年&2025年优化'!$D:$L,9,0)*VLOOKUP('5.成本表'!$D130,系数辅助表!$C:$G,5,0)/VLOOKUP($D130,系数辅助表!$C:$E,3,0),0) -> 0.76567494 | I130: =VLOOKUP($D130,系数辅助表!$C:$F,4,0) -> 1.9051023 | J130: 分割
B131: 0555 | C131: =VLOOKUP($B131,'标准费用表-2024年&2025年优化'!$D:$E,2,0) -> 洛阳正大食品有限公司 | D131: 前腿肌肉 | E131: =IFERROR(VLOOKUP($B131,'标准费用表-2024年&2025年优化'!$D:$K,8,0)*VLOOKUP("白条",系数辅助表!$C:$G,5,0)*VLOOKUP('5.成本表'!$D131,系数辅助表!$C:$G,5,0)/VLOOKUP('5.成本表'!$D131,系数辅助表!$C:$E,3,0),) -> 0.30185498 | F131: =IFERROR(VLOOKUP($B131,'标准费用表-2024年&2025年优化'!$D:$L,9,0)*VLOOKUP('5.成本表'!$D131,系数辅助表!$C:$G,5,0)/VLOOKUP($D131,系数辅助表!$C:$E,3,0),0) -> 0.57332748 | I131: =VLOOKUP($D131,系数辅助表!$C:$F,4,0) -> 1.4265159 | J131: 分割
B132: 0555 | C132: =VLOOKUP($B132,'标准费用表-2024年&2025年优化'!$D:$E,2,0) -> 洛阳正大食品有限公司 | D132: 后腿肌肉 | E132: =IFERROR(VLOOKUP($B132,'标准费用表-2024年&2025年优化'!$D:$K,8,0)*VLOOKUP("白条",系数辅助表!$C:$G,5,0)*VLOOKUP('5.成本表'!$D132,系数辅助表!$C:$G,5,0)/VLOOKUP('5.成本表'!$D132,系数辅助表!$C:$E,3,0),) -> 0.30758236 | F132: =IFERROR(VLOOKUP($B132,'标准费用表-2024年&2025年优化'!$D:$L,9,0)*VLOOKUP('5.成本表'!$D132,系数辅助表!$C:$G,5,0)/VLOOKUP($D132,系数辅助表!$C:$E,3,0),0) -> 0.58420577 | I132: =VLOOKUP($D132,系数辅助表!$C:$F,4,0) -> 1.4535826 | J132: 分割
B133: 0555 | C133: =VLOOKUP($B133,'标准费用表-2024年&2025年优化'!$D:$E,2,0) -> 洛阳正大食品有限公司 | D133: 前肘 | E133: =IFERROR(VLOOKUP($B133,'标准费用表-2024年&2025年优化'!$D:$K,8,0)*VLOOKUP("白条",系数辅助表!$C:$G,5,0)*VLOOKUP('5.成本表'!$D133,系数辅助表!$C:$G,5,0)/VLOOKUP('5.成本表'!$D133,系数辅助表!$C:$E,3,0),) -> 0.30492792 | F133: =IFERROR(VLOOKUP($B133,'标准费用表-2024年&2025年优化'!$D:$L,9,0)*VLOOKUP('5.成本表'!$D133,系数辅助表!$C:$G,5,0)/VLOOKUP($D133,系数辅助表!$C:$E,3,0),0) -> 0.57916406 | I133: =VLOOKUP($D133,系数辅助表!$C:$F,4,0) -> 1.4410381 | J133: 分割
B134: 0555 | C134: =VLOOKUP($B134,'标准费用表-2024年&2025年优化'!$D:$E,2,0) -> 洛阳正大食品有限公司 | D134: 后肘 | E134: =IFERROR(VLOOKUP($B134,'标准费用表-2024年&2025年优化'!$D:$K,8,0)*VLOOKUP("白条",系数辅助表!$C:$G,5,0)*VLOOKUP('5.成本表'!$D134,系数辅助表!$C:$G,5,0)/VLOOKUP('5.成本表'!$D134,系数辅助表!$C:$E,3,0),) -> 0.26150583 | F134: =IFERROR(VLOOKUP($B134,'标准费用表-2024年&2025年优化'!$D:$L,9,0)*VLOOKUP('5.成本表'!$D134,系数辅助表!$C:$G,5,0)/VLOOKUP($D134,系数辅助表!$C:$E,3,0),0) -> 0.49669043 | I134: =VLOOKUP($D134,系数辅助表!$C:$F,4,0) -> 1.2358326 | J134: 分割
B135: 0555 | C135: =VLOOKUP($B135,'标准费用表-2024年&2025年优化'!$D:$E,2,0) -> 洛阳正大食品有限公司 | D135: 肥膘 | E135: =IFERROR(VLOOKUP($B135,'标准费用表-2024年&2025年优化'!$D:$K,8,0)*VLOOKUP("白条",系数辅助表!$C:$G,5,0)*VLOOKUP('5.成本表'!$D135,系数辅助表!$C:$G,5,0)/VLOOKUP('5.成本表'!$D135,系数辅助表!$C:$E,3,0),) -> 0.18265927 | F135: =IFERROR(VLOOKUP($B135,'标准费用表-2024年&2025年优化'!$D:$L,9,0)*VLOOKUP('5.成本表'!$D135,系数辅助表!$C:$G,5,0)/VLOOKUP($D135,系数辅助表!$C:$E,3,0),0) -> 0.34693341 | I135: =VLOOKUP($D135,系数辅助表!$C:$F,4,0) -> 0.86321702 | J135: 分割
B136: 0555 | C136: =VLOOKUP($B136,'标准费用表-2024年&2025年优化'!$D:$E,2,0) -> 洛阳正大食品有限公司 | D136: 脊膘 | E136: =IFERROR(VLOOKUP($B136,'标准费用表-2024年&2025年优化'!$D:$K,8,0)*VLOOKUP("白条",系数辅助表!$C:$G,5,0)*VLOOKUP('5.成本表'!$D136,系数辅助表!$C:$G,5,0)/VLOOKUP('5.成本表'!$D136,系数辅助表!$C:$E,3,0),) -> 0.16862087 | F136: =IFERROR(VLOOKUP($B136,'标准费用表-2024年&2025年优化'!$D:$L,9,0)*VLOOKUP('5.成本表'!$D136,系数辅助表!$C:$G,5,0)/VLOOKUP($D136,系数辅助表!$C:$E,3,0),0) -> 0.32026962 | I136: =VLOOKUP($D136,系数辅助表!$C:$F,4,0) -> 0.79687393 | J136: 分割
... B148: 0555 | C148: =VLOOKUP($B148,'标准费用表-2024年&2025年优化'!$D:$E,2,0) -> 洛阳正大食品有限公司 | D148: 碎皮 | E148: =IFERROR(VLOOKUP($B148,'标准费用表-2024年&2025年优化'!$D:$K,8,0)*VLOOKUP("白条",系数辅助表!$C:$G,5,0)*VLOOKUP('5.成本表'!$D148,系数辅助表!$C:$G,5,0)/VLOOKUP('5.成本表'!$D148,系数辅助表!$C:$E,3,0),) -> 0.050903401 | F148: =IFERROR(VLOOKUP($B148,'标准费用表-2024年&2025年优化'!$D:$L,9,0)*VLOOKUP('5.成本表'!$D148,系数辅助表!$C:$G,5,0)/VLOOKUP($D148,系数辅助表!$C:$E,3,0),0) -> 0.096683244 | I148: =VLOOKUP($D148,系数辅助表!$C:$F,4,0) -> 0.24056092 | J148: 分割
B149: 0555 | C149: =VLOOKUP($B149,'标准费用表-2024年&2025年优化'!$D:$E,2,0) -> 洛阳正大食品有限公司 | D149: 五花肉-冷冻 | E149: =E125 -> 0.48245472 | F149: =F125 -> 0.91634914 | G149: 0.2 | H149: 0.3 | J149: 分割
B150: 0555 | C150: =VLOOKUP($B150,'标准费用表-2024年&2025年优化'!$D:$E,2,0) -> 洛阳正大食品有限公司 | D150: 大排肌肉-冷冻 | E150: =E126 -> 0.32242435 | F150: =F126 -> 0.61239586 | G150: 0.2 | H150: 0.3 | J150: 分割
B151: 0555 | C151: =VLOOKUP($B151,'标准费用表-2024年&2025年优化'!$D:$E,2,0) -> 洛阳正大食品有限公司 | D151: 肋排-冷冻 | E151: =E127 -> 0.85332199 | F151: =F127 -> 1.6207549 | G151: 0.2 | H151: 0.3 | J151: 分割
B152: 0555 | C152: =VLOOKUP($B152,'标准费用表-2024年&2025年优化'!$D:$E,2,0) -> 洛阳正大食品有限公司 | D152: 前排-冷冻 | E152: =E128 -> 0.49696645 | F152: =F128 -> 0.94391195 | G152: 0.2 | H152: 0.3 | J152: 分割
B153: 0555 | C153: =VLOOKUP($B153,'标准费用表-2024年&2025年优化'!$D:$E,2,0) -> 洛阳正大食品有限公司 | D153: 颈背肌肉-冷冻 | E153: =E129 -> 0.29854572 | F153: =F129 -> 0.56704205 | G153: 0.2 | H153: 0.3 | J153: 分割
B154: 0555 | C154: =VLOOKUP($B154,'标准费用表-2024年&2025年优化'!$D:$E,2,0) -> 洛阳正大食品有限公司 | D154: 小里脊-冷冻 | E154: =E130 -> 0.40312526 | F154: =F130 -> 0.76567494 | G154: 0.2 | H154: 0.3 | J154: 分割
B155: 0555 | C155: =VLOOKUP($B155,'标准费用表-2024年&2025年优化'!$D:$E,2,0) -> 洛阳正大食品有限公司 | D155: 前腿肌肉-冷冻 | E155: =E131 -> 0.30185498 | F155: =F131 -> 0.57332748 | G155: 0.2 | H155: 0.3 | J155: 分割
B156: 0555 | C156: =VLOOKUP($B156,'标准费用表-2024年&2025年优化'!$D:$E,2,0) -> 洛阳正大食品有限公司 | D156: 后腿肌肉-冷冻 | E156: =E132 -> 0.30758236 | F156: =F132 -> 0.58420577 | G156: 0.2 | H156: 0.3 | J156: 分割
B157: 0555 | C157: =VLOOKUP($B157,'标准费用表-2024年&2025年优化'!$D:$E,2,0) -> 洛阳正大食品有限公司 | D157: 前肘-冷冻 | E157: =E133 -> 0.30492792 | F157: =F133 -> 0.57916406 | G157: 0.2 | H157: 0.3 | J157: 分割
B158: 0555 | C158: =VLOOKUP($B158,'标准费用表-2024年&2025年优化'!$D:$E,2,0) -> 洛阳正大食品有限公司 | D158: 后肘-冷冻 | E158: =E134 -> 0.26150583 | F158: =F134 -> 0.49669043 | G158: 0.2 | H158: 0.3 | J158: 分割
B159: 0555 | C159: =VLOOKUP($B159,'标准费用表-2024年&2025年优化'!$D:$E,2,0) -> 洛阳正大食品有限公司 | D159: 肥膘-冷冻 | E159: =E135 -> 0.18265927 | F159: =F135 -> 0.34693341 | G159: 0.2 | H159: 0.3 | J159: 分割
B160: 0555 | C160: =VLOOKUP($B160,'标准费用表-2024年&2025年优化'!$D:$E,2,0) -> 洛阳正大食品有限公司 | D160: 脊膘-冷冻 | E160: =E136 -> 0.16862087 | F160: =F136 -> 0.32026962 | G160: 0.2 | H160: 0.3 | J160: 分割
... B172: 0555 | C172: =VLOOKUP($B172,'标准费用表-2024年&2025年优化'!$D:$E,2,0) -> 洛阳正大食品有限公司 | D172: 碎皮-冷冻 | E172: =E148 -> 0.050903401 | F172: =F148 -> 0.096683244 | G172: 0.2 | H172: 0.3 | J172: 分割
B173: 0555 | C173: =VLOOKUP($B173,'标准费用表-2024年&2025年优化'!$D:$E,2,0) -> 洛阳正大食品有限公司 | D173: 猪头-冷冻 | E173: =E101 -> 0.18410433 | F173: =F149 -> 0.91634914 | G173: 0.2 | H173: 0.3 | J173: 分割
B174: 0555 | C174: =VLOOKUP($B174,'标准费用表-2024年&2025年优化'!$D:$E,2,0) -> 洛阳正大食品有限公司 | D174: 猪蹄-冷冻 | E174: =E102 -> 0.49204159 | F174: =F150 -> 0.61239586 | G174: 0.2 | H174: 0.3 | J174: 分割
B175: 0555 | C175: =VLOOKUP($B175,'标准费用表-2024年&2025年优化'!$D:$E,2,0) -> 洛阳正大食品有限公司 | D175: 猪尾-冷冻 | E175: =E103 -> 0.91071682 | F175: =F151 -> 1.6207549 | G175: 0.2 | H175: 0.3 | J175: 分割
B176: 0555 | C176: =VLOOKUP($B176,'标准费用表-2024年&2025年优化'!$D:$E,2,0) -> 洛阳正大食品有限公司 | D176: 猪心-冷冻 | E176: =E104 -> 0.19139178 | F176: =F152 -> 0.94391195 | G176: 0.2 | H176: 0.3 | J176: 分割
B177: 0555 | C177: =VLOOKUP($B177,'标准费用表-2024年&2025年优化'!$D:$E,2,0) -> 洛阳正大食品有限公司 | D177: 猪肝-冷冻 | E177: =E105 -> 0.084494598 | F177: =F153 -> 0.56704205 | G177: 0.2 | H177: 0.3 | J177: 分割
B178: 0555 | C178: =VLOOKUP($B178,'标准费用表-2024年&2025年优化'!$D:$E,2,0) -> 洛阳正大食品有限公司 | D178: 猪腰-冷冻 | E178: =E106 -> 0.26149957 | F178: =F154 -> 0.76567494 | G178: 0.2 | H178: 0.3 | J178: 分割
...

Sheet 6.仓库表
B2: 屠宰厂id | C2: 公司名称 | D2: 所属省份 | E2: 库容上限-kg | F2: 库存成本系数-元/kg/日 | G2: 日期 | H2: 部位 | I2: 当期库存-kg
B3: 0567 | C3: 正大食品（襄阳）有限公司 | D3: 湖北 | E3: 5000000 | F3: 0.0073333333
B4: 0555 | C4: 洛阳正大食品有限公司 | D4: 河南 | E4: 1000000 | F4: 0.0073333333
B5: 0476 | C5: 正大食品（徐州）有限公司 | D5: 江苏 | E5: 5000000 | F5: 0.0073333333
B6: 0370 | C6: 内蒙古正大鸿业食品有限公司 | D6: 内蒙古 | E6: 5000000 | F6: 0.0073333333
B7: 0377 | C7: 山西正大食品有限公司 | D7: 山西 | E7: 300000 | F7: 0.0073333333
B8: 0388 | C8: 甘肃庆阳正大食品有限公司 | D8: 甘肃 | E8: 500000 | F8: 0.0073333333
B9: 0638 | C9: 成都正大农牧食品有限公司 | D9: 四川 | E9: 2000000 | F9: 0.0073333333
B10: 1533 | C10: 正大食品（长沙）有限公司 | D10: 湖南 | E10: 2000000 | F10: 0.0073333333
B11: A388 | C11: 庆阳正大食品有限公司OEM | D11: 甘肃 | E11: 300000 | F11: 0.0073333333
B12: 0294 | C12: 正大畜牧(阜新)有限公司 | D12: 辽宁 | E12: 2000000 | F12: 0.0073333333
B13: 0261 | C13: 吉林中新正大食品有限公司 | D13: 吉林 | E13: 0 | F13: 0.0073333333
B14: 0360 | C14: 新疆正大畜禽有限公司 | D14: 新疆 | E14: 0 | F14: 0.0073333333
... B17: 0648 | C17: 昆明正大猪业有限公司 | D17: 云南 | E17: 650000 | F17: 0.0073333333
B18: 1522 | C18: 正大食品（咸宁）有限公司 | D18: 湖北 | E18: 0 | F18: 0.0073333333
B19: 1521 | C19: 正大食品（宜昌）有限公司 | D19: 湖北 | E19: 0 | F19: 0.0073333333
B20: 1850 | C20: 江西正大畜禽有限公司高安分公司 | D20: 江西 | E20: 350000 | F20: 0.0073333333
B21: 0692 | C21: 正大食品（来宾）有限公司 | D21: 广西 | E21: 460000 | F21: 0.0073333333
B22: 0662 | C22: 贵州正大农牧食品有限公司 | D22: 贵州 | E22: 0 | F22: 0.0073333333
B23: 1658 | C23: 正大卜蜂食品(重庆)有限公司 | D23: 重庆 | E23: 1000000 | F23: 0.0073333333
B24: 1441 | C24: 正大食品（徐州）有限公司山东第二分公司 | D24: 山东 | E24: 2000000 | F24: 0.0073333333
B25: 1810 | C25: 正大食品（广东）有限公司 | D25: 广东 | E25: 0 | F25: 0.0073333333

Sheet 7.部位订单表
B2: 工厂id | C2: 分割部位 | D2: 日期 | E2: 客户类别 | F2: 订单量 | G2: 鲜销价格系数 | H2: 销售价格 | I2: 订单售达省份 | J2: 毛猪价格
A3: =I3&D3 -> 湖北46136 | B3: 0567 | C3: =IF(根据产能每天需要鲜销部分!K4<>0,根据产能每天需要鲜销部分!G4,0) -> 白条 | D3: 46136 | F3: =SUMIFS(根据产能每天需要鲜销部分!$K:$K,根据产能每天需要鲜销部分!$B:$B,$B3,根据产能每天需要鲜销部分!$G:$G,$C3) -> 137280 | G3: =_xlfn.XLOOKUP($C3,价格系数辅助表!$C:$C,价格系数辅助表!$E:$E) -> 1.1852119 | H3: =G3*$J3 -> 10.574018 | I3: =_xlfn.XLOOKUP(B3,'3.屠宰能力表'!B:B,'3.屠宰能力表'!D:D) -> 湖北 | J3: =_xlfn.XLOOKUP(A3,'1.出栏表'!A:A,'1.出栏表'!F:F) -> 8.9216268
A4: =I4&D4 -> 湖北46136 | B4: 0567 | C4: =IF(根据产能每天需要鲜销部分!K5<>0,根据产能每天需要鲜销部分!G5,0) -> 猪头 | D4: 46136 | F4: =SUMIFS(根据产能每天需要鲜销部分!$K:$K,根据产能每天需要鲜销部分!$B:$B,$B4,根据产能每天需要鲜销部分!$G:$G,$C4) -> 16643.419 | G4: =_xlfn.XLOOKUP($C4,价格系数辅助表!$C:$C,价格系数辅助表!$E:$E) -> 0.81317167 | H4: =G4*$J4 -> 7.2548142 | I4: =_xlfn.XLOOKUP(B4,'3.屠宰能力表'!B:B,'3.屠宰能力表'!D:D) -> 湖北 | J4: =_xlfn.XLOOKUP(A4,'1.出栏表'!A:A,'1.出栏表'!F:F) -> 8.9216268
A5: =I5&D5 -> 湖北46136 | B5: 0567 | C5: =IF(根据产能每天需要鲜销部分!K6<>0,根据产能每天需要鲜销部分!G6,0) -> 猪尾 | D5: 46136 | F5: =SUMIFS(根据产能每天需要鲜销部分!$K:$K,根据产能每天需要鲜销部分!$B:$B,$B5,根据产能每天需要鲜销部分!$G:$G,$C5) -> 125.03859 | G5: =_xlfn.XLOOKUP($C5,价格系数辅助表!$C:$C,价格系数辅助表!$E:$E) -> 4.0225512 | H5: =G5*$J5 -> 35.887701 | I5: =_xlfn.XLOOKUP(B5,'3.屠宰能力表'!B:B,'3.屠宰能力表'!D:D) -> 湖北 | J5: =_xlfn.XLOOKUP(A5,'1.出栏表'!A:A,'1.出栏表'!F:F) -> 8.9216268
A6: =I6&D6 -> 湖北46136 | B6: 0567 | C6: =IF(根据产能每天需要鲜销部分!K7<>0,根据产能每天需要鲜销部分!G7,0) -> 猪心 | D6: 46136 | F6: =SUMIFS(根据产能每天需要鲜销部分!$K:$K,根据产能每天需要鲜销部分!$B:$B,$B6,根据产能每天需要鲜销部分!$G:$G,$C6) -> 1176.2841 | G6: =_xlfn.XLOOKUP($C6,价格系数辅助表!$C:$C,价格系数辅助表!$E:$E) -> 0.84535964 | H6: =G6*$J6 -> 7.5419833 | I6: =_xlfn.XLOOKUP(B6,'3.屠宰能力表'!B:B,'3.屠宰能力表'!D:D) -> 湖北 | J6: =_xlfn.XLOOKUP(A6,'1.出栏表'!A:A,'1.出栏表'!F:F) -> 8.9216268
A7: =I7&D7 -> 湖北46136 | B7: 0567 | C7: =IF(根据产能每天需要鲜销部分!K8<>0,根据产能每天需要鲜销部分!G8,0) -> 猪肝 | D7: 46136 | F7: =SUMIFS(根据产能每天需要鲜销部分!$K:$K,根据产能每天需要鲜销部分!$B:$B,$B7,根据产能每天需要鲜销部分!$G:$G,$C7) -> 6075.9539 | G7: =_xlfn.XLOOKUP($C7,价格系数辅助表!$C:$C,价格系数辅助表!$E:$E) -> 0.37320475 | H7: =G7*$J7 -> 3.3295936 | I7: =_xlfn.XLOOKUP(B7,'3.屠宰能力表'!B:B,'3.屠宰能力表'!D:D) -> 湖北 | J7: =_xlfn.XLOOKUP(A7,'1.出栏表'!A:A,'1.出栏表'!F:F) -> 8.9216268
A8: =I8&D8 -> 湖北46136 | B8: 0567 | C8: =IF(根据产能每天需要鲜销部分!K9<>0,根据产能每天需要鲜销部分!G9,0) -> 猪腰 | D8: 46136 | F8: =SUMIFS(根据产能每天需要鲜销部分!$K:$K,根据产能每天需要鲜销部分!$B:$B,$B8,根据产能每天需要鲜销部分!$G:$G,$C8) -> 1187.8666 | G8: =_xlfn.XLOOKUP($C8,价格系数辅助表!$C:$C,价格系数辅助表!$E:$E) -> 1.1550192 | H8: =G8*$J8 -> 10.30465 | I8: =_xlfn.XLOOKUP(B8,'3.屠宰能力表'!B:B,'3.屠宰能力表'!D:D) -> 湖北 | J8: =_xlfn.XLOOKUP(A8,'1.出栏表'!A:A,'1.出栏表'!F:F) -> 8.9216268
A9: =I9&D9 -> 湖北46136 | B9: 0567 | C9: =IF(根据产能每天需要鲜销部分!K10<>0,根据产能每天需要鲜销部分!G10,0) -> 大肠 | D9: 46136 | F9: =SUMIFS(根据产能每天需要鲜销部分!$K:$K,根据产能每天需要鲜销部分!$B:$B,$B9,根据产能每天需要鲜销部分!$G:$G,$C9) -> 4156.7228 | G9: =_xlfn.XLOOKUP($C9,价格系数辅助表!$C:$C,价格系数辅助表!$E:$E) -> 1.9080014 | H9: =G9*$J9 -> 17.022476 | I9: =_xlfn.XLOOKUP(B9,'3.屠宰能力表'!B:B,'3.屠宰能力表'!D:D) -> 湖北 | J9: =_xlfn.XLOOKUP(A9,'1.出栏表'!A:A,'1.出栏表'!F:F) -> 8.9216268
A10: =I10&D10 -> 湖北46136 | B10: 0567 | C10: =IF(根据产能每天需要鲜销部分!K11<>0,根据产能每天需要鲜销部分!G11,0) -> 猪肚 | D10: 46136 | F10: =SUMIFS(根据产能每天需要鲜销部分!$K:$K,根据产能每天需要鲜销部分!$B:$B,$B10,根据产能每天需要鲜销部分!$G:$G,$C10) -> 1906.8385 | G10: =_xlfn.XLOOKUP($C10,价格系数辅助表!$C:$C,价格系数辅助表!$E:$E) -> 2.7678324 | H10: =G10*$J10 -> 24.693568 | I10: =_xlfn.XLOOKUP(B10,'3.屠宰能力表'!B:B,'3.屠宰能力表'!D:D) -> 湖北 | J10: =_xlfn.XLOOKUP(A10,'1.出栏表'!A:A,'1.出栏表'!F:F) -> 8.9216268
A11: =I11&D11 -> 湖北46136 | B11: 0567 | C11: =IF(根据产能每天需要鲜销部分!K12<>0,根据产能每天需要鲜销部分!G12,0) -> 罗膈肉 | D11: 46136 | F11: =SUMIFS(根据产能每天需要鲜销部分!$K:$K,根据产能每天需要鲜销部分!$B:$B,$B11,根据产能每天需要鲜销部分!$G:$G,$C11) -> 1594.242 | G11: =_xlfn.XLOOKUP($C11,价格系数辅助表!$C:$C,价格系数辅助表!$E:$E) -> 1.6170864 | H11: =G11*$J11 -> 14.427042 | I11: =_xlfn.XLOOKUP(B11,'3.屠宰能力表'!B:B,'3.屠宰能力表'!D:D) -> 湖北 | J11: =_xlfn.XLOOKUP(A11,'1.出栏表'!A:A,'1.出栏表'!F:F) -> 8.9216268
A12: =I12&D12 -> 湖北46136 | B12: 0567 | C12: =IF(根据产能每天需要鲜销部分!K13<>0,根据产能每天需要鲜销部分!G13,0) -> 猪舌 | D12: 46136 | F12: =SUMIFS(根据产能每天需要鲜销部分!$K:$K,根据产能每天需要鲜销部分!$B:$B,$B12,根据产能每天需要鲜销部分!$G:$G,$C12) -> 1406.6841 | G12: =_xlfn.XLOOKUP($C12,价格系数辅助表!$C:$C,价格系数辅助表!$E:$E) -> 1.4850675 | H12: =G12*$J12 -> 13.249218 | I12: =_xlfn.XLOOKUP(B12,'3.屠宰能力表'!B:B,'3.屠宰能力表'!D:D) -> 湖北 | J12: =_xlfn.XLOOKUP(A12,'1.出栏表'!A:A,'1.出栏表'!F:F) -> 8.9216268
A13: =I13&D13 -> 湖北46136 | B13: 0567 | C13: =IF(根据产能每天需要鲜销部分!K14<>0,根据产能每天需要鲜销部分!G14,0) -> 大肠头 | D13: 46136 | F13: =SUMIFS(根据产能每天需要鲜销部分!$K:$K,根据产能每天需要鲜销部分!$B:$B,$B13,根据产能每天需要鲜销部分!$G:$G,$C13) -> 1031.5683 | G13: =_xlfn.XLOOKUP($C13,价格系数辅助表!$C:$C,价格系数辅助表!$E:$E) -> 1.8971615 | H13: =G13*$J13 -> 16.925767 | I13: =_xlfn.XLOOKUP(B13,'3.屠宰能力表'!B:B,'3.屠宰能力表'!D:D) -> 湖北 | J13: =_xlfn.XLOOKUP(A13,'1.出栏表'!A:A,'1.出栏表'!F:F) -> 8.9216268
A14: =I14&D14 -> 湖北46136 | B14: 0567 | C14: =IF(根据产能每天需要鲜销部分!K15<>0,根据产能每天需要鲜销部分!G15,0) -> 心血管 | D14: 46136 | F14: =SUMIFS(根据产能每天需要鲜销部分!$K:$K,根据产能每天需要鲜销部分!$B:$B,$B14,根据产能每天需要鲜销部分!$G:$G,$C14) -> 111.42052 | G14: =_xlfn.XLOOKUP($C14,价格系数辅助表!$C:$C,价格系数辅助表!$E:$E) -> 3.2997149 | H14: =G14*$J14 -> 29.438825 | I14: =_xlfn.XLOOKUP(B14,'3.屠宰能力表'!B:B,'3.屠宰能力表'!D:D) -> 湖北 | J14: =_xlfn.XLOOKUP(A14,'1.出栏表'!A:A,'1.出栏表'!F:F) -> 8.9216268
... A32: =I32&D32 -> 湖北46136 | B32: 0567 | C32: =IF(根据产能每天需要鲜销部分!K33<>0,根据产能每天需要鲜销部分!G33,0) -> 颈背肌肉 | D32: 46136 | F32: =SUMIFS(根据产能每天需要鲜销部分!$K:$K,根据产能每天需要鲜销部分!$B:$B,$B32,根据产能每天需要鲜销部分!$G:$G,$C32) -> 1156.5827 | G32: =_xlfn.XLOOKUP($C32,价格系数辅助表!$C:$C,价格系数辅助表!$E:$E) -> 1.445746 | H32: =G32*$J32 -> 12.898407 | I32: =_xlfn.XLOOKUP(B32,'3.屠宰能力表'!B:B,'3.屠宰能力表'!D:D) -> 湖北 | J32: =_xlfn.XLOOKUP(A32,'1.出栏表'!A:A,'1.出栏表'!F:F) -> 8.9216268
A33: =I33&D33 -> 湖北46136 | B33: 0567 | C33: =IF(根据产能每天需要鲜销部分!K35<>0,根据产能每天需要鲜销部分!G35,0) -> 前腿肌肉 | D33: 46136 | F33: =SUMIFS(根据产能每天需要鲜销部分!$K:$K,根据产能每天需要鲜销部分!$B:$B,$B33,根据产能每天需要鲜销部分!$G:$G,$C33) -> 1559.9408 | G33: =_xlfn.XLOOKUP($C33,价格系数辅助表!$C:$C,价格系数辅助表!$E:$E) -> 1.4617715 | H33: =G33*$J33 -> 13.04138 | I33: =_xlfn.XLOOKUP(B33,'3.屠宰能力表'!B:B,'3.屠宰能力表'!D:D) -> 湖北 | J33: =_xlfn.XLOOKUP(A33,'1.出栏表'!A:A,'1.出栏表'!F:F) -> 8.9216268
A34: =I34&D34 -> 湖北46136 | B34: 0567 | C34: =IF(根据产能每天需要鲜销部分!K36<>0,根据产能每天需要鲜销部分!G36,0) -> 后腿肌肉 | D34: 46136 | F34: =SUMIFS(根据产能每天需要鲜销部分!$K:$K,根据产能每天需要鲜销部分!$B:$B,$B34,根据产能每天需要鲜销部分!$G:$G,$C34) -> 13723.174 | G34: =_xlfn.XLOOKUP($C34,价格系数辅助表!$C:$C,价格系数辅助表!$E:$E) -> 1.4895071 | H34: =G34*$J34 -> 13.288827 | I34: =_xlfn.XLOOKUP(B34,'3.屠宰能力表'!B:B,'3.屠宰能力表'!D:D) -> 湖北 | J34: =_xlfn.XLOOKUP(A34,'1.出栏表'!A:A,'1.出栏表'!F:F) -> 8.9216268
A35: =I35&D35 -> 湖北46136 | B35: 0567 | C35: =IF(根据产能每天需要鲜销部分!K37<>0,根据产能每天需要鲜销部分!G37,0) -> 前肘 | D35: 46136 | F35: =SUMIFS(根据产能每天需要鲜销部分!$K:$K,根据产能每天需要鲜销部分!$B:$B,$B35,根据产能每天需要鲜销部分!$G:$G,$C35) -> 1529.2971 | G35: =_xlfn.XLOOKUP($C35,价格系数辅助表!$C:$C,价格系数辅助表!$E:$E) -> 1.4766526 | H35: =G35*$J35 -> 13.174144 | I35: =_xlfn.XLOOKUP(B35,'3.屠宰能力表'!B:B,'3.屠宰能力表'!D:D) -> 湖北 | J35: =_xlfn.XLOOKUP(A35,'1.出栏表'!A:A,'1.出栏表'!F:F) -> 8.9216268
A36: =I36&D36 -> 湖北46136 | B36: 0567 | C36: =IF(根据产能每天需要鲜销部分!K38<>0,根据产能每天需要鲜销部分!G38,0) -> 后肘 | D36: 46136 | F36: =SUMIFS(根据产能每天需要鲜销部分!$K:$K,根据产能每天需要鲜销部分!$B:$B,$B36,根据产能每天需要鲜销部分!$G:$G,$C36) -> 2158.415 | G36: =_xlfn.XLOOKUP($C36,价格系数辅助表!$C:$C,价格系数辅助表!$E:$E) -> 1.2663756 | H36: =G36*$J36 -> 11.29813 | I36: =_xlfn.XLOOKUP(B36,'3.屠宰能力表'!B:B,'3.屠宰能力表'!D:D) -> 湖北 | J36: =_xlfn.XLOOKUP(A36,'1.出栏表'!A:A,'1.出栏表'!F:F) -> 8.9216268
A37: =I37&D37 -> 湖北46136 | B37: 0567 | C37: =IF(根据产能每天需要鲜销部分!K39<>0,根据产能每天需要鲜销部分!G39,0) -> 肥膘 | D37: 46136 | F37: =SUMIFS(根据产能每天需要鲜销部分!$K:$K,根据产能每天需要鲜销部分!$B:$B,$B37,根据产能每天需要鲜销部分!$G:$G,$C37) -> 4806.6752 | G37: =_xlfn.XLOOKUP($C37,价格系数辅助表!$C:$C,价格系数辅助表!$E:$E) -> 0.88455098 | H37: =G37*$J37 -> 7.8916337 | I37: =_xlfn.XLOOKUP(B37,'3.屠宰能力表'!B:B,'3.屠宰能力表'!D:D) -> 湖北 | J37: =_xlfn.XLOOKUP(A37,'1.出栏表'!A:A,'1.出栏表'!F:F) -> 8.9216268
A38: =I38&D38 -> 湖北46136 | B38: 0567 | C38: =IF(根据产能每天需要鲜销部分!K40<>0,根据产能每天需要鲜销部分!G40,0) -> 脊膘 | D38: 46136 | F38: =SUMIFS(根据产能每天需要鲜销部分!$K:$K,根据产能每天需要鲜销部分!$B:$B,$B38,根据产能每天需要鲜销部分!$G:$G,$C38) -> 2499.185 | G38: =_xlfn.XLOOKUP($C38,价格系数辅助表!$C:$C,价格系数辅助表!$E:$E) -> 0.81656825 | H38: =G38*$J38 -> 7.2851172 | I38: =_xlfn.XLOOKUP(B38,'3.屠宰能力表'!B:B,'3.屠宰能力表'!D:D) -> 湖北 | J38: =_xlfn.XLOOKUP(A38,'1.出栏表'!A:A,'1.出栏表'!F:F) -> 8.9216268
A39: =I39&D39 -> 湖北46136 | B39: 0567 | C39: =IF(根据产能每天需要鲜销部分!K41<>0,根据产能每天需要鲜销部分!G41,0) -> 脊骨 | D39: 46136 | F39: =SUMIFS(根据产能每天需要鲜销部分!$K:$K,根据产能每天需要鲜销部分!$B:$B,$B39,根据产能每天需要鲜销部分!$G:$G,$C39) -> 5734.7637 | G39: =_xlfn.XLOOKUP($C39,价格系数辅助表!$C:$C,价格系数辅助表!$E:$E) -> 1.1259652 | H39: =G39*$J39 -> 10.045441 | I39: =_xlfn.XLOOKUP(B39,'3.屠宰能力表'!B:B,'3.屠宰能力表'!D:D) -> 湖北 | J39: =_xlfn.XLOOKUP(A39,'1.出栏表'!A:A,'1.出栏表'!F:F) -> 8.9216268
A40: =I40&D40 -> 湖北46136 | B40: 0567 | C40: =IF(根据产能每天需要鲜销部分!K42<>0,根据产能每天需要鲜销部分!G42,0) -> 带肉后棒骨 | D40: 46136 | F40: =SUMIFS(根据产能每天需要鲜销部分!$K:$K,根据产能每天需要鲜销部分!$B:$B,$B40,根据产能每天需要鲜销部分!$G:$G,$C40) -> 1032.1431 | G40: =_xlfn.XLOOKUP($C40,价格系数辅助表!$C:$C,价格系数辅助表!$E:$E) -> 1.0259147 | H40: =G40*$J40 -> 9.1528281 | I40: =_xlfn.XLOOKUP(B40,'3.屠宰能力表'!B:B,'3.屠宰能力表'!D:D) -> 湖北 | J40: =_xlfn.XLOOKUP(A40,'1.出栏表'!A:A,'1.出栏表'!F:F) -> 8.9216268
A41: =I41&D41 -> 湖北46136 | B41: 0567 | C41: =IF(根据产能每天需要鲜销部分!K43<>0,根据产能每天需要鲜销部分!G43,0) -> 带肉前棒骨 | D41: 46136 | F41: =SUMIFS(根据产能每天需要鲜销部分!$K:$K,根据产能每天需要鲜销部分!$B:$B,$B41,根据产能每天需要鲜销部分!$G:$G,$C41) -> 1386.7429 | G41: =_xlfn.XLOOKUP($C41,价格系数辅助表!$C:$C,价格系数辅助表!$E:$E) -> 0.92260451 | H41: =G41*$J41 -> 8.2311332 | I41: =_xlfn.XLOOKUP(B41,'3.屠宰能力表'!B:B,'3.屠宰能力表'!D:D) -> 湖北 | J41: =_xlfn.XLOOKUP(A41,'1.出栏表'!A:A,'1.出栏表'!F:F) -> 8.9216268
A42: =I42&D42 -> 湖北46136 | B42: 0567 | C42: =IF(根据产能每天需要鲜销部分!K44<>0,根据产能每天需要鲜销部分!G44,0) -> 尾叉骨 | D42: 46136 | F42: =SUMIFS(根据产能每天需要鲜销部分!$K:$K,根据产能每天需要鲜销部分!$B:$B,$B42,根据产能每天需要鲜销部分!$G:$G,$C42) -> 4510.7241 | G42: =_xlfn.XLOOKUP($C42,价格系数辅助表!$C:$C,价格系数辅助表!$E:$E) -> 0.92667948 | H42: =G42*$J42 -> 8.2674885 | I42: =_xlfn.XLOOKUP(B42,'3.屠宰能力表'!B:B,'3.屠宰能力表'!D:D) -> 湖北 | J42: =_xlfn.XLOOKUP(A42,'1.出栏表'!A:A,'1.出栏表'!F:F) -> 8.9216268
A43: =I43&D43 -> 湖北46136 | B43: 0567 | C43: =IF(根据产能每天需要鲜销部分!K45<>0,根据产能每天需要鲜销部分!G45,0) -> 扇骨 | D43: 46136 | F43: =SUMIFS(根据产能每天需要鲜销部分!$K:$K,根据产能每天需要鲜销部分!$B:$B,$B43,根据产能每天需要鲜销部分!$G:$G,$C43) -> 1889.6276 | G43: =_xlfn.XLOOKUP($C43,价格系数辅助表!$C:$C,价格系数辅助表!$E:$E) -> 1.1521636 | H43: =G43*$J43 -> 10.279174 | I43: =_xlfn.XLOOKUP(B43,'3.屠宰能力表'!B:B,'3.屠宰能力表'!D:D) -> 湖北 | J43: =_xlfn.XLOOKUP(A43,'1.出栏表'!A:A,'1.出栏表'!F:F) -> 8.9216268
A44: =I44&D44 -> 湖北46136 | B44: 0567 | C44: =IF(根据产能每天需要鲜销部分!K46<>0,根据产能每天需要鲜销部分!G46,0) -> 颈骨 | D44: 46136 | F44: =SUMIFS(根据产能每天需要鲜销部分!$K:$K,根据产能每天需要鲜销部分!$B:$B,$B44,根据产能每天需要鲜销部分!$G:$G,$C44) -> 1341.0261 | G44: =_xlfn.XLOOKUP($C44,价格系数辅助表!$C:$C,价格系数辅助表!$E:$E) -> 1.0074711 | H44: =G44*$J44 -> 8.988281 | I44: =_xlfn.XLOOKUP(B44,'3.屠宰能力表'!B:B,'3.屠宰能力表'!D:D) -> 湖北 | J44: =_xlfn.XLOOKUP(A44,'1.出栏表'!A:A,'1.出栏表'!F:F) -> 8.9216268
... A50: =I50&D50 -> 湖北46136 | B50: 0567 | C50: =IF(根据产能每天需要鲜销部分!K52<>0,根据产能每天需要鲜销部分!G52,0) -> 碎皮 | D50: 46136 | F50: =SUMIFS(根据产能每天需要鲜销部分!$K:$K,根据产能每天需要鲜销部分!$B:$B,$B50,根据产能每天需要鲜销部分!$G:$G,$C50) -> 274.30079 | G50: =_xlfn.XLOOKUP($C50,价格系数辅助表!$C:$C,价格系数辅助表!$E:$E) -> 0.24650626 | H50: =G50*$J50 -> 2.1992369 | I50: =_xlfn.XLOOKUP(B50,'3.屠宰能力表'!B:B,'3.屠宰能力表'!D:D) -> 湖北 | J50: =_xlfn.XLOOKUP(A50,'1.出栏表'!A:A,'1.出栏表'!F:F) -> 8.9216268
A51: =I51&D51 -> 河南46136 | B51: 0555 | C51: 白条 | D51: 46136 | F51: =SUMIFS(根据产能每天需要鲜销部分!$K:$K,根据产能每天需要鲜销部分!$B:$B,$B51,根据产能每天需要鲜销部分!$G:$G,$C51) -> 192192 | G51: =_xlfn.XLOOKUP($C51,价格系数辅助表!$C:$C,价格系数辅助表!$E:$E) -> 1.1852119 | H51: =G51*$J51 -> 10.647946 | I51: =_xlfn.XLOOKUP(B51,'3.屠宰能力表'!B:B,'3.屠宰能力表'!D:D) -> 河南 | J51: =_xlfn.XLOOKUP(A51,'1.出栏表'!A:A,'1.出栏表'!F:F) -> 8.9840021
A52: =I52&D52 -> 河南46136 | B52: 0555 | C52: 猪头 | D52: 46136 | F52: =SUMIFS(根据产能每天需要鲜销部分!$K:$K,根据产能每天需要鲜销部分!$B:$B,$B52,根据产能每天需要鲜销部分!$G:$G,$C52) -> 16643.419 | G52: =_xlfn.XLOOKUP($C52,价格系数辅助表!$C:$C,价格系数辅助表!$E:$E) -> 0.81317167 | H52: =G52*$J52 -> 7.305536 | I52: =_xlfn.XLOOKUP(B52,'3.屠宰能力表'!B:B,'3.屠宰能力表'!D:D) -> 河南 | J52: =_xlfn.XLOOKUP(A52,'1.出栏表'!A:A,'1.出栏表'!F:F) -> 8.9840021
A53: =I53&D53 -> 河南46136 | B53: 0555 | C53: 猪尾 | D53: 46136 | F53: =SUMIFS(根据产能每天需要鲜销部分!$K:$K,根据产能每天需要鲜销部分!$B:$B,$B53,根据产能每天需要鲜销部分!$G:$G,$C53) -> 125.03859 | G53: =_xlfn.XLOOKUP($C53,价格系数辅助表!$C:$C,价格系数辅助表!$E:$E) -> 4.0225512 | H53: =G53*$J53 -> 36.138608 | I53: =_xlfn.XLOOKUP(B53,'3.屠宰能力表'!B:B,'3.屠宰能力表'!D:D) -> 河南 | J53: =_xlfn.XLOOKUP(A53,'1.出栏表'!A:A,'1.出栏表'!F:F) -> 8.9840021
A54: =I54&D54 -> 河南46136 | B54: 0555 | C54: 猪心 | D54: 46136 | F54: =SUMIFS(根据产能每天需要鲜销部分!$K:$K,根据产能每天需要鲜销部分!$B:$B,$B54,根据产能每天需要鲜销部分!$G:$G,$C54) -> 1176.2841 | G54: =_xlfn.XLOOKUP($C54,价格系数辅助表!$C:$C,价格系数辅助表!$E:$E) -> 0.84535964 | H54: =G54*$J54 -> 7.5947128 | I54: =_xlfn.XLOOKUP(B54,'3.屠宰能力表'!B:B,'3.屠宰能力表'!D:D) -> 河南 | J54: =_xlfn.XLOOKUP(A54,'1.出栏表'!A:A,'1.出栏表'!F:F) -> 8.9840021
A55: =I55&D55 -> 河南46136 | B55: 0555 | C55: 猪肝 | D55: 46136 | F55: =SUMIFS(根据产能每天需要鲜销部分!$K:$K,根据产能每天需要鲜销部分!$B:$B,$B55,根据产能每天需要鲜销部分!$G:$G,$C55) -> 6075.9539 | G55: =_xlfn.XLOOKUP($C55,价格系数辅助表!$C:$C,价格系数辅助表!$E:$E) -> 0.37320475 | H55: =G55*$J55 -> 3.3528723 | I55: =_xlfn.XLOOKUP(B55,'3.屠宰能力表'!B:B,'3.屠宰能力表'!D:D) -> 河南 | J55: =_xlfn.XLOOKUP(A55,'1.出栏表'!A:A,'1.出栏表'!F:F) -> 8.9840021
A56: =I56&D56 -> 河南46136 | B56: 0555 | C56: 猪腰 | D56: 46136 | F56: =SUMIFS(根据产能每天需要鲜销部分!$K:$K,根据产能每天需要鲜销部分!$B:$B,$B56,根据产能每天需要鲜销部分!$G:$G,$C56) -> 1187.8666 | G56: =_xlfn.XLOOKUP($C56,价格系数辅助表!$C:$C,价格系数辅助表!$E:$E) -> 1.1550192 | H56: =G56*$J56 -> 10.376695 | I56: =_xlfn.XLOOKUP(B56,'3.屠宰能力表'!B:B,'3.屠宰能力表'!D:D) -> 河南 | J56: =_xlfn.XLOOKUP(A56,'1.出栏表'!A:A,'1.出栏表'!F:F) -> 8.9840021
A57: =I57&D57 -> 河南46136 | B57: 0555 | C57: 大肠 | D57: 46136 | F57: =SUMIFS(根据产能每天需要鲜销部分!$K:$K,根据产能每天需要鲜销部分!$B:$B,$B57,根据产能每天需要鲜销部分!$G:$G,$C57) -> 4156.7228 | G57: =_xlfn.XLOOKUP($C57,价格系数辅助表!$C:$C,价格系数辅助表!$E:$E) -> 1.9080014 | H57: =G57*$J57 -> 17.141488 | I57: =_xlfn.XLOOKUP(B57,'3.屠宰能力表'!B:B,'3.屠宰能力表'!D:D) -> 河南 | J57: =_xlfn.XLOOKUP(A57,'1.出栏表'!A:A,'1.出栏表'!F:F) -> 8.9840021
A58: =I58&D58 -> 河南46136 | B58: 0555 | C58: 猪肚 | D58: 46136 | F58: =SUMIFS(根据产能每天需要鲜销部分!$K:$K,根据产能每天需要鲜销部分!$B:$B,$B58,根据产能每天需要鲜销部分!$G:$G,$C58) -> 1906.8385 | G58: =_xlfn.XLOOKUP($C58,价格系数辅助表!$C:$C,价格系数辅助表!$E:$E) -> 2.7678324 | H58: =G58*$J58 -> 24.866212 | I58: =_xlfn.XLOOKUP(B58,'3.屠宰能力表'!B:B,'3.屠宰能力表'!D:D) -> 河南 | J58: =_xlfn.XLOOKUP(A58,'1.出栏表'!A:A,'1.出栏表'!F:F) -> 8.9840021
A59: =I59&D59 -> 河南46136 | B59: 0555 | C59: 罗膈肉 | D59: 46136 | F59: =SUMIFS(根据产能每天需要鲜销部分!$K:$K,根据产能每天需要鲜销部分!$B:$B,$B59,根据产能每天需要鲜销部分!$G:$G,$C59) -> 1594.242 | G59: =_xlfn.XLOOKUP($C59,价格系数辅助表!$C:$C,价格系数辅助表!$E:$E) -> 1.6170864 | H59: =G59*$J59 -> 14.527908 | I59: =_xlfn.XLOOKUP(B59,'3.屠宰能力表'!B:B,'3.屠宰能力表'!D:D) -> 河南 | J59: =_xlfn.XLOOKUP(A59,'1.出栏表'!A:A,'1.出栏表'!F:F) -> 8.9840021
A60: =I60&D60 -> 河南46136 | B60: 0555 | C60: 猪舌 | D60: 46136 | F60: =SUMIFS(根据产能每天需要鲜销部分!$K:$K,根据产能每天需要鲜销部分!$B:$B,$B60,根据产能每天需要鲜销部分!$G:$G,$C60) -> 1406.6841 | G60: =_xlfn.XLOOKUP($C60,价格系数辅助表!$C:$C,价格系数辅助表!$E:$E) -> 1.4850675 | H60: =G60*$J60 -> 13.34185 | I60: =_xlfn.XLOOKUP(B60,'3.屠宰能力表'!B:B,'3.屠宰能力表'!D:D) -> 河南 | J60: =_xlfn.XLOOKUP(A60,'1.出栏表'!A:A,'1.出栏表'!F:F) -> 8.9840021
A61: =I61&D61 -> 河南46136 | B61: 0555 | C61: 大肠头 | D61: 46136 | F61: =SUMIFS(根据产能每天需要鲜销部分!$K:$K,根据产能每天需要鲜销部分!$B:$B,$B61,根据产能每天需要鲜销部分!$G:$G,$C61) -> 1031.5683 | G61: =_xlfn.XLOOKUP($C61,价格系数辅助表!$C:$C,价格系数辅助表!$E:$E) -> 1.8971615 | H61: =G61*$J61 -> 17.044103 | I61: =_xlfn.XLOOKUP(B61,'3.屠宰能力表'!B:B,'3.屠宰能力表'!D:D) -> 河南 | J61: =_xlfn.XLOOKUP(A61,'1.出栏表'!A:A,'1.出栏表'!F:F) -> 8.9840021
A62: =I62&D62 -> 河南46136 | B62: 0555 | C62: 心血管 | D62: 46136 | F62: =SUMIFS(根据产能每天需要鲜销部分!$K:$K,根据产能每天需要鲜销部分!$B:$B,$B62,根据产能每天需要鲜销部分!$G:$G,$C62) -> 111.42052 | G62: =_xlfn.XLOOKUP($C62,价格系数辅助表!$C:$C,价格系数辅助表!$E:$E) -> 3.2997149 | H62: =G62*$J62 -> 29.644645 | I62: =_xlfn.XLOOKUP(B62,'3.屠宰能力表'!B:B,'3.屠宰能力表'!D:D) -> 河南 | J62: =_xlfn.XLOOKUP(A62,'1.出栏表'!A:A,'1.出栏表'!F:F) -> 8.9840021
... A520: =I520&D520 -> 云南46136 | B520: 0648 | C520: 猪血 | D520: 46136 | F520: =SUMIFS(根据产能每天需要鲜销部分!$K:$K,根据产能每天需要鲜销部分!$B:$B,$B520,根据产能每天需要鲜销部分!$G:$G,$C520) -> 2160 | G520: =_xlfn.XLOOKUP($C520,价格系数辅助表!$C:$C,价格系数辅助表!$E:$E) -> 0.087444985 | H520: =G520*$J520 -> 0.79535312 | I520: =_xlfn.XLOOKUP(B520,'3.屠宰能力表'!B:B,'3.屠宰能力表'!D:D) -> 云南 | J520: =_xlfn.XLOOKUP(A520,'1.出栏表'!A:A,'1.出栏表'!F:F) -> 9.0954686
A521: =I521&D521 -> 湖北46136 | B521: 1522 | C521: 白条 | D521: 46136 | F521: =SUMIFS(根据产能每天需要鲜销部分!$K:$K,根据产能每天需要鲜销部分!$B:$B,$B521,根据产能每天需要鲜销部分!$G:$G,$C521) -> 156156 | G521: =_xlfn.XLOOKUP($C521,价格系数辅助表!$C:$C,价格系数辅助表!$E:$E) -> 1.1852119 | H521: =G521*$J521 -> 10.574018 | I521: =_xlfn.XLOOKUP(B521,'3.屠宰能力表'!B:B,'3.屠宰能力表'!D:D) -> 湖北 | J521: =_xlfn.XLOOKUP(A521,'1.出栏表'!A:A,'1.出栏表'!F:F) -> 8.9216268
A522: =I522&D522 -> 湖北46136 | B522: 1522 | C522: 猪头 | D522: 46136 | F522: =SUMIFS(根据产能每天需要鲜销部分!$K:$K,根据产能每天需要鲜销部分!$B:$B,$B522,根据产能每天需要鲜销部分!$G:$G,$C522) -> 9465.9447 | G522: =_xlfn.XLOOKUP($C522,价格系数辅助表!$C:$C,价格系数辅助表!$E:$E) -> 0.81317167 | H522: =G522*$J522 -> 7.2548142 | I522: =_xlfn.XLOOKUP(B522,'3.屠宰能力表'!B:B,'3.屠宰能力表'!D:D) -> 湖北 | J522: =_xlfn.XLOOKUP(A522,'1.出栏表'!A:A,'1.出栏表'!F:F) -> 8.9216268
A523: =I523&D523 -> 湖北46136 | B523: 1522 | C523: 猪尾 | D523: 46136 | F523: =SUMIFS(根据产能每天需要鲜销部分!$K:$K,根据产能每天需要鲜销部分!$B:$B,$B523,根据产能每天需要鲜销部分!$G:$G,$C523) -> 71.115696 | G523: =_xlfn.XLOOKUP($C523,价格系数辅助表!$C:$C,价格系数辅助表!$E:$E) -> 4.0225512 | H523: =G523*$J523 -> 35.887701 | I523: =_xlfn.XLOOKUP(B523,'3.屠宰能力表'!B:B,'3.屠宰能力表'!D:D) -> 湖北 | J523: =_xlfn.XLOOKUP(A523,'1.出栏表'!A:A,'1.出栏表'!F:F) -> 8.9216268
A524: =I524&D524 -> 湖北46136 | B524: 1522 | C524: 猪心 | D524: 46136 | F524: =SUMIFS(根据产能每天需要鲜销部分!$K:$K,根据产能每天需要鲜销部分!$B:$B,$B524,根据产能每天需要鲜销部分!$G:$G,$C524) -> 669.01158 | G524: =_xlfn.XLOOKUP($C524,价格系数辅助表!$C:$C,价格系数辅助表!$E:$E) -> 0.84535964 | H524: =G524*$J524 -> 7.5419833 | I524: =_xlfn.XLOOKUP(B524,'3.屠宰能力表'!B:B,'3.屠宰能力表'!D:D) -> 湖北 | J524: =_xlfn.XLOOKUP(A524,'1.出栏表'!A:A,'1.出栏表'!F:F) -> 8.9216268
A525: =I525&D525 -> 湖北46136 | B525: 1522 | C525: 猪肝 | D525: 46136 | F525: =SUMIFS(根据产能每天需要鲜销部分!$K:$K,根据产能每天需要鲜销部分!$B:$B,$B525,根据产能每天需要鲜销部分!$G:$G,$C525) -> 3455.6988 | G525: =_xlfn.XLOOKUP($C525,价格系数辅助表!$C:$C,价格系数辅助表!$E:$E) -> 0.37320475 | H525: =G525*$J525 -> 3.3295936 | I525: =_xlfn.XLOOKUP(B525,'3.屠宰能力表'!B:B,'3.屠宰能力表'!D:D) -> 湖北 | J525: =_xlfn.XLOOKUP(A525,'1.出栏表'!A:A,'1.出栏表'!F:F) -> 8.9216268
A526: =I526&D526 -> 湖北46136 | B526: 1522 | C526: 猪腰 | D526: 46136 | F526: =SUMIFS(根据产能每天需要鲜销部分!$K:$K,根据产能每天需要鲜销部分!$B:$B,$B526,根据产能每天需要鲜销部分!$G:$G,$C526) -> 675.59912 | G526: =_xlfn.XLOOKUP($C526,价格系数辅助表!$C:$C,价格系数辅助表!$E:$E) -> 1.1550192 | H526: =G526*$J526 -> 10.30465 | I526: =_xlfn.XLOOKUP(B526,'3.屠宰能力表'!B:B,'3.屠宰能力表'!D:D) -> 湖北 | J526: =_xlfn.XLOOKUP(A526,'1.出栏表'!A:A,'1.出栏表'!F:F) -> 8.9216268
A527: =I527&D527 -> 湖北46136 | B527: 1522 | C527: 大肠 | D527: 46136 | F527: =SUMIFS(根据产能每天需要鲜销部分!$K:$K,根据产能每天需要鲜销部分!$B:$B,$B527,根据产能每天需要鲜销部分!$G:$G,$C527) -> 2364.1361 | G527: =_xlfn.XLOOKUP($C527,价格系数辅助表!$C:$C,价格系数辅助表!$E:$E) -> 1.9080014 | H527: =G527*$J527 -> 17.022476 | I527: =_xlfn.XLOOKUP(B527,'3.屠宰能力表'!B:B,'3.屠宰能力表'!D:D) -> 湖北 | J527: =_xlfn.XLOOKUP(A527,'1.出栏表'!A:A,'1.出栏表'!F:F) -> 8.9216268
A528: =I528&D528 -> 湖北46136 | B528: 1522 | C528: 猪肚 | D528: 46136 | F528: =SUMIFS(根据产能每天需要鲜销部分!$K:$K,根据产能每天需要鲜销部分!$B:$B,$B528,根据产能每天需要鲜销部分!$G:$G,$C528) -> 1084.5144 | G528: =_xlfn.XLOOKUP($C528,价格系数辅助表!$C:$C,价格系数辅助表!$E:$E) -> 2.7678324 | H528: =G528*$J528 -> 24.693568 | I528: =_xlfn.XLOOKUP(B528,'3.屠宰能力表'!B:B,'3.屠宰能力表'!D:D) -> 湖北 | J528: =_xlfn.XLOOKUP(A528,'1.出栏表'!A:A,'1.出栏表'!F:F) -> 8.9216268
A529: =I529&D529 -> 湖北46136 | B529: 1522 | C529: 罗膈肉 | D529: 46136 | F529: =SUMIFS(根据产能每天需要鲜销部分!$K:$K,根据产能每天需要鲜销部分!$B:$B,$B529,根据产能每天需要鲜销部分!$G:$G,$C529) -> 906.72513 | G529: =_xlfn.XLOOKUP($C529,价格系数辅助表!$C:$C,价格系数辅助表!$E:$E) -> 1.6170864 | H529: =G529*$J529 -> 14.427042 | I529: =_xlfn.XLOOKUP(B529,'3.屠宰能力表'!B:B,'3.屠宰能力表'!D:D) -> 湖北 | J529: =_xlfn.XLOOKUP(A529,'1.出栏表'!A:A,'1.出栏表'!F:F) -> 8.9216268
A530: =I530&D530 -> 湖北46136 | B530: 1522 | C530: 猪舌 | D530: 46136 | F530: =SUMIFS(根据产能每天需要鲜销部分!$K:$K,根据产能每天需要鲜销部分!$B:$B,$B530,根据产能每天需要鲜销部分!$G:$G,$C530) -> 800.05158 | G530: =_xlfn.XLOOKUP($C530,价格系数辅助表!$C:$C,价格系数辅助表!$E:$E) -> 1.4850675 | H530: =G530*$J530 -> 13.249218 | I530: =_xlfn.XLOOKUP(B530,'3.屠宰能力表'!B:B,'3.屠宰能力表'!D:D) -> 湖北 | J530: =_xlfn.XLOOKUP(A530,'1.出栏表'!A:A,'1.出栏表'!F:F) -> 8.9216268
A531: =I531&D531 -> 湖北46136 | B531: 1522 | C531: 大肠头 | D531: 46136 | F531: =SUMIFS(根据产能每天需要鲜销部分!$K:$K,根据产能每天需要鲜销部分!$B:$B,$B531,根据产能每天需要鲜销部分!$G:$G,$C531) -> 586.70449 | G531: =_xlfn.XLOOKUP($C531,价格系数辅助表!$C:$C,价格系数辅助表!$E:$E) -> 1.8971615 | H531: =G531*$J531 -> 16.925767 | I531: =_xlfn.XLOOKUP(B531,'3.屠宰能力表'!B:B,'3.屠宰能力表'!D:D) -> 湖北 | J531: =_xlfn.XLOOKUP(A531,'1.出栏表'!A:A,'1.出栏表'!F:F) -> 8.9216268
A532: =I532&D532 -> 湖北46136 | B532: 1522 | C532: 心血管 | D532: 46136 | F532: =SUMIFS(根据产能每天需要鲜销部分!$K:$K,根据产能每天需要鲜销部分!$B:$B,$B532,根据产能每天需要鲜销部分!$G:$G,$C532) -> 63.370422 | G532: =_xlfn.XLOOKUP($C532,价格系数辅助表!$C:$C,价格系数辅助表!$E:$E) -> 3.2997149 | H532: =G532*$J532 -> 29.438825 | I532: =_xlfn.XLOOKUP(B532,'3.屠宰能力表'!B:B,'3.屠宰能力表'!D:D) -> 湖北 | J532: =_xlfn.XLOOKUP(A532,'1.出栏表'!A:A,'1.出栏表'!F:F) -> 8.9216268
... A543: =I543&D543 -> 湖北46136 | B543: 1522 | C543: 猪血 | D543: 46136 | F543: =SUMIFS(根据产能每天需要鲜销部分!$K:$K,根据产能每天需要鲜销部分!$B:$B,$B543,根据产能每天需要鲜销部分!$G:$G,$C543) -> 4368 | G543: =_xlfn.XLOOKUP($C543,价格系数辅助表!$C:$C,价格系数辅助表!$E:$E) -> 0.087444985 | H543: =G543*$J543 -> 0.78015153 | I543: =_xlfn.XLOOKUP(B543,'3.屠宰能力表'!B:B,'3.屠宰能力表'!D:D) -> 湖北 | J543: =_xlfn.XLOOKUP(A543,'1.出栏表'!A:A,'1.出栏表'!F:F) -> 8.9216268
A544: =I544&D544 -> 湖北46136 | B544: 1521 | C544: 白条 | D544: 46136 | F544: =SUMIFS(根据产能每天需要鲜销部分!$K:$K,根据产能每天需要鲜销部分!$B:$B,$B544,根据产能每天需要鲜销部分!$G:$G,$C544) -> 47190 | G544: =_xlfn.XLOOKUP($C544,价格系数辅助表!$C:$C,价格系数辅助表!$E:$E) -> 1.1852119 | H544: =G544*$J544 -> 10.574018 | I544: =_xlfn.XLOOKUP(B544,'3.屠宰能力表'!B:B,'3.屠宰能力表'!D:D) -> 湖北 | J544: =_xlfn.XLOOKUP(A544,'1.出栏表'!A:A,'1.出栏表'!F:F) -> 8.9216268
A545: =I545&D545 -> 湖北46136 | B545: 1521 | C545: 猪头 | D545: 46136 | F545: =SUMIFS(根据产能每天需要鲜销部分!$K:$K,根据产能每天需要鲜销部分!$B:$B,$B545,根据产能每天需要鲜销部分!$G:$G,$C545) -> 2860.5877 | G545: =_xlfn.XLOOKUP($C545,价格系数辅助表!$C:$C,价格系数辅助表!$E:$E) -> 0.81317167 | H545: =G545*$J545 -> 7.2548142 | I545: =_xlfn.XLOOKUP(B545,'3.屠宰能力表'!B:B,'3.屠宰能力表'!D:D) -> 湖北 | J545: =_xlfn.XLOOKUP(A545,'1.出栏表'!A:A,'1.出栏表'!F:F) -> 8.9216268
A546: =I546&D546 -> 湖北46136 | B546: 1521 | C546: 猪尾 | D546: 46136 | F546: =SUMIFS(根据产能每天需要鲜销部分!$K:$K,根据产能每天需要鲜销部分!$B:$B,$B546,根据产能每天需要鲜销部分!$G:$G,$C546) -> 21.491007 | G546: =_xlfn.XLOOKUP($C546,价格系数辅助表!$C:$C,价格系数辅助表!$E:$E) -> 4.0225512 | H546: =G546*$J546 -> 35.887701 | I546: =_xlfn.XLOOKUP(B546,'3.屠宰能力表'!B:B,'3.屠宰能力表'!D:D) -> 湖北 | J546: =_xlfn.XLOOKUP(A546,'1.出栏表'!A:A,'1.出栏表'!F:F) -> 8.9216268
A547: =I547&D547 -> 湖北46136 | B547: 1521 | C547: 猪心 | D547: 46136 | F547: =SUMIFS(根据产能每天需要鲜销部分!$K:$K,根据产能每天需要鲜销部分!$B:$B,$B547,根据产能每天需要鲜销部分!$G:$G,$C547) -> 202.17383 | G547: =_xlfn.XLOOKUP($C547,价格系数辅助表!$C:$C,价格系数辅助表!$E:$E) -> 0.84535964 | H547: =G547*$J547 -> 7.5419833 | I547: =_xlfn.XLOOKUP(B547,'3.屠宰能力表'!B:B,'3.屠宰能力表'!D:D) -> 湖北 | J547: =_xlfn.XLOOKUP(A547,'1.出栏表'!A:A,'1.出栏表'!F:F) -> 8.9216268
A548: =I548&D548 -> 湖北46136 | B548: 1521 | C548: 猪肝 | D548: 46136 | F548: =SUMIFS(根据产能每天需要鲜销部分!$K:$K,根据产能每天需要鲜销部分!$B:$B,$B548,根据产能每天需要鲜销部分!$G:$G,$C548) -> 1044.3046 | G548: =_xlfn.XLOOKUP($C548,价格系数辅助表!$C:$C,价格系数辅助表!$E:$E) -> 0.37320475 | H548: =G548*$J548 -> 3.3295936 | I548: =_xlfn.XLOOKUP(B548,'3.屠宰能力表'!B:B,'3.屠宰能力表'!D:D) -> 湖北 | J548: =_xlfn.XLOOKUP(A548,'1.出栏表'!A:A,'1.出栏表'!F:F) -> 8.9216268
A549: =I549&D549 -> 湖北46136 | B549: 1521 | C549: 猪腰 | D549: 46136 | F549: =SUMIFS(根据产能每天需要鲜销部分!$K:$K,根据产能每天需要鲜销部分!$B:$B,$B549,根据产能每天需要鲜销部分!$G:$G,$C549) -> 204.16457 | G549: =_xlfn.XLOOKUP($C549,价格系数辅助表!$C:$C,价格系数辅助表!$E:$E) -> 1.1550192 | H549: =G549*$J549 -> 10.30465 | I549: =_xlfn.XLOOKUP(B549,'3.屠宰能力表'!B:B,'3.屠宰能力表'!D:D) -> 湖北 | J549: =_xlfn.XLOOKUP(A549,'1.出栏表'!A:A,'1.出栏表'!F:F) -> 8.9216268
A550: =I550&D550 -> 湖北46136 | B550: 1521 | C550: 大肠 | D550: 46136 | F550: =SUMIFS(根据产能每天需要鲜销部分!$K:$K,根据产能每天需要鲜销部分!$B:$B,$B550,根据产能每天需要鲜销部分!$G:$G,$C550) -> 714.43673 | G550: =_xlfn.XLOOKUP($C550,价格系数辅助表!$C:$C,价格系数辅助表!$E:$E) -> 1.9080014 | H550: =G550*$J550 -> 17.022476 | I550: =_xlfn.XLOOKUP(B550,'3.屠宰能力表'!B:B,'3.屠宰能力表'!D:D) -> 湖北 | J550: =_xlfn.XLOOKUP(A550,'1.出栏表'!A:A,'1.出栏表'!F:F) -> 8.9216268
A551: =I551&D551 -> 湖北46136 | B551: 1521 | C551: 猪肚 | D551: 46136 | F551: =SUMIFS(根据产能每天需要鲜销部分!$K:$K,根据产能每天需要鲜销部分!$B:$B,$B551,根据产能每天需要鲜销部分!$G:$G,$C551) -> 327.73786 | G551: =_xlfn.XLOOKUP($C551,价格系数辅助表!$C:$C,价格系数辅助表!$E:$E) -> 2.7678324 | H551: =G551*$J551 -> 24.693568 | I551: =_xlfn.XLOOKUP(B551,'3.屠宰能力表'!B:B,'3.屠宰能力表'!D:D) -> 湖北 | J551: =_xlfn.XLOOKUP(A551,'1.出栏表'!A:A,'1.出栏表'!F:F) -> 8.9216268
A552: =I552&D552 -> 湖北46136 | B552: 1521 | C552: 罗膈肉 | D552: 46136 | F552: =SUMIFS(根据产能每天需要鲜销部分!$K:$K,根据产能每天需要鲜销部分!$B:$B,$B552,根据产能每天需要鲜销部分!$G:$G,$C552) -> 274.01034 | G552: =_xlfn.XLOOKUP($C552,价格系数辅助表!$C:$C,价格系数辅助表!$E:$E) -> 1.6170864 | H552: =G552*$J552 -> 14.427042 | I552: =_xlfn.XLOOKUP(B552,'3.屠宰能力表'!B:B,'3.屠宰能力表'!D:D) -> 湖北 | J552: =_xlfn.XLOOKUP(A552,'1.出栏表'!A:A,'1.出栏表'!F:F) -> 8.9216268
A553: =I553&D553 -> 湖北46136 | B553: 1521 | C553: 猪舌 | D553: 46136 | F553: =SUMIFS(根据产能每天需要鲜销部分!$K:$K,根据产能每天需要鲜销部分!$B:$B,$B553,根据产能每天需要鲜销部分!$G:$G,$C553) -> 241.77383 | G553: =_xlfn.XLOOKUP($C553,价格系数辅助表!$C:$C,价格系数辅助表!$E:$E) -> 1.4850675 | H553: =G553*$J553 -> 13.249218 | I553: =_xlfn.XLOOKUP(B553,'3.屠宰能力表'!B:B,'3.屠宰能力表'!D:D) -> 湖北 | J553: =_xlfn.XLOOKUP(A553,'1.出栏表'!A:A,'1.出栏表'!F:F) -> 8.9216268
A554: =I554&D554 -> 湖北46136 | B554: 1521 | C554: 大肠头 | D554: 46136 | F554: =SUMIFS(根据产能每天需要鲜销部分!$K:$K,根据产能每天需要鲜销部分!$B:$B,$B554,根据产能每天需要鲜销部分!$G:$G,$C554) -> 177.30081 | G554: =_xlfn.XLOOKUP($C554,价格系数辅助表!$C:$C,价格系数辅助表!$E:$E) -> 1.8971615 | H554: =G554*$J554 -> 16.925767 | I554: =_xlfn.XLOOKUP(B554,'3.屠宰能力表'!B:B,'3.屠宰能力表'!D:D) -> 湖北 | J554: =_xlfn.XLOOKUP(A554,'1.出栏表'!A:A,'1.出栏表'!F:F) -> 8.9216268
A555: =I555&D555 -> 湖北46136 | B555: 1521 | C555: 心血管 | D555: 46136 | F555: =SUMIFS(根据产能每天需要鲜销部分!$K:$K,根据产能每天需要鲜销部分!$B:$B,$B555,根据产能每天需要鲜销部分!$G:$G,$C555) -> 19.150402 | G555: =_xlfn.XLOOKUP($C555,价格系数辅助表!$C:$C,价格系数辅助表!$E:$E) -> 3.2997149 | H555: =G555*$J555 -> 29.438825 | I555: =_xlfn.XLOOKUP(B555,'3.屠宰能力表'!B:B,'3.屠宰能力表'!D:D) -> 湖北 | J555: =_xlfn.XLOOKUP(A555,'1.出栏表'!A:A,'1.出栏表'!F:F) -> 8.9216268
... A704: =I704&D704 -> 广东46136 | B704: 1810 | C704: 猪血 | D704: 46136 | F704: =SUMIFS(根据产能每天需要鲜销部分!$K:$K,根据产能每天需要鲜销部分!$B:$B,$B704,根据产能每天需要鲜销部分!$G:$G,$C704) -> 3816 | G704: =_xlfn.XLOOKUP($C704,价格系数辅助表!$C:$C,价格系数辅助表!$E:$E) -> 0.087444985 | H704: =G704*$J704 -> 0.80539855 | I704: =_xlfn.XLOOKUP(B704,'3.屠宰能力表'!B:B,'3.屠宰能力表'!D:D) -> 广东 | J704: =_xlfn.XLOOKUP(A704,'1.出栏表'!A:A,'1.出栏表'!F:F) -> 9.2103457

Sheet 8.深加工需求表
B2: 工厂ID | C2: 公司名称 | D2: 分割部位 | E2: 日期 | F2: 工厂类别 | G2: 深加工的原料需求量 | H2: 销售价格 | I2: 订单售达省份
B3: 0138 | C3: 正大食品（秦皇岛）有限公司 | D3: 前腿肌肉 | F3: 自有深加工 | G3: 2409.3542 | H3: 13.292811 | I3: 河北
B4: 0459 | C4: 正大食品（青岛）有限公司 | D4: 前腿肌肉 | F4: 自有深加工 | G4: 8519.88 | H4: 13.292811 | I4: 山东
B5: 1537 | C5: 正大食品（襄阳）有限公司 | D5: 前腿肌肉 | F5: 自有深加工 | G5: 753.84306 | H5: 13.292811 | I5: 湖北
B6: 0650 | C6: 正大食品（成都）有限公司 | D6: 前腿肌肉 | F6: 自有深加工 | G6: 1319.2254 | H6: 13.292811 | I6: 四川
B7: 0750 | C7: 正大食品（义乌）有限公司 | D7: 前腿肌肉 | F7: 自有深加工 | G7: 994.65404 | H7: 13.292811 | I7: 浙江
B8: 1537 | C8: 正大食品（湖北）有限公司 | D8: 前腿肌肉 | F8: 自有深加工 | G8: 5634.9926 | H8: 13.292811 | I8: 湖北
B9: 1538 | C9: 正大食品企业（洛阳）有限公司 | D9: 前腿肌肉 | F9: 自有深加工 | G9: 2669.9644 | H9: 13.292811 | I9: 河南
B10: 1448 | C10: 卜蜂食品（徐州）有限公司 | D10: 前腿肌肉 | F10: 自有深加工 | G10: 3596.6667 | H10: 13.292811 | I10: 江苏
B11: 1306 | C11: 内蒙古卜蜂食品有限公司 | D11: 前腿肌肉 | F11: 自有深加工 | G11: 1045.0335 | H11: 13.292811 | I11: 内蒙古
B12: 0138 | C12: 正大食品（秦皇岛）有限公司 | D12: 后腿肌肉 | F12: 自有深加工 | G12: 5326.9645 | H12: 13.545028 | I12: 河北
B13: 0459 | C13: 正大食品（青岛）有限公司 | D13: 后腿肌肉 | F13: 自有深加工 | G13: 25155.054 | H13: 13.545028 | I13: 山东
B14: 1537 | C14: 正大食品（襄阳）有限公司 | D14: 后腿肌肉 | F14: 自有深加工 | G14: 1594.3848 | H14: 13.545028 | I14: 湖北
B15: 0650 | C15: 正大食品（成都）有限公司 | D15: 后腿肌肉 | F15: 自有深加工 | G15: 2790.1734 | H15: 13.545028 | I15: 四川
B16: 0750 | C16: 正大食品（义乌）有限公司 | D16: 后腿肌肉 | F16: 自有深加工 | G16: 2103.7022 | H16: 13.545028 | I16: 浙江
B17: 1537 | C17: 正大食品（湖北）有限公司 | D17: 后腿肌肉 | F17: 自有深加工 | G17: 987.67706 | H17: 13.545028 | I17: 湖北
B18: 1538 | C18: 正大食品企业（洛阳）有限公司 | D18: 后腿肌肉 | F18: 自有深加工 | G18: 3068.3947 | H18: 13.545028 | I18: 河南
B19: 1448 | C19: 卜蜂食品（徐州）有限公司 | D19: 后腿肌肉 | F19: 自有深加工 | G19: 7136.5869 | H19: 13.545028 | I19: 江苏
B20: 1306 | C20: 内蒙古卜蜂食品有限公司 | D20: 后腿肌肉 | F20: 自有深加工 | G20: 5890.702 | H20: 13.545028 | I20: 内蒙古
B21: 0138 | C21: 正大食品（秦皇岛）有限公司 | D21: 精碎肉 | F21: 自有深加工 | G21: 1045.8882 | H21: 10.779303 | I21: 河北
B22: 0459 | C22: 正大食品（青岛）有限公司 | D22: 精碎肉 | F22: 自有深加工 | G22: 3014.5799 | H22: 10.779303 | I22: 山东
B23: 1537 | C23: 正大食品（襄阳）有限公司 | D23: 精碎肉 | F23: 自有深加工 | G23: 300 | H23: 10.779303 | I23: 湖北
B24: 0650 | C24: 正大食品（成都）有限公司 | D24: 精碎肉 | F24: 自有深加工 | G24: 525 | H24: 10.779303 | I24: 四川
B25: 0750 | C25: 正大食品（义乌）有限公司 | D25: 精碎肉 | F25: 自有深加工 | G25: 395.83333 | H25: 10.779303 | I25: 浙江
B26: 1537 | C26: 正大食品（湖北）有限公司 | D26: 精碎肉 | F26: 自有深加工 | G26: 0 | H26: 10.779303 | I26: 湖北
B27: 1538 | C27: 正大食品企业（洛阳）有限公司 | D27: 精碎肉 | F27: 自有深加工 | G27: 110.47111 | H27: 10.779303 | I27: 河南
B28: 1448 | C28: 卜蜂食品（徐州）有限公司 | D28: 精碎肉 | F28: 自有深加工 | G28: 173.33333 | H28: 10.779303 | I28: 江苏
B29: 1306 | C29: 内蒙古卜蜂食品有限公司 | D29: 精碎肉 | F29: 自有深加工 | G29: 522.29785 | H29: 10.779303 | I29: 内蒙古
B30: 0138 | C30: 正大食品（秦皇岛）有限公司 | D30: 肥膘 | F30: 自有深加工 | G30: 4700.5026 | H30: 8.04378 | I30: 河北
B31: 0459 | C31: 正大食品（青岛）有限公司 | D31: 肥膘 | F31: 自有深加工 | G31: 18200.839 | H31: 8.04378 | I31: 山东
B32: 1537 | C32: 正大食品（襄阳）有限公司 | D32: 肥膘 | F32: 自有深加工 | G32: 1451.7721 | H32: 8.04378 | I32: 湖北
B33: 0650 | C33: 正大食品（成都）有限公司 | D33: 肥膘 | F33: 自有深加工 | G33: 2540.6012 | H33: 8.04378 | I33: 四川
B34: 0750 | C34: 正大食品（义乌）有限公司 | D34: 肥膘 | F34: 自有深加工 | G34: 1915.5327 | H34: 8.04378 | I34: 浙江
B35: 1537 | C35: 正大食品（湖北）有限公司 | D35: 肥膘 | F35: 自有深加工 | G35: 0 | H35: 8.04378 | I35: 湖北
B36: 1538 | C36: 正大食品企业（洛阳）有限公司 | D36: 肥膘 | F36: 自有深加工 | G36: 331.41333 | H36: 8.04378 | I36: 河南
B37: 1448 | C37: 卜蜂食品（徐州）有限公司 | D37: 肥膘 | F37: 自有深加工 | G37: 520 | H37: 8.04378 | I37: 江苏
B38: 1306 | C38: 内蒙古卜蜂食品有限公司 | D38: 肥膘 | F38: 自有深加工 | G38: 1385.8457 | H38: 8.04378 | I38: 内蒙古
B39: 0138 | C39: 正大食品（秦皇岛）有限公司 | D39: 槽头 | F39: 自有深加工 | G39: 522.94411 | H39: 4.9513782 | I39: 河北
B40: 0459 | C40: 正大食品（青岛）有限公司 | D40: 槽头 | F40: 自有深加工 | G40: 1689.7607 | H40: 4.9513782 | I40: 山东
B41: 1537 | C41: 正大食品（襄阳）有限公司 | D41: 槽头 | F41: 自有深加工 | G41: 150 | H41: 4.9513782 | I41: 湖北
B42: 0650 | C42: 正大食品（成都）有限公司 | D42: 槽头 | F42: 自有深加工 | G42: 262.5 | H42: 4.9513782 | I42: 四川
B43: 0750 | C43: 正大食品（义乌）有限公司 | D43: 槽头 | F43: 自有深加工 | G43: 197.91667 | H43: 4.9513782 | I43: 浙江
B44: 1537 | C44: 正大食品（湖北）有限公司 | D44: 槽头 | F44: 自有深加工 | G44: 2222.1481 | H44: 4.9513782 | I44: 湖北
B45: 1538 | C45: 正大食品企业（洛阳）有限公司 | D45: 槽头 | F45: 自有深加工 | G45: 938.88889 | H45: 4.9513782 | I45: 河南
B46: 1448 | C46: 卜蜂食品（徐州）有限公司 | D46: 槽头 | F46: 自有深加工 | G46: 1733.3333 | H46: 4.9513782 | I46: 江苏
B47: 1306 | C47: 内蒙古卜蜂食品有限公司 | D47: 槽头 | F47: 自有深加工 | G47: 323.7963 | H47: 4.9513782 | I47: 内蒙古
B48: 0138 | C48: 正大食品（秦皇岛）有限公司 | D48: 带肉后棒骨 | F48: 自有深加工 | G48: 0 | H48: 9.3292895 | I48: 河北
B49: 0459 | C49: 正大食品（青岛）有限公司 | D49: 带肉后棒骨 | F49: 自有深加工 | G49: 0 | H49: 9.3292895 | I49: 山东
B50: 1537 | C50: 正大食品（襄阳）有限公司 | D50: 带肉后棒骨 | F50: 自有深加工 | G50: 0 | H50: 9.3292895 | I50: 湖北
B51: 0650 | C51: 正大食品（成都）有限公司 | D51: 带肉后棒骨 | F51: 自有深加工 | G51: 0 | H51: 9.3292895 | I51: 四川
B52: 0750 | C52: 正大食品（义乌）有限公司 | D52: 带肉后棒骨 | F52: 自有深加工 | G52: 0 | H52: 9.3292895 | I52: 浙江
B53: 1537 | C53: 正大食品（湖北）有限公司 | D53: 带肉后棒骨 | F53: 自有深加工 | G53: 2266.3287 | H53: 9.3292895 | I53: 湖北
B54: 1538 | C54: 正大食品企业（洛阳）有限公司 | D54: 带肉后棒骨 | F54: 自有深加工 | G54: 605.13398 | H54: 9.3292895 | I54: 河南
B55: 1448 | C55: 卜蜂食品（徐州）有限公司 | D55: 带肉后棒骨 | F55: 自有深加工 | G55: 0 | H55: 9.3292895 | I55: 江苏
B56: 1306 | C56: 内蒙古卜蜂食品有限公司 | D56: 带肉后棒骨 | F56: 自有深加工 | G56: 117.85381 | H56: 9.3292895 | I56: 内蒙古
B57: 0138 | C57: 正大食品（秦皇岛）有限公司 | D57: 肋排 | F57: 自有深加工 | G57: 0 | H57: 37.577805 | I57: 河北
B58: 0459 | C58: 正大食品（青岛）有限公司 | D58: 肋排 | F58: 自有深加工 | G58: 0 | H58: 37.577805 | I58: 山东
B59: 1537 | C59: 正大食品（襄阳）有限公司 | D59: 肋排 | F59: 自有深加工 | G59: 0 | H59: 37.577805 | I59: 湖北
B60: 0650 | C60: 正大食品（成都）有限公司 | D60: 肋排 | F60: 自有深加工 | G60: 0 | H60: 37.577805 | I60: 四川
B61: 0750 | C61: 正大食品（义乌）有限公司 | D61: 肋排 | F61: 自有深加工 | G61: 0 | H61: 37.577805 | I61: 浙江
B62: 1537 | C62: 正大食品（湖北）有限公司 | D62: 肋排 | F62: 自有深加工 | G62: 6694.4378 | H62: 37.577805 | I62: 湖北
B63: 1538 | C63: 正大食品企业（洛阳）有限公司 | D63: 肋排 | F63: 自有深加工 | G63: 2046.6501 | H63: 37.577805 | I63: 河南
B64: 1448 | C64: 卜蜂食品（徐州）有限公司 | D64: 肋排 | F64: 自有深加工 | G64: 1300 | H64: 37.577805 | I64: 江苏
B65: 1306 | C65: 内蒙古卜蜂食品有限公司 | D65: 肋排 | F65: 自有深加工 | G65: 333.67967 | H65: 37.577805 | I65: 内蒙古
B66: 0138 | C66: 正大食品（秦皇岛）有限公司 | D66: 五花肉 | F66: 自有深加工 | G66: 0 | H66: 21.245895 | I66: 河北
B67: 0459 | C67: 正大食品（青岛）有限公司 | D67: 五花肉 | F67: 自有深加工 | G67: 0 | H67: 21.245895 | I67: 山东
B68: 1537 | C68: 正大食品（襄阳）有限公司 | D68: 五花肉 | F68: 自有深加工 | G68: 0 | H68: 21.245895 | I68: 湖北
B69: 0650 | C69: 正大食品（成都）有限公司 | D69: 五花肉 | F69: 自有深加工 | G69: 0 | H69: 21.245895 | I69: 四川
B70: 0750 | C70: 正大食品（义乌）有限公司 | D70: 五花肉 | F70: 自有深加工 | G70: 0 | H70: 21.245895 | I70: 浙江
B71: 1537 | C71: 正大食品（湖北）有限公司 | D71: 五花肉 | F71: 自有深加工 | G71: 15712.4 | H71: 21.245895 | I71: 湖北
B72: 1538 | C72: 正大食品企业（洛阳）有限公司 | D72: 五花肉 | F72: 自有深加工 | G72: 4924.4444 | H72: 21.245895 | I72: 河南
B73: 1448 | C73: 卜蜂食品（徐州）有限公司 | D73: 五花肉 | F73: 自有深加工 | G73: 4550 | H73: 21.245895 | I73: 江苏
B74: 1306 | C74: 内蒙古卜蜂食品有限公司 | D74: 五花肉 | F74: 自有深加工 | G74: 731.85185 | H74: 21.245895 | I74: 内蒙古
B75: 0138 | C75: 正大食品（秦皇岛）有限公司 | D75: 大排肌肉 | F75: 自有深加工 | G75: 0 | H75: 14.198626 | I75: 河北
B76: 0459 | C76: 正大食品（青岛）有限公司 | D76: 大排肌肉 | F76: 自有深加工 | G76: 0 | H76: 14.198626 | I76: 山东
B77: 1537 | C77: 正大食品（襄阳）有限公司 | D77: 大排肌肉 | F77: 自有深加工 | G77: 0 | H77: 14.198626 | I77: 湖北
B78: 0650 | C78: 正大食品（成都）有限公司 | D78: 大排肌肉 | F78: 自有深加工 | G78: 0 | H78: 14.198626 | I78: 四川
B79: 0750 | C79: 正大食品（义乌）有限公司 | D79: 大排肌肉 | F79: 自有深加工 | G79: 0 | H79: 14.198626 | I79: 浙江
B80: 1537 | C80: 正大食品（湖北）有限公司 | D80: 大排肌肉 | F80: 自有深加工 | G80: 787.03704 | H80: 14.198626 | I80: 湖北
B81: 1538 | C81: 正大食品企业（洛阳）有限公司 | D81: 大排肌肉 | F81: 自有深加工 | G81: 2814.6199 | H81: 14.198626 | I81: 河南
B82: 1448 | C82: 卜蜂食品（徐州）有限公司 | D82: 大排肌肉 | F82: 自有深加工 | G82: 6617.709 | H82: 14.198626 | I82: 江苏
B83: 1306 | C83: 内蒙古卜蜂食品有限公司 | D83: 大排肌肉 | F83: 自有深加工 | G83: 0 | H83: 14.198626 | I83: 内蒙古
B84: 0138 | C84: 正大食品（秦皇岛）有限公司 | D84: 猪肘 | F84: 自有深加工 | G84: 0 | H84: 9.696 | I84: 河北
B85: 0459 | C85: 正大食品（青岛）有限公司 | D85: 猪肘 | F85: 自有深加工 | G85: 10390.073 | H85: 9.696 | I85: 山东
B86: 1537 | C86: 正大食品（襄阳）有限公司 | D86: 猪肘 | F86: 自有深加工 | G86: 0 | H86: 9.696 | I86: 湖北
B87: 0650 | C87: 正大食品（成都）有限公司 | D87: 猪肘 | F87: 自有深加工 | G87: 0 | H87: 9.696 | I87: 四川
B88: 0750 | C88: 正大食品（义乌）有限公司 | D88: 猪肘 | F88: 自有深加工 | G88: 0 | H88: 9.696 | I88: 浙江
B89: 1537 | C89: 正大食品（湖北）有限公司 | D89: 猪肘 | F89: 自有深加工 | G89: 5925.7037 | H89: 9.696 | I89: 湖北
B90: 1538 | C90: 正大食品企业（洛阳）有限公司 | D90: 猪肘 | F90: 自有深加工 | G90: 1927.7778 | H90: 9.696 | I90: 河南
B91: 1448 | C91: 卜蜂食品（徐州）有限公司 | D91: 猪肘 | F91: 自有深加工 | G91: 1733.3333 | H91: 9.696 | I91: 江苏
B92: 1306 | C92: 内蒙古卜蜂食品有限公司 | D92: 猪肘 | F92: 自有深加工 | G92: 288.88889 | H92: 9.696 | I92: 内蒙古
B93: 0138 | C93: 正大食品（秦皇岛）有限公司 | D93: 猪蹄 | F93: 自有深加工 | G93: 0 | H93: 19.154399 | I93: 河北
B94: 0459 | C94: 正大食品（青岛）有限公司 | D94: 猪蹄 | F94: 自有深加工 | G94: 0 | H94: 19.154399 | I94: 山东
B95: 1537 | C95: 正大食品（襄阳）有限公司 | D95: 猪蹄 | F95: 自有深加工 | G95: 0 | H95: 19.154399 | I95: 湖北
B96: 0650 | C96: 正大食品（成都）有限公司 | D96: 猪蹄 | F96: 自有深加工 | G96: 0 | H96: 19.154399 | I96: 四川
B97: 0750 | C97: 正大食品（义乌）有限公司 | D97: 猪蹄 | F97: 自有深加工 | G97: 0 | H97: 19.154399 | I97: 浙江
B98: 1537 | C98: 正大食品（湖北）有限公司 | D98: 猪蹄 | F98: 自有深加工 | G98: 2360.386 | H98: 19.154399 | I98: 湖北
B99: 1538 | C99: 正大食品企业（洛阳）有限公司 | D99: 猪蹄 | F99: 自有深加工 | G99: 932.60593 | H99: 19.154399 | I99: 河南
B100: 1448 | C100: 卜蜂食品（徐州）有限公司 | D100: 猪蹄 | F100: 自有深加工 | G100: 1516.6667 | H100: 19.154399 | I100: 江苏
B101: 1306 | C101: 内蒙古卜蜂食品有限公司 | D101: 猪蹄 | F101: 自有深加工 | G101: 105.89246 | H101: 19.154399 | I101: 内蒙古
...

Sheet 9.运输费用表
B2: 工厂id | C2: 订单售达省份 | D2: 运输成本-元/kg/公里 | E2: 距离-公里
B3: 0567 | C3: 湖北 | D3: 0.000625 | E3: 1250
B4: 0567 | C4: 湖北 | D4: 0.000625 | E4: 1200
B5: 0567 | C5: 湖北 | D5: 0.00095833333 | E5: 800
B6: 0567 | C6: 湖北 | D6: 0.00095833333 | E6: 700
B7: 0567 | C7: 湖北 | D7: 0.000625 | E7: 1400
B8: 0567 | C8: 湖北 | D8: 0.00095833333 | E8: 500
B9: 0567 | C9: 湖北 | D9: 0.00095833333 | E9: 750
B10: 0567 | C10: 湖北 | D10: 0.0005 | E10: 3200
B11: 0567 | C11: 湖北 | D11: 0.00058333333 | E11: 1700
B12: 0567 | C12: 湖北 | D12: 0.0010416667 | E12: 400
B13: 0567 | C13: 湖北 | D13: 0.0010416667 | E13: 400
B14: 0567 | C14: 湖北 | D14: 0 | E14: 0
... B562: 1810 | C562: 广东 | D562: 0.0005 | E562: 2400
B563: 1522 | C563: 湖北 | D563: 0.000625 | E563: 1250
B564: 1522 | C564: 湖北 | D564: 0.000625 | E564: 1200
B565: 1522 | C565: 湖北 | D565: 0.00095833333 | E565: 800
B566: 1522 | C566: 湖北 | D566: 0.00095833333 | E566: 700
B567: 1522 | C567: 湖北 | D567: 0.000625 | E567: 1400
B568: 1522 | C568: 湖北 | D568: 0.00095833333 | E568: 500
B569: 1522 | C569: 湖北 | D569: 0.00095833333 | E569: 750
B570: 1522 | C570: 湖北 | D570: 0.0005 | E570: 3200
B571: 1522 | C571: 湖北 | D571: 0.00058333333 | E571: 1700
B572: 1522 | C572: 湖北 | D572: 0.0010416667 | E572: 400
B573: 1522 | C573: 湖北 | D573: 0.0010416667 | E573: 400
B574: 1522 | C574: 湖北 | D574: 0 | E574: 0
... B590: 1522 | C590: 湖北 | D590: 0.000625 | E590: 1412
B591: 1521 | C591: 湖北 | D591: 0.000625 | E591: 1250
B592: 1521 | C592: 湖北 | D592: 0.000625 | E592: 1200
B593: 1521 | C593: 湖北 | D593: 0.00095833333 | E593: 800
B594: 1521 | C594: 湖北 | D594: 0.00095833333 | E594: 700
B595: 1521 | C595: 湖北 | D595: 0.000625 | E595: 1400
B596: 1521 | C596: 湖北 | D596: 0.00095833333 | E596: 500
B597: 1521 | C597: 湖北 | D597: 0.00095833333 | E597: 750
B598: 1521 | C598: 湖北 | D598: 0.0005 | E598: 3200
B599: 1521 | C599: 湖北 | D599: 0.00058333333 | E599: 1700
B600: 1521 | C600: 湖北 | D600: 0.0010416667 | E600: 400
B601: 1521 | C601: 湖北 | D601: 0.0010416667 | E601: 400
B602: 1521 | C602: 湖北 | D602: 0 | E602: 0
... B618: 1521 | C618: 湖北 | D618: 0.000625 | E618: 1412

Sheet 辅助表→

Sheet 系数辅助表
C2: 全分割部位 | D2: 产量占比 | E2: 单头产量 | F2: 产值系数 | G2: 产值占比
B3: 是否储备 | D3: % | E3: kg/头 | G3: %
C4: 白条 | D4: 0.715 | E4: =120*D4 -> 85.8 | F4: 1.33 | G4: 0.85
B5: 储备 | C5: 五花肉 | D5: 0.097050752 | E5: 11.64609 | F5: 2.28 | G5: 0.20344029 | I5: 白条产值占比 | J5: 0.85
B6: 储备 | C6: 大排肌肉 | D6: 0.046512517 | E6: 5.5815021 | F6: 1.5237233 | G6: 0.065159715 | I6: 副产品产值占比 | J6: 0.15
B7: 储备 | C7: 肋排 | D7: 0.028731738 | E7: 3.4478085 | F7: 4.0326564 | G7: 0.10652617
B8: 非储备 | C8: 前排 | D8: 0.029020999 | E8: 3.4825199 | F8: 2.34858 | G8: 0.062664406
B9: 储备 | C9: 颈背肌肉 | D9: 0.033890751 | E9: 4.0668901 | F9: 1.4108769 | G9: 0.043961605
B10: 储备 | C10: 小里脊 | D10: 0.0066683831 | E10: 0.80020597 | F10: 1.9051023 | G10: 0.011679979
B11: 储备 | C11: 前腿肌肉 | D11: 0.073037535 | E11: 8.7645042 | F11: 1.4265159 | G11: 0.095791274
B12: 储备 | C12: 后腿肌肉 | D12: 0.12205173 | E12: 14.646207 | F12: 1.4535826 | G12: 0.16311235
B13: 储备 | C13: 前肘 | D13: 0.019521507 | E13: 2.3425809 | F13: 1.4410381 | G13: 0.025863782
B14: 储备 | C14: 后肘 | D14: 0.02755221 | E14: 3.3062652 | F14: 1.2358326 | G14: 0.031305403
B15: 储备 | C15: 猪肘 | D15: 0.047073717 | E15: 5.648846 | F15: 1.3384354 | G15: 0.057169185
B16: 储备 | C16: 肥膘 | D16: 0.061357303 | E16: 7.3628764 | F16: 0.86321702 | G16: 0.048695572
B17: 非储备 | C17: 脊膘 | D17: 0.013016588 | E17: 1.5619906 | F17: 0.79687393 | G17: 0.0095365217
B18: 非储备 | C18: 脊骨 | D18: 0.029868561 | E18: 3.5842273 | F18: 1.0988087 | G18: 0.030174467
... B53: 非储备 | C53: 猪血 | D53: 0.02 | E53: 2.4 | F53: 0.084848664 | G53: 0.0097489051

Sheet 价格系数辅助表
C2: 全分割部位 | D2: 冻价格系数 | E2: 鲜价格系数
B4: 储备 | C4: 五花肉 | D4: 2.2131141 | E4: 2.336349
B5: 储备 | C5: 大排肌肉 | D5: 1.4790235 | E5: 1.5613813
B6: 储备 | C6: 肋排 | D6: 3.9143547 | E6: 4.1323214
B7: 非储备 | C7: 前排 | D7: 2.2796822 | E7: 2.4066239
B8: 储备 | C8: 颈背肌肉 | D8: 1.3694876 | E8: 1.445746
B9: 储备 | C9: 小里脊 | D9: 1.8492144 | E9: 1.9521859
B10: 储备 | C10: 前腿肌肉 | D10: 1.3846678 | E10: 1.4617715
B11: 储备 | C11: 后腿肌肉 | D11: 1.4109404 | E11: 1.4895071
B12: 非储备 | C12: 前肘 | D12: 1.398764 | E12: 1.4766526
B13: 非储备 | C13: 后肘 | D13: 1.1995783 | E13: 1.2663756
B14: 储备 | C14: 肥膘 | D14: 0.83789375 | E14: 0.88455098
B15: 非储备 | C15: 脊膘 | D15: 0.7734969 | E15: 0.81656825
... B52: 非储备 | C52: 猪血 | D52: 0.080280887 | E52: 0.087444985
B53: 非储备 | C53: 白条 | E53: 1.1852119

Sheet 标准费用表-2024年&2025年优化
B2: 大区 | C2: 省区 | D2: 公司 | E2: 公司名称 | K2: 2025年修订版标准
F3: 自建/OEM | G3: 使用系统 | H3: 3211生产 | I3: 6711贸易 | J3: 4811事业线 | K3: 屠宰费用 | L3: 分割费用 | M3: 管理费用 | N3: 财务费用
K4: 元/头 | L4: 元/头 | M4: 元/头 | N4: 元/头
B5: 中南区 | C5: 湖北 | D5: 0567 | E5: 正大食品（襄阳）有限公司 | F5: 自有 | G5: ework+SAP | H5: √ | I5: √ | K5: 40 | L5: 80 | M5: 15 | N5: 10
B6: 中东南区 | C6: 河南 | D6: 0555 | E6: 洛阳正大食品有限公司 | F6: 自有 | G6: ework+SAP | H6: √ | I6: √ | K6: 32.492328 | L6: 52.457086 | M6: 14.423854 | N6: 2.3719415
B7: 罗家顺区 | C7: 江苏 | D7: 0476 | E7: 正大食品（徐州）有限公司 | F7: 自有 | G7: ework+SAP | H7: √ | I7: √ | K7: 43.901675 | L7: 51.169902 | M7: 15.716339 | N7: 17.51681
B8: 北方区 | C8: 内蒙 | D8: 0370 | E8: 内蒙古正大鸿业食品有限公司 | F8: 自有 | G8: ework+SAP | H8: √ | I8: √ | K8: 46.607942 | L8: 51.983905 | M8: 16.846007 | N8: 8.1479757
B9: 北方区 | C9: 山西 | D9: 0377 | E9: 大同正大食品有限公司 | F9: 自有 | G9: ework+SAP | H9: √ | I9: √ | K9: 60.276452 | L9: 51.633303 | M9: 19.368692 | N9: 4.8505056
B10: 北方区 | C10: 甘肃 | D10: 0388 | E10: 庆阳正大食品有限公司 | F10: 自有 | G10: SAP | H10: √ | I10: √ | K10: 48.586123 | L10: 53.472329 | M10: 16.138436 | N10: 7.6396363
B11: 西南区 | C11: 四川 | D11: 0638 | E11: 成都正大农牧食品有限公司 | F11: OEM | G11: SAP | H11: √ | I11: √ | K11: 48 | L11: 120 | M11: 2 | N11: 0.27692813
B12: 中南区 | C12: 湖南 | D12: 1533 | E12: 正大食品（长沙）有限公司 | F12: OEM | G12: SAP | H12: √ | I12: √ | K12: 77.058492 | L12: 60 | M12: 21.8 | N12: 6.16
B13: 中东南区 | C13: 安徽 | D13: 0760 | E13: 正大食品（利辛）有限公司 | F13: OEM | G13: SS+SAP | H13: √ | I13: √ | K13: 55 | L13: 39 | M13: 15 | N13: 0.07407508
B14: 中南区 | C14: 广西 | D14: 0692 | E14: 正大食品（来宾）有限公司 | F14: OEM | G14: SS | H14: √ | I14: √ | K14: 78.288112 | L14: 79.617503 | M14: 25.978966 | N14: 1.2570224
B15: 中南区 | C15: 湖北 | D15: 1522 | E15: 正大食品（咸宁）有限公司 | F15: OEM | G15: SAP总账 | H15: √ | K15: 71.808427 | L15: 44 | M15: 37 | N15: 0
B16: 中南区 | C16: 江西 | D16: 0813 | E16: 江西正大畜禽有限公司 | F16: OEM | G16: SS | H16: √ | I16: √ | K16: 71.948384 | M16: 7.5434944 | N16: 0
B17: 北方区 | C17: 辽宁 | D17: 0220 | E17: 辽宁正大畜禽有限公司 | F17: OEM | G17: SS | H17: √ | I17: √ | K17: 54.165599 | L17: 0 | M17: 1.5023881 | N17: 0
B18: 北方区 | C18: 吉林 | D18: 0261 | E18: 吉林中新正大食品有限公司 | F18: OEM | G18: SS | H18: √ | I18: √ | K18: 47.996551 | L18: 0 | M18: 1.7307985 | N18: 0.029229054
B19: 北方区 | C19: 新疆 | D19: 0360 | E19: 新疆正大畜禽有限公司 | F19: OEM | G19: SS | H19: √ | I19: √ | K19: 48.531442 | L19: 0 | M19: 16.376324 | N19: 0
B20: 北方区 | C20: 陕西 | D20: 0362 | E20: 陕西正大食品有限公司 | F20: OEM | G20: SS | H20: √ | I20: √ | K20: 55.333333 | L20: 0 | M20: 8.3383839 | N20: 0
B21: 西南区 | C21: 重庆 | D21: 1658 | E21: 重庆正大猪业有限公司 | F21: OEM | G21: SS | H21: √ | I21: √ | K21: 58.069381 | L21: 0 | M21: 24.548006 | N21: 0.6
B22: 西南区 | C22: 云南 | D22: 0648 | E22: 昆明正大农牧食品有限公司 | F22: OEM | G22: SS | H22: √ | I22: √ | K22: 65.194923 | L22: 0 | M22: 2.1 | N22: 2
B23: 中南区 | C23: 湛江 | D23: 0835 | E23: 湛江正大猪业有限公司 | F23: OEM | G23: SS | H23: √ | I23: √ | K23: 92.981952 | L23: 0 | M23: 7 | N23: 0
B24: 中南区 | C24: 贵州 | D24: 0662 | E24: 贵州正大农牧食品有限公司 | F24: OEM | G24: SS | H24: √ | I24: √ | K24: 64.293108 | L24: 0 | M24: 30 | N24: 0.13799686
B25: 中南区 | C25: 湖北 | D25: 0519 | F25: OEM | G25: SAP总账 | H25: √ | K25: 50 | L25: 0 | M25: 8 | N25: 1
B26: 罗家顺区 | C26: 山东 | D26: 1441 | E26: 正大食品（徐州）有限公司山东第二分公司 | F26: 贸易 | G26: SAP | I26: √ | K26: 46 | L26: 0 | M26: 7 | N26: 1
B27: 中南区 | C27: 福建 | D27: 0824 | E27: 福建卜蜂畜禽有限公司 | K27: 0 | L27: 0 | M27: 0 | N27: 0 | O27: =K27+L27+M27+N27 -> 0
B28: 浙江区 | C28: 浙江 | D28: 0770 | E28: 正大食品（慈溪）有限公司 | F28: OEM | G28: SAP | H28: √ | I28: √ | K28: 0 | L28: 0 | M28: 0 | N28: 0 | O28: =K28+L28+M28+N28 -> 0
B29: 罗家顺区 | C29: 广东（不含湛江） | D29: 1825 | E29: 正大食品（广州）有限公司 | F29: OEM | G29: SAP | H29: √ | I29: √ | K29: / | L29: / | M29: / | N29: /
D30: 1543 | K30: / | L30: / | M30: / | N30: /
B31: 罗家顺区 | C31: 上海 | D31: 0447 | E31: 正大食品（徐州）有限公司上海分公司 | F31: 贸易 | G31: SAP | I31: √ | K31: / | L31: / | M31: / | N31: /
B32: 罗家顺区 | C32: 江苏 | D32: 1434 | E32: 正大食品（徐州）有限公司苏州分公司 | F32: 贸易 | G32: SAP | I32: √ | K32: / | L32: / | M32: / | N32: /
B33: 罗家顺区 | C33: 浙江 | D33: 1830 | E33: 正大食品（徐州）有限公司浙江分公司 | F33: 贸易 | G33: SAP | I33: √ | K33: / | L33: / | M33: / | N33: /
B34: 北京战区 | C34: 北京 | D34: 1142 | E34: 内蒙古正大食品有限公司北京分公司 | F34: 贸易 | G34: SAP | I34: √ | K34: / | L34: / | M34: / | N34: /
B35: 北方区 | C35: 辽宁 | D35: 0294 | E35: 正大畜牧(阜新)有限公司 | F35: OEM | G35: SS | H35: √ | I35: √ | K35: 54.165599 | L35: 0 | M35: 1.5023881 | N35: 0
B36: 北方区 | C36: 甘肃 | D36: A388 | E36: 庆阳正大食品有限公司-OEM | F36: 自有 | G36: SAP | H36: √ | I36: √ | K36: 48.586123 | L36: 53.472329 | M36: 16.138436 | N36: 7.6396363
B37: 中南区 | C37: 湖北 | D37: 1521 | E37: 正大食品（宜昌）有限公司 | F37: OEM | G37: SAP总账 | H37: √ | K37: 50 | L37: 0 | M37: 8 | N37: 1
B38: 中南区 | C38: 江西 | D38: 1850 | E38: 江西正大畜禽有限公司高安分公司 | F38: OEM | G38: SS | H38: √ | I38: √ | K38: 71.948384 | M38: 7.5434944 | N38: 0
B39: 中南区 | C39: 湛江 | D39: 1810 | E39: 正大食品（广东）有限公司 | F39: OEM | G39: SS | H39: √ | I39: √ | K39: 92.981952 | L39: 0 | M39: 7 | N39: 0

Sheet 根据产能每天需要鲜销部分
C1: 毛猪均重 | D1: 120
B3: 公司代码 | C3: 公司名称 | D3: 每日屠宰头数 | E3: 每日分割头数 | F3: 每日入冻能力-kg | G3: 部位 | H3: 部位出品率 | J3: 产量 | K3: 鲜销 | L3: 储备
A4: 湖北襄阳 | B4: 0567 | C4: 正大食品（襄阳）有限公司 | D4: =_xlfn.XLOOKUP(B4,'3.屠宰能力表'!B:B,'3.屠宰能力表'!E:E) -> 3200 | E4: =_xlfn.XLOOKUP(B4,'4.分割能力表'!B:B,'4.分割能力表'!D:D) -> 1600 | F4: =_xlfn.XLOOKUP(B4,'4.分割能力表'!B:B,'4.分割能力表'!E:E) -> 72000 | G4: 白条 | H4: =_xlfn.XLOOKUP(G4,系数辅助表!$C:$C,系数辅助表!$D:$D) -> 0.715 | J4: =(D4-E4)*H4*$D$1 -> 137280 | K4: =IF(J4-L4<0,0,J4-L4) -> 137280
A5: 湖北襄阳 | B5: 0567 | C5: 正大食品（襄阳）有限公司 | D5: =_xlfn.XLOOKUP(B5,'3.屠宰能力表'!B:B,'3.屠宰能力表'!E:E) -> 3200 | E5: =_xlfn.XLOOKUP(B5,'4.分割能力表'!B:B,'4.分割能力表'!D:D) -> 1600 | F5: =_xlfn.XLOOKUP(B5,'4.分割能力表'!B:B,'4.分割能力表'!E:E) -> 72000 | G5: 猪头 | H5: =_xlfn.XLOOKUP(G5,系数辅助表!$C:$C,系数辅助表!$D:$D) -> 0.043342238 | J5: =$D5*H5*$D$1 -> 16643.419 | K5: =IF(J5-L5<0,0,J5-L5) -> 16643.419
A6: 湖北襄阳 | B6: 0567 | C6: 正大食品（襄阳）有限公司 | D6: =_xlfn.XLOOKUP(B6,'3.屠宰能力表'!B:B,'3.屠宰能力表'!E:E) -> 3200 | E6: =_xlfn.XLOOKUP(B6,'4.分割能力表'!B:B,'4.分割能力表'!D:D) -> 1600 | F6: =_xlfn.XLOOKUP(B6,'4.分割能力表'!B:B,'4.分割能力表'!E:E) -> 72000 | G6: 猪尾 | H6: =_xlfn.XLOOKUP(G6,系数辅助表!$C:$C,系数辅助表!$D:$D) -> 0.00032562132 | J6: =$D6*H6*$D$1 -> 125.03859 | K6: =IF(J6-L6<0,0,J6-L6) -> 125.03859
A7: 湖北襄阳 | B7: 0567 | C7: 正大食品（襄阳）有限公司 | D7: =_xlfn.XLOOKUP(B7,'3.屠宰能力表'!B:B,'3.屠宰能力表'!E:E) -> 3200 | E7: =_xlfn.XLOOKUP(B7,'4.分割能力表'!B:B,'4.分割能力表'!D:D) -> 1600 | F7: =_xlfn.XLOOKUP(B7,'4.分割能力表'!B:B,'4.分割能力表'!E:E) -> 72000 | G7: 猪心 | H7: =_xlfn.XLOOKUP(G7,系数辅助表!$C:$C,系数辅助表!$D:$D) -> 0.0030632399 | J7: =$D7*H7*$D$1 -> 1176.2841 | K7: =IF(J7-L7<0,0,J7-L7) -> 1176.2841
A8: 湖北襄阳 | B8: 0567 | C8: 正大食品（襄阳）有限公司 | D8: =_xlfn.XLOOKUP(B8,'3.屠宰能力表'!B:B,'3.屠宰能力表'!E:E) -> 3200 | E8: =_xlfn.XLOOKUP(B8,'4.分割能力表'!B:B,'4.分割能力表'!D:D) -> 1600 | F8: =_xlfn.XLOOKUP(B8,'4.分割能力表'!B:B,'4.分割能力表'!E:E) -> 72000 | G8: 猪肝 | H8: =_xlfn.XLOOKUP(G8,系数辅助表!$C:$C,系数辅助表!$D:$D) -> 0.015822797 | J8: =$D8*H8*$D$1 -> 6075.9539 | K8: =IF(J8-L8<0,0,J8-L8) -> 6075.9539
A9: 湖北襄阳 | B9: 0567 | C9: 正大食品（襄阳）有限公司 | D9: =_xlfn.XLOOKUP(B9,'3.屠宰能力表'!B:B,'3.屠宰能力表'!E:E) -> 3200 | E9: =_xlfn.XLOOKUP(B9,'4.分割能力表'!B:B,'4.分割能力表'!D:D) -> 1600 | F9: =_xlfn.XLOOKUP(B9,'4.分割能力表'!B:B,'4.分割能力表'!E:E) -> 72000 | G9: 猪腰 | H9: =_xlfn.XLOOKUP(G9,系数辅助表!$C:$C,系数辅助表!$D:$D) -> 0.0030934025 | J9: =$D9*H9*$D$1 -> 1187.8666 | K9: =IF(J9-L9<0,0,J9-L9) -> 1187.8666
A10: 湖北襄阳 | B10: 0567 | C10: 正大食品（襄阳）有限公司 | D10: =_xlfn.XLOOKUP(B10,'3.屠宰能力表'!B:B,'3.屠宰能力表'!E:E) -> 3200 | E10: =_xlfn.XLOOKUP(B10,'4.分割能力表'!B:B,'4.分割能力表'!D:D) -> 1600 | F10: =_xlfn.XLOOKUP(B10,'4.分割能力表'!B:B,'4.分割能力表'!E:E) -> 72000 | G10: 大肠 | H10: =_xlfn.XLOOKUP(G10,系数辅助表!$C:$C,系数辅助表!$D:$D) -> 0.010824799 | J10: =$D10*H10*$D$1 -> 4156.7228 | K10: =IF(J10-L10<0,0,J10-L10) -> 4156.7228
A11: 湖北襄阳 | B11: 0567 | C11: 正大食品（襄阳）有限公司 | D11: =_xlfn.XLOOKUP(B11,'3.屠宰能力表'!B:B,'3.屠宰能力表'!E:E) -> 3200 | E11: =_xlfn.XLOOKUP(B11,'4.分割能力表'!B:B,'4.分割能力表'!D:D) -> 1600 | F11: =_xlfn.XLOOKUP(B11,'4.分割能力表'!B:B,'4.分割能力表'!E:E) -> 72000 | G11: 猪肚 | H11: =_xlfn.XLOOKUP(G11,系数辅助表!$C:$C,系数辅助表!$D:$D) -> 0.0049657251 | J11: =$D11*H11*$D$1 -> 1906.8385 | K11: =IF(J11-L11<0,0,J11-L11) -> 1906.8385
A12: 湖北襄阳 | B12: 0567 | C12: 正大食品（襄阳）有限公司 | D12: =_xlfn.XLOOKUP(B12,'3.屠宰能力表'!B:B,'3.屠宰能力表'!E:E) -> 3200 | E12: =_xlfn.XLOOKUP(B12,'4.分割能力表'!B:B,'4.分割能力表'!D:D) -> 1600 | F12: =_xlfn.XLOOKUP(B12,'4.分割能力表'!B:B,'4.分割能力表'!E:E) -> 72000 | G12: 罗膈肉 | H12: =_xlfn.XLOOKUP(G12,系数辅助表!$C:$C,系数辅助表!$D:$D) -> 0.0041516718 | J12: =$D12*H12*$D$1 -> 1594.242 | K12: =IF(J12-L12<0,0,J12-L12) -> 1594.242
A13: 湖北襄阳 | B13: 0567 | C13: 正大食品（襄阳）有限公司 | D13: =_xlfn.XLOOKUP(B13,'3.屠宰能力表'!B:B,'3.屠宰能力表'!E:E) -> 3200 | E13: =_xlfn.XLOOKUP(B13,'4.分割能力表'!B:B,'4.分割能力表'!D:D) -> 1600 | F13: =_xlfn.XLOOKUP(B13,'4.分割能力表'!B:B,'4.分割能力表'!E:E) -> 72000 | G13: 猪舌 | H13: =_xlfn.XLOOKUP(G13,系数辅助表!$C:$C,系数辅助表!$D:$D) -> 0.0036632399 | J13: =$D13*H13*$D$1 -> 1406.6841 | K13: =IF(J13-L13<0,0,J13-L13) -> 1406.6841
A14: 湖北襄阳 | B14: 0567 | C14: 正大食品（襄阳）有限公司 | D14: =_xlfn.XLOOKUP(B14,'3.屠宰能力表'!B:B,'3.屠宰能力表'!E:E) -> 3200 | E14: =_xlfn.XLOOKUP(B14,'4.分割能力表'!B:B,'4.分割能力表'!D:D) -> 1600 | F14: =_xlfn.XLOOKUP(B14,'4.分割能力表'!B:B,'4.分割能力表'!E:E) -> 72000 | G14: 大肠头 | H14: =_xlfn.XLOOKUP(G14,系数辅助表!$C:$C,系数辅助表!$D:$D) -> 0.0026863759 | J14: =$D14*H14*$D$1 -> 1031.5683 | K14: =IF(J14-L14<0,0,J14-L14) -> 1031.5683
A15: 湖北襄阳 | B15: 0567 | C15: 正大食品（襄阳）有限公司 | D15: =_xlfn.XLOOKUP(B15,'3.屠宰能力表'!B:B,'3.屠宰能力表'!E:E) -> 3200 | E15: =_xlfn.XLOOKUP(B15,'4.分割能力表'!B:B,'4.分割能力表'!D:D) -> 1600 | F15: =_xlfn.XLOOKUP(B15,'4.分割能力表'!B:B,'4.分割能力表'!E:E) -> 72000 | G15: 心血管 | H15: =_xlfn.XLOOKUP(G15,系数辅助表!$C:$C,系数辅助表!$D:$D) -> 0.00029015761 | J15: =$D15*H15*$D$1 -> 111.42052 | K15: =IF(J15-L15<0,0,J15-L15) -> 111.42052
A16: 湖北襄阳 | B16: 0567 | C16: 正大食品（襄阳）有限公司 | D16: =_xlfn.XLOOKUP(B16,'3.屠宰能力表'!B:B,'3.屠宰能力表'!E:E) -> 3200 | E16: =_xlfn.XLOOKUP(B16,'4.分割能力表'!B:B,'4.分割能力表'!D:D) -> 1600 | F16: =_xlfn.XLOOKUP(B16,'4.分割能力表'!B:B,'4.分割能力表'!E:E) -> 72000 | G16: 杂油 | H16: =_xlfn.XLOOKUP(G16,系数辅助表!$C:$C,系数辅助表!$D:$D) -> 0.010245933 | J16: =$D16*H16*$D$1 -> 3934.4382 | K16: =IF(J16-L16<0,0,J16-L16) -> 3934.4382
... A26: 湖北襄阳 | B26: 0567 | C26: 正大食品（襄阳）有限公司 | D26: =_xlfn.XLOOKUP(B26,'3.屠宰能力表'!B:B,'3.屠宰能力表'!E:E) -> 3200 | E26: =_xlfn.XLOOKUP(B26,'4.分割能力表'!B:B,'4.分割能力表'!D:D) -> 1600 | F26: =_xlfn.XLOOKUP(B26,'4.分割能力表'!B:B,'4.分割能力表'!E:E) -> 72000 | G26: 猪血 | H26: =_xlfn.XLOOKUP(G26,系数辅助表!$C:$C,系数辅助表!$D:$D) -> 0.02 | J26: =$D26*H26*$D$1 -> 7680 | K26: =IF(J26-L26<0,0,J26-L26) -> 7680
A27: 湖北襄阳 | B27: 0567 | C27: 正大食品（襄阳）有限公司 | D27: =_xlfn.XLOOKUP(B27,'3.屠宰能力表'!B:B,'3.屠宰能力表'!E:E) -> 3200 | E27: =_xlfn.XLOOKUP(B27,'4.分割能力表'!B:B,'4.分割能力表'!D:D) -> 1600 | F27: =_xlfn.XLOOKUP(B27,'4.分割能力表'!B:B,'4.分割能力表'!E:E) -> 72000 | G27: 槽头 | H27: =_xlfn.XLOOKUP(G27,系数辅助表!$C:$C,系数辅助表!$D:$D) -> 0.018500772 | J27: =$E27*H27*$D$1 -> 3552.1482 | K27: =IF(J27-L27<0,0,J27-L27) -> 1449.3336 | L27: 2102.8146
A28: 湖北襄阳 | B28: 0567 | C28: 正大食品（襄阳）有限公司 | D28: =_xlfn.XLOOKUP(B28,'3.屠宰能力表'!B:B,'3.屠宰能力表'!E:E) -> 3200 | E28: =_xlfn.XLOOKUP(B28,'4.分割能力表'!B:B,'4.分割能力表'!D:D) -> 1600 | F28: =_xlfn.XLOOKUP(B28,'4.分割能力表'!B:B,'4.分割能力表'!E:E) -> 72000 | G28: 猪蹄 | H28: =_xlfn.XLOOKUP(G28,系数辅助表!$C:$C,系数辅助表!$D:$D) -> 0.018327695 | J28: =$E28*H28*$D$1 -> 3518.9174 | K28: =IF(J28-L28<0,0,J28-L28) -> 1435.7749 | L28: 2083.1425
A29: 湖北襄阳 | B29: 0567 | C29: 正大食品（襄阳）有限公司 | D29: =_xlfn.XLOOKUP(B29,'3.屠宰能力表'!B:B,'3.屠宰能力表'!E:E) -> 3200 | E29: =_xlfn.XLOOKUP(B29,'4.分割能力表'!B:B,'4.分割能力表'!D:D) -> 1600 | F29: =_xlfn.XLOOKUP(B29,'4.分割能力表'!B:B,'4.分割能力表'!E:E) -> 72000 | G29: 五花肉 | H29: =_xlfn.XLOOKUP(G29,系数辅助表!$C:$C,系数辅助表!$D:$D) -> 0.097050752 | J29: =$E29*H29*$D$1 -> 18633.744 | K29: =IF(J29-L29<0,0,J29-L29) -> 9257.4989 | L29: 9376.2454
A30: 湖北襄阳 | B30: 0567 | C30: 正大食品（襄阳）有限公司 | D30: =_xlfn.XLOOKUP(B30,'3.屠宰能力表'!B:B,'3.屠宰能力表'!E:E) -> 3200 | E30: =_xlfn.XLOOKUP(B30,'4.分割能力表'!B:B,'4.分割能力表'!D:D) -> 1600 | F30: =_xlfn.XLOOKUP(B30,'4.分割能力表'!B:B,'4.分割能力表'!E:E) -> 72000 | G30: 大排肌肉 | H30: =_xlfn.XLOOKUP(G30,系数辅助表!$C:$C,系数辅助表!$D:$D) -> 0.046512517 | J30: =$E30*H30*$D$1 -> 8930.4033 | K30: =IF(J30-L30<0,0,J30-L30) -> 7275.7718 | L30: 1654.6315
A31: 湖北襄阳 | B31: 0567 | C31: 正大食品（襄阳）有限公司 | D31: =_xlfn.XLOOKUP(B31,'3.屠宰能力表'!B:B,'3.屠宰能力表'!E:E) -> 3200 | E31: =_xlfn.XLOOKUP(B31,'4.分割能力表'!B:B,'4.分割能力表'!D:D) -> 1600 | F31: =_xlfn.XLOOKUP(B31,'4.分割能力表'!B:B,'4.分割能力表'!E:E) -> 72000 | G31: 肋排 | H31: =_xlfn.XLOOKUP(G31,系数辅助表!$C:$C,系数辅助表!$D:$D) -> 0.028731738 | J31: =$E31*H31*$D$1 -> 5516.4936 | K31: =IF(J31-L31<0,0,J31-L31) -> 2250.8181 | L31: 3265.6755
A32: 湖北襄阳 | B32: 0567 | C32: 正大食品（襄阳）有限公司 | D32: =_xlfn.XLOOKUP(B32,'3.屠宰能力表'!B:B,'3.屠宰能力表'!E:E) -> 3200 | E32: =_xlfn.XLOOKUP(B32,'4.分割能力表'!B:B,'4.分割能力表'!D:D) -> 1600 | F32: =_xlfn.XLOOKUP(B32,'4.分割能力表'!B:B,'4.分割能力表'!E:E) -> 72000 | G32: 前排 | H32: =_xlfn.XLOOKUP(G32,系数辅助表!$C:$C,系数辅助表!$D:$D) -> 0.029020999 | J32: =$E32*H32*$D$1 -> 5572.0318 | K32: =IF(J32-L32<0,0,J32-L32) -> 5572.0318 | L32: 0
A33: 湖北襄阳 | B33: 0567 | C33: 正大食品（襄阳）有限公司 | D33: =_xlfn.XLOOKUP(B33,'3.屠宰能力表'!B:B,'3.屠宰能力表'!E:E) -> 3200 | E33: =_xlfn.XLOOKUP(B33,'4.分割能力表'!B:B,'4.分割能力表'!D:D) -> 1600 | F33: =_xlfn.XLOOKUP(B33,'4.分割能力表'!B:B,'4.分割能力表'!E:E) -> 72000 | G33: 颈背肌肉 | H33: =_xlfn.XLOOKUP(G33,系数辅助表!$C:$C,系数辅助表!$D:$D) -> 0.033890751 | J33: =$E33*H33*$D$1 -> 6507.0242 | K33: =IF(J33-L33<0,0,J33-L33) -> 1156.5827 | L33: 5350.4416
A34: 湖北襄阳 | B34: 0567 | C34: 正大食品（襄阳）有限公司 | D34: =_xlfn.XLOOKUP(B34,'3.屠宰能力表'!B:B,'3.屠宰能力表'!E:E) -> 3200 | E34: =_xlfn.XLOOKUP(B34,'4.分割能力表'!B:B,'4.分割能力表'!D:D) -> 1600 | F34: =_xlfn.XLOOKUP(B34,'4.分割能力表'!B:B,'4.分割能力表'!E:E) -> 72000 | G34: 小里脊 | H34: =_xlfn.XLOOKUP(G34,系数辅助表!$C:$C,系数辅助表!$D:$D) -> 0.0066683831 | J34: =$E34*H34*$D$1 -> 1280.3296 | K34: =J34-L34 -> 0 | L34: =J34 -> 1280.3296
A35: 湖北襄阳 | B35: 0567 | C35: 正大食品（襄阳）有限公司 | D35: =_xlfn.XLOOKUP(B35,'3.屠宰能力表'!B:B,'3.屠宰能力表'!E:E) -> 3200 | E35: =_xlfn.XLOOKUP(B35,'4.分割能力表'!B:B,'4.分割能力表'!D:D) -> 1600 | F35: =_xlfn.XLOOKUP(B35,'4.分割能力表'!B:B,'4.分割能力表'!E:E) -> 72000 | G35: 前腿肌肉 | H35: =_xlfn.XLOOKUP(G35,系数辅助表!$C:$C,系数辅助表!$D:$D) -> 0.073037535 | J35: =$E35*H35*$D$1 -> 14023.207 | K35: =IF(J35-L35<0,0,J35-L35) -> 1559.9408 | L35: 12463.266
A36: 湖北襄阳 | B36: 0567 | C36: 正大食品（襄阳）有限公司 | D36: =_xlfn.XLOOKUP(B36,'3.屠宰能力表'!B:B,'3.屠宰能力表'!E:E) -> 3200 | E36: =_xlfn.XLOOKUP(B36,'4.分割能力表'!B:B,'4.分割能力表'!D:D) -> 1600 | F36: =_xlfn.XLOOKUP(B36,'4.分割能力表'!B:B,'4.分割能力表'!E:E) -> 72000 | G36: 后腿肌肉 | H36: =_xlfn.XLOOKUP(G36,系数辅助表!$C:$C,系数辅助表!$D:$D) -> 0.12205173 | J36: =$E36*H36*$D$1 -> 23433.931 | K36: =IF(J36-L36<0,0,J36-L36) -> 13723.174 | L36: 9710.7573
A37: 湖北襄阳 | B37: 0567 | C37: 正大食品（襄阳）有限公司 | D37: =_xlfn.XLOOKUP(B37,'3.屠宰能力表'!B:B,'3.屠宰能力表'!E:E) -> 3200 | E37: =_xlfn.XLOOKUP(B37,'4.分割能力表'!B:B,'4.分割能力表'!D:D) -> 1600 | F37: =_xlfn.XLOOKUP(B37,'4.分割能力表'!B:B,'4.分割能力表'!E:E) -> 72000 | G37: 前肘 | H37: =_xlfn.XLOOKUP(G37,系数辅助表!$C:$C,系数辅助表!$D:$D) -> 0.019521507 | J37: =$E37*H37*$D$1 -> 3748.1294 | K37: =IF(J37-L37<0,0,J37-L37) -> 1529.2971 | L37: 2218.8323
A38: 湖北襄阳 | B38: 0567 | C38: 正大食品（襄阳）有限公司 | D38: =_xlfn.XLOOKUP(B38,'3.屠宰能力表'!B:B,'3.屠宰能力表'!E:E) -> 3200 | E38: =_xlfn.XLOOKUP(B38,'4.分割能力表'!B:B,'4.分割能力表'!D:D) -> 1600 | F38: =_xlfn.XLOOKUP(B38,'4.分割能力表'!B:B,'4.分割能力表'!E:E) -> 72000 | G38: 后肘 | H38: =_xlfn.XLOOKUP(G38,系数辅助表!$C:$C,系数辅助表!$D:$D) -> 0.02755221 | J38: =$E38*H38*$D$1 -> 5290.0242 | K38: =IF(J38-L38<0,0,J38-L38) -> 2158.415 | L38: 3131.6093
A39: 湖北襄阳 | B39: 0567 | C39: 正大食品（襄阳）有限公司 | D39: =_xlfn.XLOOKUP(B39,'3.屠宰能力表'!B:B,'3.屠宰能力表'!E:E) -> 3200 | E39: =_xlfn.XLOOKUP(B39,'4.分割能力表'!B:B,'4.分割能力表'!D:D) -> 1600 | F39: =_xlfn.XLOOKUP(B39,'4.分割能力表'!B:B,'4.分割能力表'!E:E) -> 72000 | G39: 肥膘 | H39: =_xlfn.XLOOKUP(G39,系数辅助表!$C:$C,系数辅助表!$D:$D) -> 0.061357303 | J39: =$E39*H39*$D$1 -> 11780.602 | K39: =IF(J39-L39<0,0,J39-L39) -> 4806.6752 | L39: 6973.927
A40: 湖北襄阳 | B40: 0567 | C40: 正大食品（襄阳）有限公司 | D40: =_xlfn.XLOOKUP(B40,'3.屠宰能力表'!B:B,'3.屠宰能力表'!E:E) -> 3200 | E40: =_xlfn.XLOOKUP(B40,'4.分割能力表'!B:B,'4.分割能力表'!D:D) -> 1600 | F40: =_xlfn.XLOOKUP(B40,'4.分割能力表'!B:B,'4.分割能力表'!E:E) -> 72000 | G40: 脊膘 | H40: =_xlfn.XLOOKUP(G40,系数辅助表!$C:$C,系数辅助表!$D:$D) -> 0.013016588 | J40: =$E40*H40*$D$1 -> 2499.185 | K40: =IF(J40-L40<0,0,J40-L40) -> 2499.185 | L40: 0
A41: 湖北襄阳 | B41: 0567 | C41: 正大食品（襄阳）有限公司 | D41: =_xlfn.XLOOKUP(B41,'3.屠宰能力表'!B:B,'3.屠宰能力表'!E:E) -> 3200 | E41: =_xlfn.XLOOKUP(B41,'4.分割能力表'!B:B,'4.分割能力表'!D:D) -> 1600 | F41: =_xlfn.XLOOKUP(B41,'4.分割能力表'!B:B,'4.分割能力表'!E:E) -> 72000 | G41: 脊骨 | H41: =_xlfn.XLOOKUP(G41,系数辅助表!$C:$C,系数辅助表!$D:$D) -> 0.029868561 | J41: =$E41*H41*$D$1 -> 5734.7637 | K41: =IF(J41-L41<0,0,J41-L41) -> 5734.7637 | L41: 0
A42: 湖北襄阳 | B42: 0567 | C42: 正大食品（襄阳）有限公司 | D42: =_xlfn.XLOOKUP(B42,'3.屠宰能力表'!B:B,'3.屠宰能力表'!E:E) -> 3200 | E42: =_xlfn.XLOOKUP(B42,'4.分割能力表'!B:B,'4.分割能力表'!D:D) -> 1600 | F42: =_xlfn.XLOOKUP(B42,'4.分割能力表'!B:B,'4.分割能力表'!E:E) -> 72000 | G42: 带肉后棒骨 | H42: =_xlfn.XLOOKUP(G42,系数辅助表!$C:$C,系数辅助表!$D:$D) -> 0.013175327 | J42: =$E42*H42*$D$1 -> 2529.6628 | K42: =IF(J42-L42<0,0,J42-L42) -> 1032.1431 | L42: 1497.5197
A43: 湖北襄阳 | B43: 0567 | C43: 正大食品（襄阳）有限公司 | D43: =_xlfn.XLOOKUP(B43,'3.屠宰能力表'!B:B,'3.屠宰能力表'!E:E) -> 3200 | E43: =_xlfn.XLOOKUP(B43,'4.分割能力表'!B:B,'4.分割能力表'!D:D) -> 1600 | F43: =_xlfn.XLOOKUP(B43,'4.分割能力表'!B:B,'4.分割能力表'!E:E) -> 72000 | G43: 带肉前棒骨 | H43: =_xlfn.XLOOKUP(G43,系数辅助表!$C:$C,系数辅助表!$D:$D) -> 0.0072226191 | J43: =$E43*H43*$D$1 -> 1386.7429 | K43: =IF(J43-L43<0,0,J43-L43) -> 1386.7429 | L43: 0
A44: 湖北襄阳 | B44: 0567 | C44: 正大食品（襄阳）有限公司 | D44: =_xlfn.XLOOKUP(B44,'3.屠宰能力表'!B:B,'3.屠宰能力表'!E:E) -> 3200 | E44: =_xlfn.XLOOKUP(B44,'4.分割能力表'!B:B,'4.分割能力表'!D:D) -> 1600 | F44: =_xlfn.XLOOKUP(B44,'4.分割能力表'!B:B,'4.分割能力表'!E:E) -> 72000 | G44: 尾叉骨 | H44: =_xlfn.XLOOKUP(G44,系数辅助表!$C:$C,系数辅助表!$D:$D) -> 0.023493354 | J44: =$E44*H44*$D$1 -> 4510.7241 | K44: =IF(J44-L44<0,0,J44-L44) -> 4510.7241 | L44: 0
A45: 湖北襄阳 | B45: 0567 | C45: 正大食品（襄阳）有限公司 | D45: =_xlfn.XLOOKUP(B45,'3.屠宰能力表'!B:B,'3.屠宰能力表'!E:E) -> 3200 | E45: =_xlfn.XLOOKUP(B45,'4.分割能力表'!B:B,'4.分割能力表'!D:D) -> 1600 | F45: =_xlfn.XLOOKUP(B45,'4.分割能力表'!B:B,'4.分割能力表'!E:E) -> 72000 | G45: 扇骨 | H45: =_xlfn.XLOOKUP(G45,系数辅助表!$C:$C,系数辅助表!$D:$D) -> 0.0098418107 | J45: =$E45*H45*$D$1 -> 1889.6276 | K45: =IF(J45-L45<0,0,J45-L45) -> 1889.6276 | L45: 0
A46: 湖北襄阳 | B46: 0567 | C46: 正大食品（襄阳）有限公司 | D46: =_xlfn.XLOOKUP(B46,'3.屠宰能力表'!B:B,'3.屠宰能力表'!E:E) -> 3200 | E46: =_xlfn.XLOOKUP(B46,'4.分割能力表'!B:B,'4.分割能力表'!D:D) -> 1600 | F46: =_xlfn.XLOOKUP(B46,'4.分割能力表'!B:B,'4.分割能力表'!E:E) -> 72000 | G46: 颈骨 | H46: =_xlfn.XLOOKUP(G46,系数辅助表!$C:$C,系数辅助表!$D:$D) -> 0.0069845108 | J46: =$E46*H46*$D$1 -> 1341.0261 | K46: =IF(J46-L46<0,0,J46-L46) -> 1341.0261 | L46: 0
... A52: 湖北襄阳 | B52: 0567 | C52: 正大食品（襄阳）有限公司 | D52: =_xlfn.XLOOKUP(B52,'3.屠宰能力表'!B:B,'3.屠宰能力表'!E:E) -> 3200 | E52: =_xlfn.XLOOKUP(B52,'4.分割能力表'!B:B,'4.分割能力表'!D:D) -> 1600 | F52: =_xlfn.XLOOKUP(B52,'4.分割能力表'!B:B,'4.分割能力表'!E:E) -> 72000 | G52: 碎皮 | H52: =_xlfn.XLOOKUP(G52,系数辅助表!$C:$C,系数辅助表!$D:$D) -> 0.0014286499 | J52: =$E52*H52*$D$1 -> 274.30079 | K52: =IF(J52-L52<0,0,J52-L52) -> 274.30079 | L52: 0
A53: 湖北襄阳 | B53: 0567 | C53: 正大食品（襄阳）有限公司 | D53: =_xlfn.XLOOKUP(B53,'3.屠宰能力表'!B:B,'3.屠宰能力表'!E:E) -> 3200 | E53: =_xlfn.XLOOKUP(B53,'4.分割能力表'!B:B,'4.分割能力表'!D:D) -> 1600 | F53: =_xlfn.XLOOKUP(B53,'4.分割能力表'!B:B,'4.分割能力表'!E:E) -> 72000 | G53: 五花肉-冷冻 | J53: =IFERROR(INDEX($L:$L,MATCH(SUBSTITUTE(G53,"-冷冻",""),$G:$G,0)),"") -> 9376.2454
A54: 湖北襄阳 | B54: 0567 | C54: 正大食品（襄阳）有限公司 | D54: =_xlfn.XLOOKUP(B54,'3.屠宰能力表'!B:B,'3.屠宰能力表'!E:E) -> 3200 | E54: =_xlfn.XLOOKUP(B54,'4.分割能力表'!B:B,'4.分割能力表'!D:D) -> 1600 | F54: =_xlfn.XLOOKUP(B54,'4.分割能力表'!B:B,'4.分割能力表'!E:E) -> 72000 | G54: 大排肌肉-冷冻 | J54: =IFERROR(INDEX($L:$L,MATCH(SUBSTITUTE(G54,"-冷冻",""),$G:$G,0)),"") -> 1654.6315
A55: 湖北襄阳 | B55: 0567 | C55: 正大食品（襄阳）有限公司 | D55: =_xlfn.XLOOKUP(B55,'3.屠宰能力表'!B:B,'3.屠宰能力表'!E:E) -> 3200 | E55: =_xlfn.XLOOKUP(B55,'4.分割能力表'!B:B,'4.分割能力表'!D:D) -> 1600 | F55: =_xlfn.XLOOKUP(B55,'4.分割能力表'!B:B,'4.分割能力表'!E:E) -> 72000 | G55: 肋排-冷冻 | J55: =IFERROR(INDEX($L:$L,MATCH(SUBSTITUTE(G55,"-冷冻",""),$G:$G,0)),"") -> 3265.6755
A56: 湖北襄阳 | B56: 0567 | C56: 正大食品（襄阳）有限公司 | D56: =_xlfn.XLOOKUP(B56,'3.屠宰能力表'!B:B,'3.屠宰能力表'!E:E) -> 3200 | E56: =_xlfn.XLOOKUP(B56,'4.分割能力表'!B:B,'4.分割能力表'!D:D) -> 1600 | F56: =_xlfn.XLOOKUP(B56,'4.分割能力表'!B:B,'4.分割能力表'!E:E) -> 72000 | G56: 颈背肌肉-冷冻 | J56: =IFERROR(INDEX($L:$L,MATCH(SUBSTITUTE(G56,"-冷冻",""),$G:$G,0)),"") -> 5350.4416
A57: 湖北襄阳 | B57: 0567 | C57: 正大食品（襄阳）有限公司 | D57: =_xlfn.XLOOKUP(B57,'3.屠宰能力表'!B:B,'3.屠宰能力表'!E:E) -> 3200 | E57: =_xlfn.XLOOKUP(B57,'4.分割能力表'!B:B,'4.分割能力表'!D:D) -> 1600 | F57: =_xlfn.XLOOKUP(B57,'4.分割能力表'!B:B,'4.分割能力表'!E:E) -> 72000 | G57: 小里脊-冷冻 | J57: =IFERROR(INDEX($L:$L,MATCH(SUBSTITUTE(G57,"-冷冻",""),$G:$G,0)),"") -> 1280.3296
A58: 湖北襄阳 | B58: 0567 | C58: 正大食品（襄阳）有限公司 | D58: =_xlfn.XLOOKUP(B58,'3.屠宰能力表'!B:B,'3.屠宰能力表'!E:E) -> 3200 | E58: =_xlfn.XLOOKUP(B58,'4.分割能力表'!B:B,'4.分割能力表'!D:D) -> 1600 | F58: =_xlfn.XLOOKUP(B58,'4.分割能力表'!B:B,'4.分割能力表'!E:E) -> 72000 | G58: 前腿肌肉-冷冻 | J58: =IFERROR(INDEX($L:$L,MATCH(SUBSTITUTE(G58,"-冷冻",""),$G:$G,0)),"") -> 12463.266
A59: 湖北襄阳 | B59: 0567 | C59: 正大食品（襄阳）有限公司 | D59: =_xlfn.XLOOKUP(B59,'3.屠宰能力表'!B:B,'3.屠宰能力表'!E:E) -> 3200 | E59: =_xlfn.XLOOKUP(B59,'4.分割能力表'!B:B,'4.分割能力表'!D:D) -> 1600 | F59: =_xlfn.XLOOKUP(B59,'4.分割能力表'!B:B,'4.分割能力表'!E:E) -> 72000 | G59: 后腿肌肉-冷冻 | J59: =IFERROR(INDEX($L:$L,MATCH(SUBSTITUTE(G59,"-冷冻",""),$G:$G,0)),"") -> 9710.7573
A60: 湖北襄阳 | B60: 0567 | C60: 正大食品（襄阳）有限公司 | D60: =_xlfn.XLOOKUP(B60,'3.屠宰能力表'!B:B,'3.屠宰能力表'!E:E) -> 3200 | E60: =_xlfn.XLOOKUP(B60,'4.分割能力表'!B:B,'4.分割能力表'!D:D) -> 1600 | F60: =_xlfn.XLOOKUP(B60,'4.分割能力表'!B:B,'4.分割能力表'!E:E) -> 72000 | G60: 前肘-冷冻 | J60: =IFERROR(INDEX($L:$L,MATCH(SUBSTITUTE(G60,"-冷冻",""),$G:$G,0)),"") -> 2218.8323
A61: 湖北襄阳 | B61: 0567 | C61: 正大食品（襄阳）有限公司 | D61: =_xlfn.XLOOKUP(B61,'3.屠宰能力表'!B:B,'3.屠宰能力表'!E:E) -> 3200 | E61: =_xlfn.XLOOKUP(B61,'4.分割能力表'!B:B,'4.分割能力表'!D:D) -> 1600 | F61: =_xlfn.XLOOKUP(B61,'4.分割能力表'!B:B,'4.分割能力表'!E:E) -> 72000 | G61: 后肘-冷冻 | J61: =IFERROR(INDEX($L:$L,MATCH(SUBSTITUTE(G61,"-冷冻",""),$G:$G,0)),"") -> 3131.6093
A62: 湖北襄阳 | B62: 0567 | C62: 正大食品（襄阳）有限公司 | D62: =_xlfn.XLOOKUP(B62,'3.屠宰能力表'!B:B,'3.屠宰能力表'!E:E) -> 3200 | E62: =_xlfn.XLOOKUP(B62,'4.分割能力表'!B:B,'4.分割能力表'!D:D) -> 1600 | F62: =_xlfn.XLOOKUP(B62,'4.分割能力表'!B:B,'4.分割能力表'!E:E) -> 72000 | G62: 肥膘-冷冻 | J62: =IFERROR(INDEX($L:$L,MATCH(SUBSTITUTE(G62,"-冷冻",""),$G:$G,0)),"") -> 6973.927
A63: 湖北襄阳 | B63: 0567 | C63: 正大食品（襄阳）有限公司 | D63: =_xlfn.XLOOKUP(B63,'3.屠宰能力表'!B:B,'3.屠宰能力表'!E:E) -> 3200 | E63: =_xlfn.XLOOKUP(B63,'4.分割能力表'!B:B,'4.分割能力表'!D:D) -> 1600 | F63: =_xlfn.XLOOKUP(B63,'4.分割能力表'!B:B,'4.分割能力表'!E:E) -> 72000 | G63: 带肉后棒骨-冷冻 | J63: =IFERROR(INDEX($L:$L,MATCH(SUBSTITUTE(G63,"-冷冻",""),$G:$G,0)),"") -> 1497.5197
A64: 湖北襄阳 | B64: 0567 | C64: 正大食品（襄阳）有限公司 | D64: =_xlfn.XLOOKUP(B64,'3.屠宰能力表'!B:B,'3.屠宰能力表'!E:E) -> 3200 | E64: =_xlfn.XLOOKUP(B64,'4.分割能力表'!B:B,'4.分割能力表'!D:D) -> 1600 | F64: =_xlfn.XLOOKUP(B64,'4.分割能力表'!B:B,'4.分割能力表'!E:E) -> 72000 | G64: 精碎肉-冷冻 | J64: =IFERROR(INDEX($L:$L,MATCH(SUBSTITUTE(G64,"-冷冻",""),$G:$G,0)),"") -> 1173.5236
... A68: 湖北襄阳 | B68: 0567 | C68: 正大食品（襄阳）有限公司 | D68: =_xlfn.XLOOKUP(B68,'3.屠宰能力表'!B:B,'3.屠宰能力表'!E:E) -> 3200 | E68: =_xlfn.XLOOKUP(B68,'4.分割能力表'!B:B,'4.分割能力表'!D:D) -> 1600 | F68: =_xlfn.XLOOKUP(B68,'4.分割能力表'!B:B,'4.分割能力表'!E:E) -> 72000 | G68: 槽头-冷冻 | J68: =IFERROR(INDEX($L:$L,MATCH(SUBSTITUTE(G68,"-冷冻",""),$G:$G,0)),"") -> 2102.8146
A69: 河南 | B69: 0555 | C69: 洛阳正大食品有限公司 | D69: =_xlfn.XLOOKUP(B69,'3.屠宰能力表'!B:B,'3.屠宰能力表'!E:E) -> 3200 | E69: =_xlfn.XLOOKUP(B69,'4.分割能力表'!B:B,'4.分割能力表'!D:D) -> 960 | F69: =_xlfn.XLOOKUP(B69,'4.分割能力表'!B:B,'4.分割能力表'!E:E) -> 60000 | G69: 白条 | H69: =_xlfn.XLOOKUP(G69,系数辅助表!$C:$C,系数辅助表!$D:$D) -> 0.715 | J69: =(D69-E69)*H69*$D$1 -> 192192 | K69: =J69-L69 -> 192192
A70: 河南 | B70: 0555 | C70: 洛阳正大食品有限公司 | D70: =_xlfn.XLOOKUP(B70,'3.屠宰能力表'!B:B,'3.屠宰能力表'!E:E) -> 3200 | E70: =_xlfn.XLOOKUP(B70,'4.分割能力表'!B:B,'4.分割能力表'!D:D) -> 960 | F70: =_xlfn.XLOOKUP(B70,'4.分割能力表'!B:B,'4.分割能力表'!E:E) -> 60000 | G70: 猪头 | H70: =_xlfn.XLOOKUP(G70,系数辅助表!$C:$C,系数辅助表!$D:$D) -> 0.043342238 | J70: =$D70*H70*$D$1 -> 16643.419 | K70: =J70-L70 -> 16643.419
A71: 河南 | B71: 0555 | C71: 洛阳正大食品有限公司 | D71: =_xlfn.XLOOKUP(B71,'3.屠宰能力表'!B:B,'3.屠宰能力表'!E:E) -> 3200 | E71: =_xlfn.XLOOKUP(B71,'4.分割能力表'!B:B,'4.分割能力表'!D:D) -> 960 | F71: =_xlfn.XLOOKUP(B71,'4.分割能力表'!B:B,'4.分割能力表'!E:E) -> 60000 | G71: 猪尾 | H71: =_xlfn.XLOOKUP(G71,系数辅助表!$C:$C,系数辅助表!$D:$D) -> 0.00032562132 | J71: =$D71*H71*$D$1 -> 125.03859 | K71: =J71-L71 -> 125.03859
A72: 河南 | B72: 0555 | C72: 洛阳正大食品有限公司 | D72: =_xlfn.XLOOKUP(B72,'3.屠宰能力表'!B:B,'3.屠宰能力表'!E:E) -> 3200 | E72: =_xlfn.XLOOKUP(B72,'4.分割能力表'!B:B,'4.分割能力表'!D:D) -> 960 | F72: =_xlfn.XLOOKUP(B72,'4.分割能力表'!B:B,'4.分割能力表'!E:E) -> 60000 | G72: 猪心 | H72: =_xlfn.XLOOKUP(G72,系数辅助表!$C:$C,系数辅助表!$D:$D) -> 0.0030632399 | J72: =$D72*H72*$D$1 -> 1176.2841 | K72: =J72-L72 -> 1176.2841
A73: 河南 | B73: 0555 | C73: 洛阳正大食品有限公司 | D73: =_xlfn.XLOOKUP(B73,'3.屠宰能力表'!B:B,'3.屠宰能力表'!E:E) -> 3200 | E73: =_xlfn.XLOOKUP(B73,'4.分割能力表'!B:B,'4.分割能力表'!D:D) -> 960 | F73: =_xlfn.XLOOKUP(B73,'4.分割能力表'!B:B,'4.分割能力表'!E:E) -> 60000 | G73: 猪肝 | H73: =_xlfn.XLOOKUP(G73,系数辅助表!$C:$C,系数辅助表!$D:$D) -> 0.015822797 | J73: =$D73*H73*$D$1 -> 6075.9539 | K73: =J73-L73 -> 6075.9539
A74: 河南 | B74: 0555 | C74: 洛阳正大食品有限公司 | D74: =_xlfn.XLOOKUP(B74,'3.屠宰能力表'!B:B,'3.屠宰能力表'!E:E) -> 3200 | E74: =_xlfn.XLOOKUP(B74,'4.分割能力表'!B:B,'4.分割能力表'!D:D) -> 960 | F74: =_xlfn.XLOOKUP(B74,'4.分割能力表'!B:B,'4.分割能力表'!E:E) -> 60000 | G74: 猪腰 | H74: =_xlfn.XLOOKUP(G74,系数辅助表!$C:$C,系数辅助表!$D:$D) -> 0.0030934025 | J74: =$D74*H74*$D$1 -> 1187.8666 | K74: =J74-L74 -> 1187.8666
A75: 河南 | B75: 0555 | C75: 洛阳正大食品有限公司 | D75: =_xlfn.XLOOKUP(B75,'3.屠宰能力表'!B:B,'3.屠宰能力表'!E:E) -> 3200 | E75: =_xlfn.XLOOKUP(B75,'4.分割能力表'!B:B,'4.分割能力表'!D:D) -> 960 | F75: =_xlfn.XLOOKUP(B75,'4.分割能力表'!B:B,'4.分割能力表'!E:E) -> 60000 | G75: 大肠 | H75: =_xlfn.XLOOKUP(G75,系数辅助表!$C:$C,系数辅助表!$D:$D) -> 0.010824799 | J75: =$D75*H75*$D$1 -> 4156.7228 | K75: =J75-L75 -> 4156.7228
A76: 河南 | B76: 0555 | C76: 洛阳正大食品有限公司 | D76: =_xlfn.XLOOKUP(B76,'3.屠宰能力表'!B:B,'3.屠宰能力表'!E:E) -> 3200 | E76: =_xlfn.XLOOKUP(B76,'4.分割能力表'!B:B,'4.分割能力表'!D:D) -> 960 | F76: =_xlfn.XLOOKUP(B76,'4.分割能力表'!B:B,'4.分割能力表'!E:E) -> 60000 | G76: 猪肚 | H76: =_xlfn.XLOOKUP(G76,系数辅助表!$C:$C,系数辅助表!$D:$D) -> 0.0049657251 | J76: =$D76*H76*$D$1 -> 1906.8385 | K76: =J76-L76 -> 1906.8385
A77: 河南 | B77: 0555 | C77: 洛阳正大食品有限公司 | D77: =_xlfn.XLOOKUP(B77,'3.屠宰能力表'!B:B,'3.屠宰能力表'!E:E) -> 3200 | E77: =_xlfn.XLOOKUP(B77,'4.分割能力表'!B:B,'4.分割能力表'!D:D) -> 960 | F77: =_xlfn.XLOOKUP(B77,'4.分割能力表'!B:B,'4.分割能力表'!E:E) -> 60000 | G77: 罗膈肉 | H77: =_xlfn.XLOOKUP(G77,系数辅助表!$C:$C,系数辅助表!$D:$D) -> 0.0041516718 | J77: =$D77*H77*$D$1 -> 1594.242 | K77: =J77-L77 -> 1594.242
A78: 河南 | B78: 0555 | C78: 洛阳正大食品有限公司 | D78: =_xlfn.XLOOKUP(B78,'3.屠宰能力表'!B:B,'3.屠宰能力表'!E:E) -> 3200 | E78: =_xlfn.XLOOKUP(B78,'4.分割能力表'!B:B,'4.分割能力表'!D:D) -> 960 | F78: =_xlfn.XLOOKUP(B78,'4.分割能力表'!B:B,'4.分割能力表'!E:E) -> 60000 | G78: 猪舌 | H78: =_xlfn.XLOOKUP(G78,系数辅助表!$C:$C,系数辅助表!$D:$D) -> 0.0036632399 | J78: =$D78*H78*$D$1 -> 1406.6841 | K78: =J78-L78 -> 1406.6841
A79: 河南 | B79: 0555 | C79: 洛阳正大食品有限公司 | D79: =_xlfn.XLOOKUP(B79,'3.屠宰能力表'!B:B,'3.屠宰能力表'!E:E) -> 3200 | E79: =_xlfn.XLOOKUP(B79,'4.分割能力表'!B:B,'4.分割能力表'!D:D) -> 960 | F79: =_xlfn.XLOOKUP(B79,'4.分割能力表'!B:B,'4.分割能力表'!E:E) -> 60000 | G79: 大肠头 | H79: =_xlfn.XLOOKUP(G79,系数辅助表!$C:$C,系数辅助表!$D:$D) -> 0.0026863759 | J79: =$D79*H79*$D$1 -> 1031.5683 | K79: =J79-L79 -> 1031.5683
A80: 河南 | B80: 0555 | C80: 洛阳正大食品有限公司 | D80: =_xlfn.XLOOKUP(B80,'3.屠宰能力表'!B:B,'3.屠宰能力表'!E:E) -> 3200 | E80: =_xlfn.XLOOKUP(B80,'4.分割能力表'!B:B,'4.分割能力表'!D:D) -> 960 | F80: =_xlfn.XLOOKUP(B80,'4.分割能力表'!B:B,'4.分割能力表'!E:E) -> 60000 | G80: 心血管 | H80: =_xlfn.XLOOKUP(G80,系数辅助表!$C:$C,系数辅助表!$D:$D) -> 0.00029015761 | J80: =$D80*H80*$D$1 -> 111.42052 | K80: =J80-L80 -> 111.42052
A81: 河南 | B81: 0555 | C81: 洛阳正大食品有限公司 | D81: =_xlfn.XLOOKUP(B81,'3.屠宰能力表'!B:B,'3.屠宰能力表'!E:E) -> 3200 | E81: =_xlfn.XLOOKUP(B81,'4.分割能力表'!B:B,'4.分割能力表'!D:D) -> 960 | F81: =_xlfn.XLOOKUP(B81,'4.分割能力表'!B:B,'4.分割能力表'!E:E) -> 60000 | G81: 杂油 | H81: =_xlfn.XLOOKUP(G81,系数辅助表!$C:$C,系数辅助表!$D:$D) -> 0.010245933 | J81: =$D81*H81*$D$1 -> 3934.4382 | K81: =J81-L81 -> 3934.4382
... A91: 河南 | B91: 0555 | C91: 洛阳正大食品有限公司 | D91: =_xlfn.XLOOKUP(B91,'3.屠宰能力表'!B:B,'3.屠宰能力表'!E:E) -> 3200 | E91: =_xlfn.XLOOKUP(B91,'4.分割能力表'!B:B,'4.分割能力表'!D:D) -> 960 | F91: =_xlfn.XLOOKUP(B91,'4.分割能力表'!B:B,'4.分割能力表'!E:E) -> 60000 | G91: 猪血 | H91: =_xlfn.XLOOKUP(G91,系数辅助表!$C:$C,系数辅助表!$D:$D) -> 0.02 | J91: =$D91*H91*$D$1 -> 7680 | K91: =J91-L91 -> 7680
A92: 河南 | B92: 0555 | C92: 洛阳正大食品有限公司 | D92: =_xlfn.XLOOKUP(B92,'3.屠宰能力表'!B:B,'3.屠宰能力表'!E:E) -> 3200 | E92: =_xlfn.XLOOKUP(B92,'4.分割能力表'!B:B,'4.分割能力表'!D:D) -> 960 | F92: =_xlfn.XLOOKUP(B92,'4.分割能力表'!B:B,'4.分割能力表'!E:E) -> 60000 | G92: 槽头 | H92: =_xlfn.XLOOKUP(G92,系数辅助表!$C:$C,系数辅助表!$D:$D) -> 0.018500772 | J92: =$E92*H92*$D$1 -> 2131.2889 | K92: =J92-L92 -> 378.94342 | L92: 1752.3455
A93: 河南 | B93: 0555 | C93: 洛阳正大食品有限公司 | D93: =_xlfn.XLOOKUP(B93,'3.屠宰能力表'!B:B,'3.屠宰能力表'!E:E) -> 3200 | E93: =_xlfn.XLOOKUP(B93,'4.分割能力表'!B:B,'4.分割能力表'!D:D) -> 960 | F93: =_xlfn.XLOOKUP(B93,'4.分割能力表'!B:B,'4.分割能力表'!E:E) -> 60000 | G93: 猪蹄 | H93: =_xlfn.XLOOKUP(G93,系数辅助表!$C:$C,系数辅助表!$D:$D) -> 0.018327695 | J93: =$E93*H93*$D$1 -> 2111.3505 | K93: =J93-L93 -> 375.39836 | L93: 1735.9521
A94: 河南 | B94: 0555 | C94: 洛阳正大食品有限公司 | D94: =_xlfn.XLOOKUP(B94,'3.屠宰能力表'!B:B,'3.屠宰能力表'!E:E) -> 3200 | E94: =_xlfn.XLOOKUP(B94,'4.分割能力表'!B:B,'4.分割能力表'!D:D) -> 960 | F94: =_xlfn.XLOOKUP(B94,'4.分割能力表'!B:B,'4.分割能力表'!E:E) -> 60000 | G94: 五花肉 | H94: =_xlfn.XLOOKUP(G94,系数辅助表!$C:$C,系数辅助表!$D:$D) -> 0.097050752 | J94: =$E94*H94*$D$1 -> 11180.247 | K94: =J94-L94 -> 3366.7088 | L94: 7813.5378
A95: 河南 | B95: 0555 | C95: 洛阳正大食品有限公司 | D95: =_xlfn.XLOOKUP(B95,'3.屠宰能力表'!B:B,'3.屠宰能力表'!E:E) -> 3200 | E95: =_xlfn.XLOOKUP(B95,'4.分割能力表'!B:B,'4.分割能力表'!D:D) -> 960 | F95: =_xlfn.XLOOKUP(B95,'4.分割能力表'!B:B,'4.分割能力表'!E:E) -> 60000 | G95: 大排肌肉 | H95: =_xlfn.XLOOKUP(G95,系数辅助表!$C:$C,系数辅助表!$D:$D) -> 0.046512517 | J95: =$E95*H95*$D$1 -> 5358.242 | K95: =J95-L95 -> 3979.3824 | L95: 1378.8596
A96: 河南 | B96: 0555 | C96: 洛阳正大食品有限公司 | D96: =_xlfn.XLOOKUP(B96,'3.屠宰能力表'!B:B,'3.屠宰能力表'!E:E) -> 3200 | E96: =_xlfn.XLOOKUP(B96,'4.分割能力表'!B:B,'4.分割能力表'!D:D) -> 960 | F96: =_xlfn.XLOOKUP(B96,'4.分割能力表'!B:B,'4.分割能力表'!E:E) -> 60000 | G96: 肋排 | H96: =_xlfn.XLOOKUP(G96,系数辅助表!$C:$C,系数辅助表!$D:$D) -> 0.028731738 | J96: =$E96*H96*$D$1 -> 3309.8962 | K96: =J96-L96 -> 588.49993 | L96: 2721.3962
A97: 河南 | B97: 0555 | C97: 洛阳正大食品有限公司 | D97: =_xlfn.XLOOKUP(B97,'3.屠宰能力表'!B:B,'3.屠宰能力表'!E:E) -> 3200 | E97: =_xlfn.XLOOKUP(B97,'4.分割能力表'!B:B,'4.分割能力表'!D:D) -> 960 | F97: =_xlfn.XLOOKUP(B97,'4.分割能力表'!B:B,'4.分割能力表'!E:E) -> 60000 | G97: 前排 | H97: =_xlfn.XLOOKUP(G97,系数辅助表!$C:$C,系数辅助表!$D:$D) -> 0.029020999 | J97: =$E97*H97*$D$1 -> 3343.2191 | K97: =J97-L97 -> 3343.2191 | L97: 0
A98: 河南 | B98: 0555 | C98: 洛阳正大食品有限公司 | D98: =_xlfn.XLOOKUP(B98,'3.屠宰能力表'!B:B,'3.屠宰能力表'!E:E) -> 3200 | E98: =_xlfn.XLOOKUP(B98,'4.分割能力表'!B:B,'4.分割能力表'!D:D) -> 960 | F98: =_xlfn.XLOOKUP(B98,'4.分割能力表'!B:B,'4.分割能力表'!E:E) -> 60000 | G98: 颈背肌肉 | H98: =_xlfn.XLOOKUP(G98,系数辅助表!$C:$C,系数辅助表!$D:$D) -> 0.033890751 | J98: =$E98*H98*$D$1 -> 3904.2145 | K98: =J98-L98 -> 0 | L98: =J98 -> 3904.2145
A99: 河南 | B99: 0555 | C99: 洛阳正大食品有限公司 | D99: =_xlfn.XLOOKUP(B99,'3.屠宰能力表'!B:B,'3.屠宰能力表'!E:E) -> 3200 | E99: =_xlfn.XLOOKUP(B99,'4.分割能力表'!B:B,'4.分割能力表'!D:D) -> 960 | F99: =_xlfn.XLOOKUP(B99,'4.分割能力表'!B:B,'4.分割能力表'!E:E) -> 60000 | G99: 小里脊 | H99: =_xlfn.XLOOKUP(G99,系数辅助表!$C:$C,系数辅助表!$D:$D) -> 0.0066683831 | J99: =$E99*H99*$D$1 -> 768.19773 | K99: =J99-L99 -> 0 | L99: =J99 -> 768.19773
A100: 河南 | B100: 0555 | C100: 洛阳正大食品有限公司 | D100: =_xlfn.XLOOKUP(B100,'3.屠宰能力表'!B:B,'3.屠宰能力表'!E:E) -> 3200 | E100: =_xlfn.XLOOKUP(B100,'4.分割能力表'!B:B,'4.分割能力表'!D:D) -> 960 | F100: =_xlfn.XLOOKUP(B100,'4.分割能力表'!B:B,'4.分割能力表'!E:E) -> 60000 | G100: 前腿肌肉 | H100: =_xlfn.XLOOKUP(G100,系数辅助表!$C:$C,系数辅助表!$D:$D) -> 0.073037535 | J100: =$E100*H100*$D$1 -> 8413.9241 | K100: =J100-L100 -> 0 | L100: =J100 -> 8413.9241
A101: 河南 | B101: 0555 | C101: 洛阳正大食品有限公司 | D101: =_xlfn.XLOOKUP(B101,'3.屠宰能力表'!B:B,'3.屠宰能力表'!E:E) -> 3200 | E101: =_xlfn.XLOOKUP(B101,'4.分割能力表'!B:B,'4.分割能力表'!D:D) -> 960 | F101: =_xlfn.XLOOKUP(B101,'4.分割能力表'!B:B,'4.分割能力表'!E:E) -> 60000 | G101: 后腿肌肉 | H101: =_xlfn.XLOOKUP(G101,系数辅助表!$C:$C,系数辅助表!$D:$D) -> 0.12205173 | J101: =$E101*H101*$D$1 -> 14060.359 | K101: =J101-L101 -> 5968.061 | L101: 8092.2977
A102: 河南 | B102: 0555 | C102: 洛阳正大食品有限公司 | D102: =_xlfn.XLOOKUP(B102,'3.屠宰能力表'!B:B,'3.屠宰能力表'!E:E) -> 3200 | E102: =_xlfn.XLOOKUP(B102,'4.分割能力表'!B:B,'4.分割能力表'!D:D) -> 960 | F102: =_xlfn.XLOOKUP(B102,'4.分割能力表'!B:B,'4.分割能力表'!E:E) -> 60000 | G102: 前肘 | H102: =_xlfn.XLOOKUP(G102,系数辅助表!$C:$C,系数辅助表!$D:$D) -> 0.019521507 | J102: =$E102*H102*$D$1 -> 2248.8776 | K102: =J102-L102 -> 399.85071 | L102: 1849.0269
A103: 河南 | B103: 0555 | C103: 洛阳正大食品有限公司 | D103: =_xlfn.XLOOKUP(B103,'3.屠宰能力表'!B:B,'3.屠宰能力表'!E:E) -> 3200 | E103: =_xlfn.XLOOKUP(B103,'4.分割能力表'!B:B,'4.分割能力表'!D:D) -> 960 | F103: =_xlfn.XLOOKUP(B103,'4.分割能力表'!B:B,'4.分割能力表'!E:E) -> 60000 | G103: 后肘 | H103: =_xlfn.XLOOKUP(G103,系数辅助表!$C:$C,系数辅助表!$D:$D) -> 0.02755221 | J103: =$E103*H103*$D$1 -> 3174.0145 | K103: =J103-L103 -> 564.34016 | L103: 2609.6744
A104: 河南 | B104: 0555 | C104: 洛阳正大食品有限公司 | D104: =_xlfn.XLOOKUP(B104,'3.屠宰能力表'!B:B,'3.屠宰能力表'!E:E) -> 3200 | E104: =_xlfn.XLOOKUP(B104,'4.分割能力表'!B:B,'4.分割能力表'!D:D) -> 960 | F104: =_xlfn.XLOOKUP(B104,'4.分割能力表'!B:B,'4.分割能力表'!E:E) -> 60000 | G104: 肥膘 | H104: =_xlfn.XLOOKUP(G104,系数辅助表!$C:$C,系数辅助表!$D:$D) -> 0.061357303 | J104: =$E104*H104*$D$1 -> 7068.3613 | K104: =J104-L104 -> 1256.7555 | L104: 5811.6058
A105: 河南 | B105: 0555 | C105: 洛阳正大食品有限公司 | D105: =_xlfn.XLOOKUP(B105,'3.屠宰能力表'!B:B,'3.屠宰能力表'!E:E) -> 3200 | E105: =_xlfn.XLOOKUP(B105,'4.分割能力表'!B:B,'4.分割能力表'!D:D) -> 960 | F105: =_xlfn.XLOOKUP(B105,'4.分割能力表'!B:B,'4.分割能力表'!E:E) -> 60000 | G105: 脊膘 | H105: =_xlfn.XLOOKUP(G105,系数辅助表!$C:$C,系数辅助表!$D:$D) -> 0.013016588 | J105: =$E105*H105*$D$1 -> 1499.511 | K105: =J105-L105 -> 1499.511 | L105: 0
A106: 河南 | B106: 0555 | C106: 洛阳正大食品有限公司 | D106: =_xlfn.XLOOKUP(B106,'3.屠宰能力表'!B:B,'3.屠宰能力表'!E:E) -> 3200 | E106: =_xlfn.XLOOKUP(B106,'4.分割能力表'!B:B,'4.分割能力表'!D:D) -> 960 | F106: =_xlfn.XLOOKUP(B106,'4.分割能力表'!B:B,'4.分割能力表'!E:E) -> 60000 | G106: 脊骨 | H106: =_xlfn.XLOOKUP(G106,系数辅助表!$C:$C,系数辅助表!$D:$D) -> 0.029868561 | J106: =$E106*H106*$D$1 -> 3440.8582 | K106: =J106-L106 -> 3440.8582 | L106: 0
A107: 河南 | B107: 0555 | C107: 洛阳正大食品有限公司 | D107: =_xlfn.XLOOKUP(B107,'3.屠宰能力表'!B:B,'3.屠宰能力表'!E:E) -> 3200 | E107: =_xlfn.XLOOKUP(B107,'4.分割能力表'!B:B,'4.分割能力表'!D:D) -> 960 | F107: =_xlfn.XLOOKUP(B107,'4.分割能力表'!B:B,'4.分割能力表'!E:E) -> 60000 | G107: 带肉后棒骨 | H107: =_xlfn.XLOOKUP(G107,系数辅助表!$C:$C,系数辅助表!$D:$D) -> 0.013175327 | J107: =$E107*H107*$D$1 -> 1517.7977 | K107: =J107-L107 -> 269.86461 | L107: 1247.9331
A108: 河南 | B108: 0555 | C108: 洛阳正大食品有限公司 | D108: =_xlfn.XLOOKUP(B108,'3.屠宰能力表'!B:B,'3.屠宰能力表'!E:E) -> 3200 | E108: =_xlfn.XLOOKUP(B108,'4.分割能力表'!B:B,'4.分割能力表'!D:D) -> 960 | F108: =_xlfn.XLOOKUP(B108,'4.分割能力表'!B:B,'4.分割能力表'!E:E) -> 60000 | G108: 带肉前棒骨 | H108: =_xlfn.XLOOKUP(G108,系数辅助表!$C:$C,系数辅助表!$D:$D) -> 0.0072226191 | J108: =$E108*H108*$D$1 -> 832.04572 | K108: =J108-L108 -> 832.04572 | L108: 0
A109: 河南 | B109: 0555 | C109: 洛阳正大食品有限公司 | D109: =_xlfn.XLOOKUP(B109,'3.屠宰能力表'!B:B,'3.屠宰能力表'!E:E) -> 3200 | E109: =_xlfn.XLOOKUP(B109,'4.分割能力表'!B:B,'4.分割能力表'!D:D) -> 960 | F109: =_xlfn.XLOOKUP(B109,'4.分割能力表'!B:B,'4.分割能力表'!E:E) -> 60000 | G109: 尾叉骨 | H109: =_xlfn.XLOOKUP(G109,系数辅助表!$C:$C,系数辅助表!$D:$D) -> 0.023493354 | J109: =$E109*H109*$D$1 -> 2706.4344 | K109: =J109-L109 -> 2706.4344 | L109: 0
A110: 河南 | B110: 0555 | C110: 洛阳正大食品有限公司 | D110: =_xlfn.XLOOKUP(B110,'3.屠宰能力表'!B:B,'3.屠宰能力表'!E:E) -> 3200 | E110: =_xlfn.XLOOKUP(B110,'4.分割能力表'!B:B,'4.分割能力表'!D:D) -> 960 | F110: =_xlfn.XLOOKUP(B110,'4.分割能力表'!B:B,'4.分割能力表'!E:E) -> 60000 | G110: 扇骨 | H110: =_xlfn.XLOOKUP(G110,系数辅助表!$C:$C,系数辅助表!$D:$D) -> 0.0098418107 | J110: =$E110*H110*$D$1 -> 1133.7766 | K110: =J110-L110 -> 1133.7766 | L110: 0
A111: 河南 | B111: 0555 | C111: 洛阳正大食品有限公司 | D111: =_xlfn.XLOOKUP(B111,'3.屠宰能力表'!B:B,'3.屠宰能力表'!E:E) -> 3200 | E111: =_xlfn.XLOOKUP(B111,'4.分割能力表'!B:B,'4.分割能力表'!D:D) -> 960 | F111: =_xlfn.XLOOKUP(B111,'4.分割能力表'!B:B,'4.分割能力表'!E:E) -> 60000 | G111: 颈骨 | H111: =_xlfn.XLOOKUP(G111,系数辅助表!$C:$C,系数辅助表!$D:$D) -> 0.0069845108 | J111: =$E111*H111*$D$1 -> 804.61564 | K111: =J111-L111 -> 804.61564 | L111: 0
A112: 河南 | B112: 0555 | C112: 洛阳正大食品有限公司 | D112: =_xlfn.XLOOKUP(B112,'3.屠宰能力表'!B:B,'3.屠宰能力表'!E:E) -> 3200 | E112: =_xlfn.XLOOKUP(B112,'4.分割能力表'!B:B,'4.分割能力表'!D:D) -> 960 | F112: =_xlfn.XLOOKUP(B112,'4.分割能力表'!B:B,'4.分割能力表'!E:E) -> 60000 | G112: 杂骨 | H112: =_xlfn.XLOOKUP(G112,系数辅助表!$C:$C,系数辅助表!$D:$D) -> 0.0022223443 | J112: =$E112*H112*$D$1 -> 256.01407 | K112: =J112-L112 -> 256.01407 | L112: 0
... A117: 河南 | B117: 0555 | C117: 洛阳正大食品有限公司 | D117: =_xlfn.XLOOKUP(B117,'3.屠宰能力表'!B:B,'3.屠宰能力表'!E:E) -> 3200 | E117: =_xlfn.XLOOKUP(B117,'4.分割能力表'!B:B,'4.分割能力表'!D:D) -> 960 | F117: =_xlfn.XLOOKUP(B117,'4.分割能力表'!B:B,'4.分割能力表'!E:E) -> 60000 | G117: 碎皮 | H117: =_xlfn.XLOOKUP(G117,系数辅助表!$C:$C,系数辅助表!$D:$D) -> 0.0014286499 | J117: =$E117*H117*$D$1 -> 164.58047 | K117: =J117-L117 -> 164.58047 | L117: 0
A118: 河南 | B118: 0555 | C118: 洛阳正大食品有限公司 | D118: =_xlfn.XLOOKUP(B118,'3.屠宰能力表'!B:B,'3.屠宰能力表'!E:E) -> 3200 | E118: =_xlfn.XLOOKUP(B118,'4.分割能力表'!B:B,'4.分割能力表'!D:D) -> 960 | F118: =_xlfn.XLOOKUP(B118,'4.分割能力表'!B:B,'4.分割能力表'!E:E) -> 60000 | G118: 五花肉-冷冻 | J118: =IFERROR(INDEX($L:$L,MATCH(SUBSTITUTE(G118,"-冷冻",""),$G:$G,0)),"") -> 9376.2454
A119: 河南 | B119: 0555 | C119: 洛阳正大食品有限公司 | D119: =_xlfn.XLOOKUP(B119,'3.屠宰能力表'!B:B,'3.屠宰能力表'!E:E) -> 3200 | E119: =_xlfn.XLOOKUP(B119,'4.分割能力表'!B:B,'4.分割能力表'!D:D) -> 960 | F119: =_xlfn.XLOOKUP(B119,'4.分割能力表'!B:B,'4.分割能力表'!E:E) -> 60000 | G119: 大排肌肉-冷冻 | J119: =IFERROR(INDEX($L:$L,MATCH(SUBSTITUTE(G119,"-冷冻",""),$G:$G,0)),"") -> 1654.6315
A120: 河南 | B120: 0555 | C120: 洛阳正大食品有限公司 | D120: =_xlfn.XLOOKUP(B120,'3.屠宰能力表'!B:B,'3.屠宰能力表'!E:E) -> 3200 | E120: =_xlfn.XLOOKUP(B120,'4.分割能力表'!B:B,'4.分割能力表'!D:D) -> 960 | F120: =_xlfn.XLOOKUP(B120,'4.分割能力表'!B:B,'4.分割能力表'!E:E) -> 60000 | G120: 肋排-冷冻 | J120: =IFERROR(INDEX($L:$L,MATCH(SUBSTITUTE(G120,"-冷冻",""),$G:$G,0)),"") -> 3265.6755
A121: 河南 | B121: 0555 | C121: 洛阳正大食品有限公司 | D121: =_xlfn.XLOOKUP(B121,'3.屠宰能力表'!B:B,'3.屠宰能力表'!E:E) -> 3200 | E121: =_xlfn.XLOOKUP(B121,'4.分割能力表'!B:B,'4.分割能力表'!D:D) -> 960 | F121: =_xlfn.XLOOKUP(B121,'4.分割能力表'!B:B,'4.分割能力表'!E:E) -> 60000 | G121: 颈背肌肉-冷冻 | J121: =IFERROR(INDEX($L:$L,MATCH(SUBSTITUTE(G121,"-冷冻",""),$G:$G,0)),"") -> 5350.4416
A122: 河南 | B122: 0555 | C122: 洛阳正大食品有限公司 | D122: =_xlfn.XLOOKUP(B122,'3.屠宰能力表'!B:B,'3.屠宰能力表'!E:E) -> 3200 | E122: =_xlfn.XLOOKUP(B122,'4.分割能力表'!B:B,'4.分割能力表'!D:D) -> 960 | F122: =_xlfn.XLOOKUP(B122,'4.分割能力表'!B:B,'4.分割能力表'!E:E) -> 60000 | G122: 小里脊-冷冻 | J122: =IFERROR(INDEX($L:$L,MATCH(SUBSTITUTE(G122,"-冷冻",""),$G:$G,0)),"") -> 1280.3296
A123: 河南 | B123: 0555 | C123: 洛阳正大食品有限公司 | D123: =_xlfn.XLOOKUP(B123,'3.屠宰能力表'!B:B,'3.屠宰能力表'!E:E) -> 3200 | E123: =_xlfn.XLOOKUP(B123,'4.分割能力表'!B:B,'4.分割能力表'!D:D) -> 960 | F123: =_xlfn.XLOOKUP(B123,'4.分割能力表'!B:B,'4.分割能力表'!E:E) -> 60000 | G123: 前腿肌肉-冷冻 | J123: =IFERROR(INDEX($L:$L,MATCH(SUBSTITUTE(G123,"-冷冻",""),$G:$G,0)),"") -> 12463.266
A124: 河南 | B124: 0555 | C124: 洛阳正大食品有限公司 | D124: =_xlfn.XLOOKUP(B124,'3.屠宰能力表'!B:B,'3.屠宰能力表'!E:E) -> 3200 | E124: =_xlfn.XLOOKUP(B124,'4.分割能力表'!B:B,'4.分割能力表'!D:D) -> 960 | F124: =_xlfn.XLOOKUP(B124,'4.分割能力表'!B:B,'4.分割能力表'!E:E) -> 60000 | G124: 后腿肌肉-冷冻 | J124: =IFERROR(INDEX($L:$L,MATCH(SUBSTITUTE(G124,"-冷冻",""),$G:$G,0)),"") -> 9710.7573
A125: 河南 | B125: 0555 | C125: 洛阳正大食品有限公司 | D125: =_xlfn.XLOOKUP(B125,'3.屠宰能力表'!B:B,'3.屠宰能力表'!E:E) -> 3200 | E125: =_xlfn.XLOOKUP(B125,'4.分割能力表'!B:B,'4.分割能力表'!D:D) -> 960 | F125: =_xlfn.XLOOKUP(B125,'4.分割能力表'!B:B,'4.分割能力表'!E:E) -> 60000 | G125: 前肘-冷冻 | J125: =IFERROR(INDEX($L:$L,MATCH(SUBSTITUTE(G125,"-冷冻",""),$G:$G,0)),"") -> 2218.8323
A126: 河南 | B126: 0555 | C126: 洛阳正大食品有限公司 | D126: =_xlfn.XLOOKUP(B126,'3.屠宰能力表'!B:B,'3.屠宰能力表'!E:E) -> 3200 | E126: =_xlfn.XLOOKUP(B126,'4.分割能力表'!B:B,'4.分割能力表'!D:D) -> 960 | F126: =_xlfn.XLOOKUP(B126,'4.分割能力表'!B:B,'4.分割能力表'!E:E) -> 60000 | G126: 后肘-冷冻 | J126: =IFERROR(INDEX($L:$L,MATCH(SUBSTITUTE(G126,"-冷冻",""),$G:$G,0)),"") -> 3131.6093
A127: 河南 | B127: 0555 | C127: 洛阳正大食品有限公司 | D127: =_xlfn.XLOOKUP(B127,'3.屠宰能力表'!B:B,'3.屠宰能力表'!E:E) -> 3200 | E127: =_xlfn.XLOOKUP(B127,'4.分割能力表'!B:B,'4.分割能力表'!D:D) -> 960 | F127: =_xlfn.XLOOKUP(B127,'4.分割能力表'!B:B,'4.分割能力表'!E:E) -> 60000 | G127: 肥膘-冷冻 | J127: =IFERROR(INDEX($L:$L,MATCH(SUBSTITUTE(G127,"-冷冻",""),$G:$G,0)),"") -> 6973.927
A128: 河南 | B128: 0555 | C128: 洛阳正大食品有限公司 | D128: =_xlfn.XLOOKUP(B128,'3.屠宰能力表'!B:B,'3.屠宰能力表'!E:E) -> 3200 | E128: =_xlfn.XLOOKUP(B128,'4.分割能力表'!B:B,'4.分割能力表'!D:D) -> 960 | F128: =_xlfn.XLOOKUP(B128,'4.分割能力表'!B:B,'4.分割能力表'!E:E) -> 60000 | G128: 带肉后棒骨-冷冻 | J128: =IFERROR(INDEX($L:$L,MATCH(SUBSTITUTE(G128,"-冷冻",""),$G:$G,0)),"") -> 1497.5197
A129: 河南 | B129: 0555 | C129: 洛阳正大食品有限公司 | D129: =_xlfn.XLOOKUP(B129,'3.屠宰能力表'!B:B,'3.屠宰能力表'!E:E) -> 3200 | E129: =_xlfn.XLOOKUP(B129,'4.分割能力表'!B:B,'4.分割能力表'!D:D) -> 960 | F129: =_xlfn.XLOOKUP(B129,'4.分割能力表'!B:B,'4.分割能力表'!E:E) -> 60000 | G129: 精碎肉-冷冻 | J129: =IFERROR(INDEX($L:$L,MATCH(SUBSTITUTE(G129,"-冷冻",""),$G:$G,0)),"") -> 1173.5236
... A133: 河南 | B133: 0555 | C133: 洛阳正大食品有限公司 | D133: =_xlfn.XLOOKUP(B133,'3.屠宰能力表'!B:B,'3.屠宰能力表'!E:E) -> 3200 | E133: =_xlfn.XLOOKUP(B133,'4.分割能力表'!B:B,'4.分割能力表'!D:D) -> 960 | F133: =_xlfn.XLOOKUP(B133,'4.分割能力表'!B:B,'4.分割能力表'!E:E) -> 60000 | G133: 槽头-冷冻 | J133: =IFERROR(INDEX($L:$L,MATCH(SUBSTITUTE(G133,"-冷冻",""),$G:$G,0)),"") -> 2102.8146
A134: 江苏 | B134: 0476 | C134: 正大食品（徐州）有限公司 | D134: =_xlfn.XLOOKUP(B134,'3.屠宰能力表'!B:B,'3.屠宰能力表'!E:E) -> 3200 | E134: =_xlfn.XLOOKUP(B134,'4.分割能力表'!B:B,'4.分割能力表'!D:D) -> 1600 | F134: =_xlfn.XLOOKUP(B134,'4.分割能力表'!B:B,'4.分割能力表'!E:E) -> 72000 | G134: 白条 | H134: =_xlfn.XLOOKUP(G134,系数辅助表!$C:$C,系数辅助表!$D:$D) -> 0.715 | J134: =(D134-E134)*H134*$D$1 -> 137280 | K134: =J134-L134 -> 137280
...
